Workbook
Name A1VerVal: Drops!$B$27
Name BusInfoArray: 'Business Information'!$A$4:$E$38
Name CompanyHashSIG: Drops!$B$36
Name CompanyName: Drops!$B$34
Name CompanyNameFlag: Drops!$B$35
Name CurrentVersionSIG: Drops!$B$25
Name FullResponses: Full!$A$2:$M$1026
Name JumpArray: Drops!$F$26:$F$44
Name JumpSelection: Drops!$F$45
Name OutputArray: Drops!$M$2:$U$5758
Name ServiceSelection: Drops!$M$2:$N$5758

Sheet Copyright
B2: 2021 SHARED ASSESSMENTS STANDARDIZED INFORMATION GATHERING (SIG) QUESTIONNAIRE
B3: ="Version: "&CurrentVersionSIG&" - Licensed to: "&CompanyName -> Version: 2021.02 - Licensed to: Seismic Software
B4: The SIG Questionnaire Tools are a comprehensive questionnaire management interface that lets you build, customize, store and automatically analyze SIG questionnaires and their associated evidence requirements all in one place. It is built on a holistic set of industry best practices for gathering and assessing 18 critical control domains including information technology, cybersecurity, privacy, resiliency and compliance risks and their corresponding controls. Service providers can also use SIG Questionnaires to reduce assessment fatigue by proactively supplying their own SIGs to Outsourcers.
B5: © 2020, 2021 The Santa Fe Group, Shared Assessments Program. All rights reserved.
B6: Documents created under the Shared Assessments Program may be downloaded from the official Shared Assessments Program website at SharedAssessments.org.
B7: While retaining copyrights, the Shared Assessments Program makes specific documents available via license for assessments and other uses. Individuals and organizations should review the terms of use prior to downloading, copying, using or modifying Shared Assessment Program documents.
B8: This notice must be included on any copy of the Shared Assessments Program documents, excluding Assessors' or consultants' reports.
B9: The Shared Assessments Program is administered by The Santa Fe Group at Santa-Fe-Group.com.
B10: Please refer to the support documentation provided on how to use this workbook. If you have additional questions or issues, please go to SharedAssessments.org/tools-support/.
B11: To learn more about our education offerings or sign up for one of our workshops please go to SharedAssessments.org.
B12: If you are interested in learning more about the Shared Assessments Program and would like us to contact you, email us at info@SharedAssessments.org.
B13: Terms of Use
B14: 2021 SHARED ASSESSMENTS STANDARDIZED INFORMATION GATHERING (SIG) QUESTIONNAIRE TOOLS (2021 SIG)
B15: The Shared Assessments Program ("Program") maintains, promotes and facilitates the use of the Standardized Information Gathering ("SIG") questionnaire documents and other Program resource documents.
... B22: THE SHARED ASSESSMENTS PROGRAM DOCUMENTS ARE PROVIDED "AS IS" AND ANY EXPRESSED OR IMPLIED WARRANTIES, INCLUDING, BUT NOT LIMITED TO, THE IMPLIED WARRANTIES OF MERCHANTABILITY AND FITNESS FOR A PARTICULAR PURPOSE, ARE DISCLAIMED. IN NO EVENT SHALL THE SANTA FE GROUP, OR THE SHARED ASSESSMENTS PROGRAM, ITS SPONSORS OR PROGRAM MEMBERS BE LIABLE FOR ANY DIRECT, INDIRECT, INCIDENTAL, SPECIAL, EXEMPLARY, OR CONSEQUENTIAL DAMAGES (INCLUDING, BUT NOT LIMITED TO, PROCUREMENT OF SUBSTITUTE GOODS OR SERVICES; LOSS OF USE, DATA, OR PROFITS; OR BUSINESS INTERRUPTION) HOWEVER CAUSED AND ON ANY THEORY OF LIABILITY, WHETHER IN CONTRACT, STRICT LIABILITY, OR TORT (INCLUDING NEGLIGENCE OR OTHERWISE) ARISING IN ANY WAY OUT OF THE USE OF THE SHARED ASSESSMENTS PROGRAM DOCUMENTS, EVEN IF ADVISED OF THE POSSIBILITY OF SUCH DAMAGE.

Sheet Instructions
B2: 2021 SHARED ASSESSMENTS STANDARDIZED INFORMATION GATHERING (SIG) QUESTIONNAIRE
B3: ="Version: "&CurrentVersionSIG&" Licensed to: "&CompanyName -> Version: 2021.02 Licensed to: Seismic Software
B4: ASSESSEE INSTRUCTIONS FOR SIG QUESTIONNAIRE COMPLETION: | D4: ISSUER/OUTSOURCER ADDITIONAL INFORMATION
B5: Before You Start: Review the instructions provided by your Issuer/Outsourcer on how to answer the SIG. Issuer/Outsourcer should provide you with the scope of services for which to provide responses. The SIG is complex. If you did not receive instructions from your Issuer/Outsourcer it is recommended that you contact them before you start and seek guidance on how to proceed with the SIG to meet their needs.
B6: Don't be overwhelmed by the volume of questions. Some are filtering questions to remove out of scope services or have a question hierarchy to reduce the need to complete items that are NA. Primary or ‘parent’ questions, indicated in bold, are followed by numbered sub or ‘child’ questions. If a parent question is answered Yes, child questions will display. There can be up to four generations of questions below a parent question.
B7: NOTE: To display all of the questions (parent, child, grandchild, etc.) disable macros when opening the file or select Disable from the Tab Automation dropdown on each risk domain tab.
B8: Steps for each SIG Worksheet:
B9: 1) Complete the Business Information tab: Open the tab and complete all of the grey fields. It is recommended that you provide as much detail as possible in your responses.
B10: 2) Review and Complete the Documentation tab: Open the Documentation tab. Review the list of documents and compile all of the appropriate corporate policies and processes as listed on this tab. List the document’s name in the gray field to correspond to the appropriate document list. This will allow the Outsourcer to identify the documents provided along with the completed SIG. Compile the documentation requested on the Documentation tab and update the tab with the documents provided.
B11: 3) Answer the Questions in each Risk Domain tab:
B12: • The background color will change depending on the response provided.
B13: • If Excel macros are enabled, then Child questions will either be displayed if the response is Yes or hidden if the response is No or N/A.
B14: • If the question is a Parent question and the response is No or N/ A, then the background will change to the associated color for all Child and Grandchild questions of that Parent.
B15: • When selecting an N/A response, commentary must be entered in the Additional Information field explaining why that question is not applicable.
B16: • The progress bar at the top of the page shows the percentage of questions completed for a given tab.
... B18: 5) Sending the Completed SIG: Once all of the answers have been entered, send the completed SIG and all policy/process documents compiled in Step 1-3 to the Outsourcer according to the instructions you have been provided.
B19: Question Numbering | D19: Glossary:
B20: There may be gaps in the question numbering depending on how the Issuer/Outsourcer scoped the SIG. | D20: For definitions of terms within this document, please refer to the following link: https://sharedassessments.org/glossary

Sheet Dashboard
B2: Dashboard | G2: 1
B3: The Dashboard provides you with a quick and easy reference to determine the percentage of completion for the required sections of the SIG. As questions are answered, either directly or by being pre-filled, the Dashboard will track the completion percentage of each section. | G3: 1
B4: Tabs | C4: % Comp | D4: Please wait for the SIG to update... | E4: Response Cell Background Color Coding (All tabs) | F4: Resp | G4: 1
B5: Copyright | C5: N/A | E5: Response Required (cells with a gray background are editable) | G5: 1
B6: Instructions | C6: N/A | E6: Yes Response | F6: Yes | G6: 1
B7: Business Information | C7: ='Business Information'!C2 -> 1 | E7: No Response | F7: No | G7: 1
B8: Documentation | C8: N/A | E8: N/A Response | F8: N/A | G8: 1
B9: A. Risk Assessment and Treatment | C9: =Drops!H3 | G9: =IF(Drops!I3=TRUE,1,0) -> 0
B10: B. Security Policy | C10: =Drops!H4 | G10: =IF(Drops!I4=TRUE,1,0) -> 0
B11: C. Organizational Security | C11: =Drops!H5 | D11: Response Type | G11: =IF(Drops!I5=TRUE,1,0) -> 0
B12: D. Asset and Information Management | C12: =Drops!H6 | D12: Binary | G12: =IF(Drops!I6=TRUE,1,0) -> 0
B13: E. Human Resource Security | C13: =Drops!H7 | G13: =IF(Drops!I7=TRUE,1,0) -> 0
B14: F. Physical and Environmental Security | C14: =Drops!H8 | G14: =IF(Drops!I8=TRUE,1,0) -> 0
B15: G. IT Operations Management | C15: =Drops!H9 | G15: =IF(Drops!I9=TRUE,1,0) -> 0
B16: H. Access Control | C16: =Drops!H10 | G16: =IF(Drops!I10=TRUE,1,0) -> 0
B17: I. Application Security | C17: =Drops!H11 | G17: =IF(Drops!I11=TRUE,1,0) -> 0
B18: J. Incident Event and Communications Management | C18: =Drops!H12 | G18: =IF(Drops!I12=TRUE,1,0) -> 0
B19: K. Business Resiliency | C19: =Drops!H13 | G19: =IF(Drops!I13=TRUE,1,0) -> 0
B20: L. Compliance | C20: =Drops!H14 | G20: =IF(Drops!I14=TRUE,1,0) -> 0
B21: M. End User Device Security | C21: =Drops!H15 | G21: =IF(Drops!I15=TRUE,1,0) -> 0
B22: N. Network Security | C22: =Drops!H16 | G22: =IF(Drops!I16=TRUE,1,0) -> 0
B23: P. Privacy | C23: =Drops!H17 | G23: =IF(Drops!I17=TRUE,1,0) -> 0
B24: T. Threat Management | C24: =Drops!H18 | G24: =IF(Drops!I18=TRUE,1,0) -> 0
... B28: SIG 2021 | C28: =Drops!H22 -> 1 | G28: =IF(Drops!I22=TRUE,1,0) -> 1
B29: Glossary | C29: N/A | G29: 1
B30: Formula Notes | C30: N/A | G30: 1
B31: Full | C31: N/A | G31: =IF(Drops!I23=TRUE,1,0) -> 1
B32: SIG Total | C32: =Drops!H24 -> 1 | G32: 1

Sheet Business Information
A1: Serial No | B1: Business Information | D1: Count | E1: Resp
B2: Progress: | C2: =IF(D3=0,"0%",D3/D2) -> 1 | D2: =COUNTA(D4:D61) -> 47
B3: Question/Request | D3: =COUNTIF(D4:D61,1) -> 47
A4: 2891 | B4: Assessee Name | C4: Information Security | D4: =COUNTA(C4) -> 1 | E4: =IF(C4="Yes",1,IF(C4="No",2,IF(C4="N/A",3,0))) -> 0
A5: 2892 | B5: Assessee Job Title | C5: Sr. Director of Information Security | D5: =COUNTA(C5) -> 1 | E5: =IF(C5="Yes",1,IF(C5="No",2,IF(C5="N/A",3,0))) -> 0
A6: 2893 | B6: Assessee Contact Information | C6: security@seismic.com | D6: =COUNTA(C6) -> 1 | E6: =IF(C6="Yes",1,IF(C6="No",2,IF(C6="N/A",3,0))) -> 0
A7: 4616 | B7: Names and titles/functions of individuals who contributed to this questionnaire | C7: Same as above | D7: =COUNTA(C7) -> 1 | E7: =IF(C7="Yes",1,IF(C7="No",2,IF(C7="N/A",3,0))) -> 0
A8: 2894 | B8: Date of Response | C8: 44454 | D8: =COUNTA(C8) -> 1 | E8: =IF(C8="Yes",1,IF(C8="No",2,IF(C8="N/A",3,0))) -> 0
B9: Company Profile | E9: =IF(C9="Yes",1,IF(C9="No",2,IF(C9="N/A",3,0))) -> 0
A10: 2896 | B10: Name of the holding or parent company | C10: Seismic Software | D10: =COUNTA(C10) -> 1 | E10: =IF(C10="Yes",1,IF(C10="No",2,IF(C10="N/A",3,0))) -> 0
A11: 2897 | B11: Company/business name | C11: Lessonly by Seismic | D11: =COUNTA(C11) -> 1 | E11: =IF(C11="Yes",1,IF(C11="No",2,IF(C11="N/A",3,0))) -> 0
A12: 2898 | B12: Publicly or privately held company | C12: Privately held | D12: =COUNTA(C12) -> 1 | E12: =IF(C12="Yes",1,IF(C12="No",2,IF(C12="N/A",3,0))) -> 0
A13: 2899 | B13: If public, what is the name of the Exchange | D13: =IF(C12="Privately held",1,COUNTA(C13)) -> 1 | E13: =IF(C13="Yes",1,IF(C13="No",2,IF(C13="N/A",3,0))) -> 0
A14: 2900 | B14: If public, what is the trading symbol | D14: =IF(C12="Privately held",1,COUNTA(C14)) -> 1 | E14: =IF(C14="Yes",1,IF(C14="No",2,IF(C14="N/A",3,0))) -> 0
A15: 2901 | B15: Type of legal entity and state of incorporation | C15: C-Corp, Delaware | D15: =COUNTA(C15) -> 1 | E15: =IF(C15="Yes",1,IF(C15="No",2,IF(C15="N/A",3,0))) -> 0
A16: 2902 | B16: How long has the company been in business | C16: Since 2014 | D16: =COUNTA(C16) -> 1 | E16: =IF(C16="Yes",1,IF(C16="No",2,IF(C16="N/A",3,0))) -> 0
A17: 2903 | B17: Are there any material claims or judgments against the company | C17: No | D17: =COUNTA(C17) -> 1 | E17: =IF(C17="Yes",1,IF(C17="No",2,IF(C17="N/A",3,0))) -> 2
A18: 2904 | B18: If yes, describe the impact it may have on the services in scope of this document | D18: =IF(C17="No",1,COUNTA(C18)) -> 1 | E18: =IF(C18="Yes",1,IF(C18="No",2,IF(C18="N/A",3,0))) -> 0
A19: 4000 | B19: Has your company suffered a data loss or security breach within the last 3 years | C19: No | D19: =COUNTA(C19) -> 1 | E19: =IF(C19="Yes",1,IF(C19="No",2,IF(C19="N/A",3,0))) -> 2
A20: 4001 | B20: If yes, please describe the loss or breach | D20: =IF(C19="No",1,COUNTA(C20)) -> 1 | E20: =IF(C20="Yes",1,IF(C20="No",2,IF(C20="N/A",3,0))) -> 0
A21: 4002 | B21: Has any of your Third Party Vendors suffered a data loss or security breach within the last 3 years | C21: No | D21: =COUNTA(C21) -> 1 | E21: =IF(C21="Yes",1,IF(C21="No",2,IF(C21="N/A",3,0))) -> 2
A22: 4003 | B22: If yes, please describe the loss or breach | C22: Not to our knowledge | D22: =IF(C21="No",1,COUNTA(C22)) -> 1 | E22: =IF(C22="Yes",1,IF(C22="No",2,IF(C22="N/A",3,0))) -> 0
B23: Scope | E23: =IF(C23="Yes",1,IF(C23="No",2,IF(C23="N/A",3,0))) -> 0
A24: 2911 | B24: Are the answers in this questionnaire for only one facility or geographic location If yes, provide description of physical location (address, city, state, country) | C24: No | D24: =COUNTA(C24) -> 1 | E24: =IF(C24="Yes",1,IF(C24="No",2,IF(C24="N/A",3,0))) -> 2
A25: 2912 | B25: Backup site physical address | C25: AWS East-1 | D25: =COUNTA(C25) -> 1 | E25: =IF(C25="Yes",1,IF(C25="No",2,IF(C25="N/A",3,0))) -> 0
A26: 2913 | B26: Any additional locations where Scoped Systems and Data are stored | C26: No | D26: =COUNTA(C26) -> 1 | E26: =IF(C26="Yes",1,IF(C26="No",2,IF(C26="N/A",3,0))) -> 2
A27: 2914 | B27: If yes, provide each location (address, city, state, country) | D27: =IF(C26="No",1,COUNTA(C27)) -> 1 | E27: =IF(C27="Yes",1,IF(C27="No",2,IF(C27="N/A",3,0))) -> 0
A28: 2973 | B28: Are the answers to this questionnaire for only one specific type of service If yes, describe the service | C28: SaaS | D28: =COUNTA(C28) -> 1 | E28: =IF(C28="Yes",1,IF(C28="No",2,IF(C28="N/A",3,0))) -> 0
A29: 4617 | B29: Are software applications provided | C29: Yes | D29: =COUNTA(C29) -> 1 | E29: =IF(C29="Yes",1,IF(C29="No",2,IF(C29="N/A",3,0))) -> 1
A30: 3992 | B30: List the applications provided that are in scope | C30: Lessonly by Seismic | D30: =IF($C$29="No",1,COUNTA(C30)) -> 1 | E30: =IF(C30="Yes",1,IF(C30="No",2,IF(C30="N/A",3,0))) -> 0
A31: 3993 | B31: Identify the applications which are covered by the secure software development lifecycle | C31: Lessonly by Seismic | D31: =IF($C$29="No",1,COUNTA(C31)) -> 1 | E31: =IF(C31="Yes",1,IF(C31="No",2,IF(C31="N/A",3,0))) -> 0
A32: 3994 | B32: What type of software is being provided, select all that apply from the list below: | E32: =IF(C32="Yes",1,IF(C32="No",2,IF(C32="N/A",3,0))) -> 0
A33: 3995 | B33: Commercial Off-The-Shelf (COTS) | C33: No | D33: =IF($C$29="No",1,COUNTA(C33)) -> 1 | E33: =IF(C33="Yes",1,IF(C33="No",2,IF(C33="N/A",3,0))) -> 2
A34: 3996 | B34: Custom Developed | C34: No | D34: =IF($C$29="No",1,COUNTA(C34)) -> 1 | E34: =IF(C34="Yes",1,IF(C34="No",2,IF(C34="N/A",3,0))) -> 2
A35: 3997 | B35: Cloud | C35: Yes | D35: =IF($C$29="No",1,COUNTA(C35)) -> 1 | E35: =IF(C35="Yes",1,IF(C35="No",2,IF(C35="N/A",3,0))) -> 1
A36: 3998 | B36: Mobile | C36: No | D36: =IF($C$29="No",1,COUNTA(C36)) -> 1 | E36: =IF(C36="Yes",1,IF(C36="No",2,IF(C36="N/A",3,0))) -> 2
A37: 4004 | B37: Open Source Software | C37: No | D37: =IF($C$29="No",1,COUNTA(C37)) -> 1 | E37: =IF(C37="Yes",1,IF(C37="No",2,IF(C37="N/A",3,0))) -> 2
A38: 3999 | B38: Other | C38: No | D38: =IF($C$29="No",1,COUNTA(C38)) -> 1 | E38: =IF(C38="Yes",1,IF(C38="No",2,IF(C38="N/A",3,0))) -> 2
A39: 4410 | B39: Does your company require approval prior to submitting the responses and documentation associated with this document | C39: No | D39: =COUNTA(C39) -> 1
A40: 4411 | B40: If yes, describe your approval process and the individual who approves the submission | D40: =IF($C$39="No",1,COUNTA(C40)) -> 1
A41: 4618 | B41: Does this SIG include Cloud Hosting services | C41: Yes | D41: =COUNTA(C41) -> 1
A42: 4619 | B42: What service hosting models are provided as part of this service:
A43: 4620 | B43: Data center: single tenancy | C43: No | D43: =IF($C$41="No",1,COUNTA(C43)) -> 1
A44: 4621 | B44: Co-location: dedicated server | C44: No | D44: =IF($C$41="No",1,COUNTA(C44)) -> 1
A45: 4622 | B45: Web Hosting | C45: No | D45: =IF($C$41="No",1,COUNTA(C45)) -> 1
A46: 4623 | B46: File Hosting | C46: No | D46: =IF($C$41="No",1,COUNTA(C46)) -> 1
A47: 4624 | B47: Continuous | C47: No | D47: =IF($C$41="No",1,COUNTA(C47)) -> 1
A48: 4625 | B48: Cloud Hosting: (eg, AWS, Azure, Google, etc) | C48: Yes | D48: =IF($C$41="No",1,COUNTA(C48)) -> 1
A49: 4615 | B49: What Cloud Hosting Tiers are provided as part of this service:
A50: 4626 | B50: Software as a Service (SaaS) | C50: Yes | D50: =IF($C$41="No",1,COUNTA(C50)) -> 1
A51: 4627 | B51: Infrastructure as a Service (IaaS) | C51: No | D51: =IF($C$41="No",1,COUNTA(C51)) -> 1
A52: 4628 | B52: What deployment models are provided (select all that apply):
A53: 4629 | B53: Private cloud | C53: Yes | D53: =IF($C$41="No",1,COUNTA(C53)) -> 1
A54: 4630 | B54: Public cloud | C54: Yes | D54: =IF($C$41="No",1,COUNTA(C54)) -> 1
A55: 4631 | B55: Community cloud | C55: No | D55: =IF($C$41="No",1,COUNTA(C55)) -> 1
A56: 4632 | B56: Hybrid cloud | C56: No | D56: =IF($C$41="No",1,COUNTA(C56)) -> 1

Sheet Documentation
A1: Serial No | B1: Documentation Use this section to request any specific documentation you want the Assessee to provide along with the SIG
A2: SN | B2: Document Request | C2: Domain | D2: SCA Reference | E2: Document Access | F2: Documentation Description
A3: 5660 | B3: Documentation that defines the Enterprise Risk Management program requirements (i.e., Enterprise risk governance plan, policies and procedures) | C3: A. Risk Assessment & Treatment | D3: A.1
A4: 5661 | B4: Documentation that defines the organization's risk assessment lifecycle. Inventory/register of applicable risks and controls included in the risk management program | C4: A. Risk Assessment & Treatment | D4: A.2
A5: 5662 | B5: Documentation that defines oversight functions and procedures accountable for compliance with legal, regulatory, and standards obligations | C5: A. Risk Assessment & Treatment | D5: A.3
A6: 5663 | B6: Documentation that defines the IT risk assessment process requirements for systems and critical business processes, including a list of critical business processes related to the services provided | C6: A. Risk Assessment & Treatment | D6: A.4
A7: 5664 | B7: Documentation that defines the organization's third party risk management program and assessment requirements e.g., policies, standards, procedures. Documentation and evidence of the structure and maintenance of the organization's third party inventory and vendor classification | C7: A. Risk Assessment & Treatment | D7: A.5
A8: 5665 | B8: Documentation that describes the organization's process for addressing security contract clauses within service provider agreements and provides evidence that the organization's required security requirements (e.g., standard provisions, model contracts, contract term database) have been included in its vendor contracting process. Documentation that defines the organization's guidelines and process for management and approval of exception handling for required contract terms | C8: A. Risk Assessment & Treatment | D8: A.6
A9: 5666 | B9: Documentation that defines the requirements for subcontractor selection and management | C9: A. Risk Assessment & Treatment | D9: A.7
A10: 5667 | B10: A list of the critical subcontractors and evidence of the execution of the standard contract provisions, master services agreements in place for identified critical subcontractor relationships that are required for the delivery of the services | C10: A. Risk Assessment & Treatment | D10: A.8
A11: 5668 | B11: Documentation that defines the requirements for the assessment process that is in place to manage information security of its subcontractors | C11: A. Risk Assessment & Treatment | D11: A.9
A12: 5669 | B12: A copy of the formal criteria and methodology used to identify the inherent risk associated to a subcontractor | C12: A. Risk Assessment & Treatment | D12: A.10
A13: 5670 | B13: Documentation that reflects the logging, tracking and risk rating of subcontractor issues | C13: A. Risk Assessment & Treatment | D13: A.11
A14: 2922 | B14: Documentation of the organization's information security policies | C14: B. Security Policy | D14: B.1
... A136: 5779 | B136: Documentation that defines the CSP's process for validating secure configurations and documentation of its operational practices that are being applied to its virtual host systems and hypervisors, pre and postproduction, including a sample of the applicable system log report | C136: V. Cloud Hosting | D136: V.3

Sheet SIG 2021
A1: =A1VerVal -> 18 | B1: SIG 2021 | E1: =" Scoped As: "&Drops!A24 -> Scoped As: SIG Core 2021 | H1: Jump To: | M1: Tot | N1: Ans | O1: aa023ad7efc04973ff784e5fb415cc33 | W1: Yes | X1: No | Y1: N/A | AA1: Enable | AB1: Disable | AM1: SME SIG
B2: Licensed to: Seismic Software | D2: Progress: | E2: =IF(N2=0,"0%",N2/M2) -> 1 | H2: Tab Automation: | I2: Enable | M2: =COUNTIF(L:L,">0") -> 1025 | N2: =COUNTIF(S:S,">0") -> 1025 | W2: 1 | X2: 2 | Y2: 3 | Z2: 4 | AA2: 5 | AB2: N/A
B3: Questionnaire Instructions: - For each question choose either Yes, No or N/A from the drop-down menu provided. If N/A is chosen, an explanation is recommended. Use the Additional Information field in column E to provide an explanation. - To display the entire contents of the tab, select the word "Disable" in the Tab Automation field at the top of the page. - There may be gaps in the question number sequence depending on how the outsourcer generated the SIG. MODIFICATION OF THIS DOCUMENT IS A VIOLATION OF THE COPYRIGHT AND MAY RESULT IN FINANCIAL PENALTY FOR YOU OR YOUR SERVICE PROVIDER | L3: Q Depth | M3: Scoping Level | N3: Maturity N/A | P3: Answer Calc | Q3: Jump Domain | R3: Jump Row | S3: Resp Calc | T3: Family Delta | U3: Tab | V3: L1 Calc | W3: L2 Calc | X3: L3 Calc | Y3: L4 Calc | Z3: L5 Calc | AA3: Child Filter | AB3: Bold Ques Text | AC3: L1 Res Carry | AD3: L2 Res Carry | AE3: L3 Res Carry | AF3: L4 Res Carry | AG3: L5 Res Carry | AH3: L1 Filter Calc | AI3: L2 Filter Calc | AJ3: L3 Filter Calc | AK3: L4 Filter Calc | AL3: L5 Filter Calc | AM3: This SIG is intended for internal use only. Do not distribute outside of the organization.
A4: Serial No | B4: Ques Num | C4: Question/Request | D4: Response | E4: Additional Information | F4: Maturity | G4: Category | H4: Sub-category | I4: SCA Reference | J4: ISO 27002:2013 Relevance | U4: =U5 -> A | V4: 1 | W4: 2 | X4: 3 | Y4: 4 | Z4: 5 | AC4: 1 | AD4: 2 | AE4: 3 | AF4: 4 | AG4: 5 | AH4: 1 | AI4: 2 | AJ4: 3 | AK4: 4 | AL4: 5 | AM4: Subject Matter Expert Name | AN4: Subject Matter Expert Notes | AO4: Optional Score
A5: 5643 | B5: A.1 | C5: Is there a formalized risk governance plan that defines the Enterprise Risk Management program requirements? | D5: Yes | E5: Seismic has an established Risk Governance Program based off ISO 27005 controls. The program is run by Seismic's internal Information Security team. Seismic performs Enterprise Risk Assessment at least annually and communicate risk findings to executive management. Where risks are identified, appropriate controls are established to remove or reduce the risk to an acceptable level. | G5: Enterprise Risk Management | H5: Risk Governance Plan | I5: A.1 Enterprise Risk Governance | J5: An organization's enterprise risk governance program should include a formal program that documents the organization's assets and threats and evaluates associated risks. | L5: 1 | M5: 2 | P5: =IF($L5="","",IF($D5="Yes",1,IF($D5="No",2,IF($D5="N/A",3,0)))) -> 1 | Q5: =IF(AND(Drops!$D$45>1,OR(U5<>U4,AND(ROW()=5,U4=U5))),VLOOKUP(U5,Drops!$D$26:$E$44,2,FALSE),"") -> A. Risk Management | R5: =IF(Q5<>"",ROW(),"") -> 5 | S5: =OFFSET(AC5,,L5-1) -> 1 | T5: =IF(OR(V5<>V4,U5<>U4,AND(V5<>V4,W5<>W4),AND(V5<>V4,W5<>W4,X5<>X4),AND(V5<>V4,W5<>W4,X5<>X4,Y5<>Y4),AND(V5<>V4,W5<>W4,X5<>X4,Y5<>Y4,Z5<>Z4),L5-L4>1),1,0) -> 0 | U5: A | V5: 1 | W5: 0 | X5: 0 | Y5: 0 | Z5: 0 | AA5: =IF(ROW()=5,1,IF(OR(AH5=1,P5>0,T5=1),1,IF(OR(AND(AH5=2,AI5=1),AND(AI5=2,AJ5=1),AND(AJ5=2,AK5=1),AND(AK5=2,AL5=1)),1,0))) -> 1 | AB5: =IF(L6>L5,1,0) -> 1 | AC5: =IF(ROW()=5,P5,IF(AND($P5>1,AC$4=$L5),$P5,IF(AND($U5=$U4,V5=V4),AC4,IF(AND($L5=AC$4,P5=1),P5,0)))) -> 1 | AD5: =IF(AC5>1,AC5,IF(AND($P5>1,AD$4=$L5),$P5,IF(AND($U5=$U4,W5=W4),AD4,IF(AND($L5=AD$4,P5=1),P5,0)))) -> 0 | AE5: =IF(AD5>1,AD5,IF(AND($P5>1,AE$4=$L5),$P5,IF(AND($U5=$U4,X5=X4),AE4,IF(AND($L5=AE$4,P5=1),P5,0)))) -> 0 | AF5: =IF(AE5>1,AE5,IF(AND($P5>1,AF$4=$L5),$P5,IF(AND($U5=$U4,Y5=Y4),AF4,IF(AND($L5=AF$4,P5=1),P5,0)))) -> 0 | AG5: =IF(AF5>1,AF5,IF(AND($P5>1,AG$4=$L5),$P5,IF(AND($U5=$U4,Z5=Z4),AG4,IF(AND($L5=AG$4,P5=1),P5,0)))) -> 0 | AH5: =IF(AND($P5=1,$L5=AH$4),2,IF(AND($L5<>AH$4,AH4=2),AH4,IF($L5<>AH$4,0,1))) -> 2 | AI5: =IF(OR(ROW()=5,$U4<>$U5),0,IF(AND($P5=1,$L5=AI$4),2,IF(AND($L5<>AI$4,AI4=2),AI4,IF($L5<>AI$4,0,1)))) -> 0 | AJ5: =IF(OR(ROW()=5,$U4<>$U5),0,IF(AND($P5=1,$L5=AJ$4),2,IF(AND($L5<>AJ$4,AJ4=2),AJ4,IF($L5<>AJ$4,0,1)))) -> 0 | AK5: =IF(OR(ROW()=5,$U4<>$U5),0,IF(AND($P5=1,$L5=AK$4),2,IF(AND($L5<>AK$4,AK4=2),AK4,IF($L5<>AK$4,0,1)))) -> 0 | AL5: =IF(OR(ROW()=5,$U4<>$U5),0,IF(AND($P5=1,$L5=AL$4),2,IF(AND($L5<>AL$4,AL4=2),AL4,IF($L5<>AL$4,0,1)))) -> 0
A6: 2325 | B6: A.1.1 | C6: Does the risk governance plan include risk management policies, procedures, and internal controls? | D6: Yes | G6: Enterprise Risk Management | H6: Risk Governance Plan | I6: A.1 Enterprise Risk Governance | L6: 2 | M6: 2 | P6: =IF($L6="","",IF($D6="Yes",1,IF($D6="No",2,IF($D6="N/A",3,0)))) -> 1 | Q6: =IF(AND(Drops!$D$45>1,OR(U6<>U5,AND(ROW()=5,U5=U6))),VLOOKUP(U6,Drops!$D$26:$E$44,2,FALSE),"") | R6: =IF(Q6<>"",ROW(),"") | S6: =OFFSET(AC6,,L6-1) -> 1 | T6: =IF(OR(V6<>V5,U6<>U5,AND(V6<>V5,W6<>W5),AND(V6<>V5,W6<>W5,X6<>X5),AND(V6<>V5,W6<>W5,X6<>X5,Y6<>Y5),AND(V6<>V5,W6<>W5,X6<>X5,Y6<>Y5,Z6<>Z5),L6-L5>1),1,0) -> 0 | U6: A | V6: 1 | W6: 1 | X6: 0 | Y6: 0 | Z6: 0 | AA6: =IF(ROW()=5,1,IF(OR(AH6=1,P6>0,T6=1),1,IF(OR(AND(AH6=2,AI6=1),AND(AI6=2,AJ6=1),AND(AJ6=2,AK6=1),AND(AK6=2,AL6=1)),1,0))) -> 1 | AB6: =IF(L7>L6,1,0) -> 0 | AC6: =IF(ROW()=5,P6,IF(AND($P6>1,AC$4=$L6),$P6,IF(AND($U6=$U5,V6=V5),AC5,IF(AND($L6=AC$4,P6=1),P6,0)))) -> 1 | AD6: =IF(AC6>1,AC6,IF(AND($P6>1,AD$4=$L6),$P6,IF(AND($U6=$U5,W6=W5),AD5,IF(AND($L6=AD$4,P6=1),P6,0)))) -> 1 | AE6: =IF(AD6>1,AD6,IF(AND($P6>1,AE$4=$L6),$P6,IF(AND($U6=$U5,X6=X5),AE5,IF(AND($L6=AE$4,P6=1),P6,0)))) -> 0 | AF6: =IF(AE6>1,AE6,IF(AND($P6>1,AF$4=$L6),$P6,IF(AND($U6=$U5,Y6=Y5),AF5,IF(AND($L6=AF$4,P6=1),P6,0)))) -> 0 | AG6: =IF(AF6>1,AF6,IF(AND($P6>1,AG$4=$L6),$P6,IF(AND($U6=$U5,Z6=Z5),AG5,IF(AND($L6=AG$4,P6=1),P6,0)))) -> 0 | AH6: =IF(AND($P6=1,$L6=AH$4),2,IF(AND($L6<>AH$4,AH5=2),AH5,IF($L6<>AH$4,0,1))) -> 2 | AI6: =IF(OR(ROW()=5,$U5<>$U6),0,IF(AND($P6=1,$L6=AI$4),2,IF(AND($L6<>AI$4,AI5=2),AI5,IF($L6<>AI$4,0,1)))) -> 2 | AJ6: =IF(OR(ROW()=5,$U5<>$U6),0,IF(AND($P6=1,$L6=AJ$4),2,IF(AND($L6<>AJ$4,AJ5=2),AJ5,IF($L6<>AJ$4,0,1)))) -> 0 | AK6: =IF(OR(ROW()=5,$U5<>$U6),0,IF(AND($P6=1,$L6=AK$4),2,IF(AND($L6<>AK$4,AK5=2),AK5,IF($L6<>AK$4,0,1)))) -> 0 | AL6: =IF(OR(ROW()=5,$U5<>$U6),0,IF(AND($P6=1,$L6=AL$4),2,IF(AND($L6<>AL$4,AL5=2),AL5,IF($L6<>AL$4,0,1)))) -> 0
A7: 2326 | B7: A.1.2 | C7: Does the risk governance plan include range of assets to include: people, processes, data and technology? | D7: Yes | G7: Enterprise Risk Management | H7: Risk Governance Plan | I7: A.1 Enterprise Risk Governance | L7: 2 | M7: 2 | P7: =IF($L7="","",IF($D7="Yes",1,IF($D7="No",2,IF($D7="N/A",3,0)))) -> 1 | Q7: =IF(AND(Drops!$D$45>1,OR(U7<>U6,AND(ROW()=5,U6=U7))),VLOOKUP(U7,Drops!$D$26:$E$44,2,FALSE),"") | R7: =IF(Q7<>"",ROW(),"") | S7: =OFFSET(AC7,,L7-1) -> 1 | T7: =IF(OR(V7<>V6,U7<>U6,AND(V7<>V6,W7<>W6),AND(V7<>V6,W7<>W6,X7<>X6),AND(V7<>V6,W7<>W6,X7<>X6,Y7<>Y6),AND(V7<>V6,W7<>W6,X7<>X6,Y7<>Y6,Z7<>Z6),L7-L6>1),1,0) -> 0 | U7: A | V7: 1 | W7: 2 | X7: 0 | Y7: 0 | Z7: 0 | AA7: =IF(ROW()=5,1,IF(OR(AH7=1,P7>0,T7=1),1,IF(OR(AND(AH7=2,AI7=1),AND(AI7=2,AJ7=1),AND(AJ7=2,AK7=1),AND(AK7=2,AL7=1)),1,0))) -> 1 | AB7: =IF(L8>L7,1,0) -> 0 | AC7: =IF(ROW()=5,P7,IF(AND($P7>1,AC$4=$L7),$P7,IF(AND($U7=$U6,V7=V6),AC6,IF(AND($L7=AC$4,P7=1),P7,0)))) -> 1 | AD7: =IF(AC7>1,AC7,IF(AND($P7>1,AD$4=$L7),$P7,IF(AND($U7=$U6,W7=W6),AD6,IF(AND($L7=AD$4,P7=1),P7,0)))) -> 1 | AE7: =IF(AD7>1,AD7,IF(AND($P7>1,AE$4=$L7),$P7,IF(AND($U7=$U6,X7=X6),AE6,IF(AND($L7=AE$4,P7=1),P7,0)))) -> 0 | AF7: =IF(AE7>1,AE7,IF(AND($P7>1,AF$4=$L7),$P7,IF(AND($U7=$U6,Y7=Y6),AF6,IF(AND($L7=AF$4,P7=1),P7,0)))) -> 0 | AG7: =IF(AF7>1,AF7,IF(AND($P7>1,AG$4=$L7),$P7,IF(AND($U7=$U6,Z7=Z6),AG6,IF(AND($L7=AG$4,P7=1),P7,0)))) -> 0 | AH7: =IF(AND($P7=1,$L7=AH$4),2,IF(AND($L7<>AH$4,AH6=2),AH6,IF($L7<>AH$4,0,1))) -> 2 | AI7: =IF(OR(ROW()=5,$U6<>$U7),0,IF(AND($P7=1,$L7=AI$4),2,IF(AND($L7<>AI$4,AI6=2),AI6,IF($L7<>AI$4,0,1)))) -> 2 | AJ7: =IF(OR(ROW()=5,$U6<>$U7),0,IF(AND($P7=1,$L7=AJ$4),2,IF(AND($L7<>AJ$4,AJ6=2),AJ6,IF($L7<>AJ$4,0,1)))) -> 0 | AK7: =IF(OR(ROW()=5,$U6<>$U7),0,IF(AND($P7=1,$L7=AK$4),2,IF(AND($L7<>AK$4,AK6=2),AK6,IF($L7<>AK$4,0,1)))) -> 0 | AL7: =IF(OR(ROW()=5,$U6<>$U7),0,IF(AND($P7=1,$L7=AL$4),2,IF(AND($L7<>AL$4,AL6=2),AL6,IF($L7<>AL$4,0,1)))) -> 0
A8: 2420 | B8: A.1.3 | C8: Does the risk governance plan include range of internal and external threats to include: malicious, natural, accidental, cyber, business changes (transaction volume)? | D8: Yes | G8: Enterprise Risk Management | H8: Risk Governance Plan | I8: A.1 Enterprise Risk Governance | L8: 2 | M8: 3 | P8: =IF($L8="","",IF($D8="Yes",1,IF($D8="No",2,IF($D8="N/A",3,0)))) -> 1 | Q8: =IF(AND(Drops!$D$45>1,OR(U8<>U7,AND(ROW()=5,U7=U8))),VLOOKUP(U8,Drops!$D$26:$E$44,2,FALSE),"") | R8: =IF(Q8<>"",ROW(),"") | S8: =OFFSET(AC8,,L8-1) -> 1 | T8: =IF(OR(V8<>V7,U8<>U7,AND(V8<>V7,W8<>W7),AND(V8<>V7,W8<>W7,X8<>X7),AND(V8<>V7,W8<>W7,X8<>X7,Y8<>Y7),AND(V8<>V7,W8<>W7,X8<>X7,Y8<>Y7,Z8<>Z7),L8-L7>1),1,0) -> 0 | U8: A | V8: 1 | W8: 3 | X8: 0 | Y8: 0 | Z8: 0 | AA8: =IF(ROW()=5,1,IF(OR(AH8=1,P8>0,T8=1),1,IF(OR(AND(AH8=2,AI8=1),AND(AI8=2,AJ8=1),AND(AJ8=2,AK8=1),AND(AK8=2,AL8=1)),1,0))) -> 1 | AB8: =IF(L9>L8,1,0) -> 0 | AC8: =IF(ROW()=5,P8,IF(AND($P8>1,AC$4=$L8),$P8,IF(AND($U8=$U7,V8=V7),AC7,IF(AND($L8=AC$4,P8=1),P8,0)))) -> 1 | AD8: =IF(AC8>1,AC8,IF(AND($P8>1,AD$4=$L8),$P8,IF(AND($U8=$U7,W8=W7),AD7,IF(AND($L8=AD$4,P8=1),P8,0)))) -> 1 | AE8: =IF(AD8>1,AD8,IF(AND($P8>1,AE$4=$L8),$P8,IF(AND($U8=$U7,X8=X7),AE7,IF(AND($L8=AE$4,P8=1),P8,0)))) -> 0 | AF8: =IF(AE8>1,AE8,IF(AND($P8>1,AF$4=$L8),$P8,IF(AND($U8=$U7,Y8=Y7),AF7,IF(AND($L8=AF$4,P8=1),P8,0)))) -> 0 | AG8: =IF(AF8>1,AF8,IF(AND($P8>1,AG$4=$L8),$P8,IF(AND($U8=$U7,Z8=Z7),AG7,IF(AND($L8=AG$4,P8=1),P8,0)))) -> 0 | AH8: =IF(AND($P8=1,$L8=AH$4),2,IF(AND($L8<>AH$4,AH7=2),AH7,IF($L8<>AH$4,0,1))) -> 2 | AI8: =IF(OR(ROW()=5,$U7<>$U8),0,IF(AND($P8=1,$L8=AI$4),2,IF(AND($L8<>AI$4,AI7=2),AI7,IF($L8<>AI$4,0,1)))) -> 2 | AJ8: =IF(OR(ROW()=5,$U7<>$U8),0,IF(AND($P8=1,$L8=AJ$4),2,IF(AND($L8<>AJ$4,AJ7=2),AJ7,IF($L8<>AJ$4,0,1)))) -> 0 | AK8: =IF(OR(ROW()=5,$U7<>$U8),0,IF(AND($P8=1,$L8=AK$4),2,IF(AND($L8<>AK$4,AK7=2),AK7,IF($L8<>AK$4,0,1)))) -> 0 | AL8: =IF(OR(ROW()=5,$U7<>$U8),0,IF(AND($P8=1,$L8=AL$4),2,IF(AND($L8<>AL$4,AL7=2),AL7,IF($L8<>AL$4,0,1)))) -> 0
A9: 2429 | B9: A.1.4 | C9: Does the risk governance plan include risk scenarios that address threats, vulnerabilities, likelihoods, and impacts that could impact people, processes, technologies, and facilities? | D9: Yes | G9: Enterprise Risk Management | H9: Risk Governance Plan | I9: A.1 Enterprise Risk Governance | L9: 2 | M9: 3 | P9: =IF($L9="","",IF($D9="Yes",1,IF($D9="No",2,IF($D9="N/A",3,0)))) -> 1 | Q9: =IF(AND(Drops!$D$45>1,OR(U9<>U8,AND(ROW()=5,U8=U9))),VLOOKUP(U9,Drops!$D$26:$E$44,2,FALSE),"") | R9: =IF(Q9<>"",ROW(),"") | S9: =OFFSET(AC9,,L9-1) -> 1 | T9: =IF(OR(V9<>V8,U9<>U8,AND(V9<>V8,W9<>W8),AND(V9<>V8,W9<>W8,X9<>X8),AND(V9<>V8,W9<>W8,X9<>X8,Y9<>Y8),AND(V9<>V8,W9<>W8,X9<>X8,Y9<>Y8,Z9<>Z8),L9-L8>1),1,0) -> 0 | U9: A | V9: 1 | W9: 4 | X9: 0 | Y9: 0 | Z9: 0 | AA9: =IF(ROW()=5,1,IF(OR(AH9=1,P9>0,T9=1),1,IF(OR(AND(AH9=2,AI9=1),AND(AI9=2,AJ9=1),AND(AJ9=2,AK9=1),AND(AK9=2,AL9=1)),1,0))) -> 1 | AB9: =IF(L10>L9,1,0) -> 0 | AC9: =IF(ROW()=5,P9,IF(AND($P9>1,AC$4=$L9),$P9,IF(AND($U9=$U8,V9=V8),AC8,IF(AND($L9=AC$4,P9=1),P9,0)))) -> 1 | AD9: =IF(AC9>1,AC9,IF(AND($P9>1,AD$4=$L9),$P9,IF(AND($U9=$U8,W9=W8),AD8,IF(AND($L9=AD$4,P9=1),P9,0)))) -> 1 | AE9: =IF(AD9>1,AD9,IF(AND($P9>1,AE$4=$L9),$P9,IF(AND($U9=$U8,X9=X8),AE8,IF(AND($L9=AE$4,P9=1),P9,0)))) -> 0 | AF9: =IF(AE9>1,AE9,IF(AND($P9>1,AF$4=$L9),$P9,IF(AND($U9=$U8,Y9=Y8),AF8,IF(AND($L9=AF$4,P9=1),P9,0)))) -> 0 | AG9: =IF(AF9>1,AF9,IF(AND($P9>1,AG$4=$L9),$P9,IF(AND($U9=$U8,Z9=Z8),AG8,IF(AND($L9=AG$4,P9=1),P9,0)))) -> 0 | AH9: =IF(AND($P9=1,$L9=AH$4),2,IF(AND($L9<>AH$4,AH8=2),AH8,IF($L9<>AH$4,0,1))) -> 2 | AI9: =IF(OR(ROW()=5,$U8<>$U9),0,IF(AND($P9=1,$L9=AI$4),2,IF(AND($L9<>AI$4,AI8=2),AI8,IF($L9<>AI$4,0,1)))) -> 2 | AJ9: =IF(OR(ROW()=5,$U8<>$U9),0,IF(AND($P9=1,$L9=AJ$4),2,IF(AND($L9<>AJ$4,AJ8=2),AJ8,IF($L9<>AJ$4,0,1)))) -> 0 | AK9: =IF(OR(ROW()=5,$U8<>$U9),0,IF(AND($P9=1,$L9=AK$4),2,IF(AND($L9<>AK$4,AK8=2),AK8,IF($L9<>AK$4,0,1)))) -> 0 | AL9: =IF(OR(ROW()=5,$U8<>$U9),0,IF(AND($P9=1,$L9=AL$4),2,IF(AND($L9<>AL$4,AL8=2),AL8,IF($L9<>AL$4,0,1)))) -> 0
A10: 4633 | B10: A.1.5 | C10: Does the organization have a governing body accountable to maintain the risk governance plan? | D10: Yes | G10: Enterprise Risk Management | H10: Risk Governance Plan | I10: A.1 Enterprise Risk Governance | L10: 2 | M10: 3 | P10: =IF($L10="","",IF($D10="Yes",1,IF($D10="No",2,IF($D10="N/A",3,0)))) -> 1 | Q10: =IF(AND(Drops!$D$45>1,OR(U10<>U9,AND(ROW()=5,U9=U10))),VLOOKUP(U10,Drops!$D$26:$E$44,2,FALSE),"") | R10: =IF(Q10<>"",ROW(),"") | S10: =OFFSET(AC10,,L10-1) -> 1 | T10: =IF(OR(V10<>V9,U10<>U9,AND(V10<>V9,W10<>W9),AND(V10<>V9,W10<>W9,X10<>X9),AND(V10<>V9,W10<>W9,X10<>X9,Y10<>Y9),AND(V10<>V9,W10<>W9,X10<>X9,Y10<>Y9,Z10<>Z9),L10-L9>1),1,0) -> 0 | U10: A | V10: 1 | W10: 5 | X10: 0 | Y10: 0 | Z10: 0 | AA10: =IF(ROW()=5,1,IF(OR(AH10=1,P10>0,T10=1),1,IF(OR(AND(AH10=2,AI10=1),AND(AI10=2,AJ10=1),AND(AJ10=2,AK10=1),AND(AK10=2,AL10=1)),1,0))) -> 1 | AB10: =IF(L11>L10,1,0) -> 0 | AC10: =IF(ROW()=5,P10,IF(AND($P10>1,AC$4=$L10),$P10,IF(AND($U10=$U9,V10=V9),AC9,IF(AND($L10=AC$4,P10=1),P10,0)))) -> 1 | AD10: =IF(AC10>1,AC10,IF(AND($P10>1,AD$4=$L10),$P10,IF(AND($U10=$U9,W10=W9),AD9,IF(AND($L10=AD$4,P10=1),P10,0)))) -> 1 | AE10: =IF(AD10>1,AD10,IF(AND($P10>1,AE$4=$L10),$P10,IF(AND($U10=$U9,X10=X9),AE9,IF(AND($L10=AE$4,P10=1),P10,0)))) -> 0 | AF10: =IF(AE10>1,AE10,IF(AND($P10>1,AF$4=$L10),$P10,IF(AND($U10=$U9,Y10=Y9),AF9,IF(AND($L10=AF$4,P10=1),P10,0)))) -> 0 | AG10: =IF(AF10>1,AF10,IF(AND($P10>1,AG$4=$L10),$P10,IF(AND($U10=$U9,Z10=Z9),AG9,IF(AND($L10=AG$4,P10=1),P10,0)))) -> 0 | AH10: =IF(AND($P10=1,$L10=AH$4),2,IF(AND($L10<>AH$4,AH9=2),AH9,IF($L10<>AH$4,0,1))) -> 2 | AI10: =IF(OR(ROW()=5,$U9<>$U10),0,IF(AND($P10=1,$L10=AI$4),2,IF(AND($L10<>AI$4,AI9=2),AI9,IF($L10<>AI$4,0,1)))) -> 2 | AJ10: =IF(OR(ROW()=5,$U9<>$U10),0,IF(AND($P10=1,$L10=AJ$4),2,IF(AND($L10<>AJ$4,AJ9=2),AJ9,IF($L10<>AJ$4,0,1)))) -> 0 | AK10: =IF(OR(ROW()=5,$U9<>$U10),0,IF(AND($P10=1,$L10=AK$4),2,IF(AND($L10<>AK$4,AK9=2),AK9,IF($L10<>AK$4,0,1)))) -> 0 | AL10: =IF(OR(ROW()=5,$U9<>$U10),0,IF(AND($P10=1,$L10=AL$4),2,IF(AND($L10<>AL$4,AL9=2),AL9,IF($L10<>AL$4,0,1)))) -> 0
A11: 4635 | B11: A.1.7 | C11: Is the risk governance plan approved by senior management and/or board of directors? | D11: Yes | G11: Enterprise Risk Management | H11: Risk Governance Plan | I11: A.1 Enterprise Risk Governance | L11: 2 | M11: 3 | P11: =IF($L11="","",IF($D11="Yes",1,IF($D11="No",2,IF($D11="N/A",3,0)))) -> 1 | Q11: =IF(AND(Drops!$D$45>1,OR(U11<>U10,AND(ROW()=5,U10=U11))),VLOOKUP(U11,Drops!$D$26:$E$44,2,FALSE),"") | R11: =IF(Q11<>"",ROW(),"") | S11: =OFFSET(AC11,,L11-1) -> 1 | T11: =IF(OR(V11<>V10,U11<>U10,AND(V11<>V10,W11<>W10),AND(V11<>V10,W11<>W10,X11<>X10),AND(V11<>V10,W11<>W10,X11<>X10,Y11<>Y10),AND(V11<>V10,W11<>W10,X11<>X10,Y11<>Y10,Z11<>Z10),L11-L10>1),1,0) -> 0 | U11: A | V11: 1 | W11: 7 | X11: 0 | Y11: 0 | Z11: 0 | AA11: =IF(ROW()=5,1,IF(OR(AH11=1,P11>0,T11=1),1,IF(OR(AND(AH11=2,AI11=1),AND(AI11=2,AJ11=1),AND(AJ11=2,AK11=1),AND(AK11=2,AL11=1)),1,0))) -> 1 | AB11: =IF(L12>L11,1,0) -> 0 | AC11: =IF(ROW()=5,P11,IF(AND($P11>1,AC$4=$L11),$P11,IF(AND($U11=$U10,V11=V10),AC10,IF(AND($L11=AC$4,P11=1),P11,0)))) -> 1 | AD11: =IF(AC11>1,AC11,IF(AND($P11>1,AD$4=$L11),$P11,IF(AND($U11=$U10,W11=W10),AD10,IF(AND($L11=AD$4,P11=1),P11,0)))) -> 1 | AE11: =IF(AD11>1,AD11,IF(AND($P11>1,AE$4=$L11),$P11,IF(AND($U11=$U10,X11=X10),AE10,IF(AND($L11=AE$4,P11=1),P11,0)))) -> 0 | AF11: =IF(AE11>1,AE11,IF(AND($P11>1,AF$4=$L11),$P11,IF(AND($U11=$U10,Y11=Y10),AF10,IF(AND($L11=AF$4,P11=1),P11,0)))) -> 0 | AG11: =IF(AF11>1,AF11,IF(AND($P11>1,AG$4=$L11),$P11,IF(AND($U11=$U10,Z11=Z10),AG10,IF(AND($L11=AG$4,P11=1),P11,0)))) -> 0 | AH11: =IF(AND($P11=1,$L11=AH$4),2,IF(AND($L11<>AH$4,AH10=2),AH10,IF($L11<>AH$4,0,1))) -> 2 | AI11: =IF(OR(ROW()=5,$U10<>$U11),0,IF(AND($P11=1,$L11=AI$4),2,IF(AND($L11<>AI$4,AI10=2),AI10,IF($L11<>AI$4,0,1)))) -> 2 | AJ11: =IF(OR(ROW()=5,$U10<>$U11),0,IF(AND($P11=1,$L11=AJ$4),2,IF(AND($L11<>AJ$4,AJ10=2),AJ10,IF($L11<>AJ$4,0,1)))) -> 0 | AK11: =IF(OR(ROW()=5,$U10<>$U11),0,IF(AND($P11=1,$L11=AK$4),2,IF(AND($L11<>AK$4,AK10=2),AK10,IF($L11<>AK$4,0,1)))) -> 0 | AL11: =IF(OR(ROW()=5,$U10<>$U11),0,IF(AND($P11=1,$L11=AL$4),2,IF(AND($L11<>AL$4,AL10=2),AL10,IF($L11<>AL$4,0,1)))) -> 0
A12: 4636 | B12: A.1.8 | C12: Is training provided to employees regarding risk expectations and their obligations? | D12: Yes | G12: Enterprise Risk Management | H12: Risk Governance Plan | I12: A.1 Enterprise Risk Governance | L12: 2 | M12: 3 | P12: =IF($L12="","",IF($D12="Yes",1,IF($D12="No",2,IF($D12="N/A",3,0)))) -> 1 | Q12: =IF(AND(Drops!$D$45>1,OR(U12<>U11,AND(ROW()=5,U11=U12))),VLOOKUP(U12,Drops!$D$26:$E$44,2,FALSE),"") | R12: =IF(Q12<>"",ROW(),"") | S12: =OFFSET(AC12,,L12-1) -> 1 | T12: =IF(OR(V12<>V11,U12<>U11,AND(V12<>V11,W12<>W11),AND(V12<>V11,W12<>W11,X12<>X11),AND(V12<>V11,W12<>W11,X12<>X11,Y12<>Y11),AND(V12<>V11,W12<>W11,X12<>X11,Y12<>Y11,Z12<>Z11),L12-L11>1),1,0) -> 0 | U12: A | V12: 1 | W12: 8 | X12: 0 | Y12: 0 | Z12: 0 | AA12: =IF(ROW()=5,1,IF(OR(AH12=1,P12>0,T12=1),1,IF(OR(AND(AH12=2,AI12=1),AND(AI12=2,AJ12=1),AND(AJ12=2,AK12=1),AND(AK12=2,AL12=1)),1,0))) -> 1 | AB12: =IF(L13>L12,1,0) -> 0 | AC12: =IF(ROW()=5,P12,IF(AND($P12>1,AC$4=$L12),$P12,IF(AND($U12=$U11,V12=V11),AC11,IF(AND($L12=AC$4,P12=1),P12,0)))) -> 1 | AD12: =IF(AC12>1,AC12,IF(AND($P12>1,AD$4=$L12),$P12,IF(AND($U12=$U11,W12=W11),AD11,IF(AND($L12=AD$4,P12=1),P12,0)))) -> 1 | AE12: =IF(AD12>1,AD12,IF(AND($P12>1,AE$4=$L12),$P12,IF(AND($U12=$U11,X12=X11),AE11,IF(AND($L12=AE$4,P12=1),P12,0)))) -> 0 | AF12: =IF(AE12>1,AE12,IF(AND($P12>1,AF$4=$L12),$P12,IF(AND($U12=$U11,Y12=Y11),AF11,IF(AND($L12=AF$4,P12=1),P12,0)))) -> 0 | AG12: =IF(AF12>1,AF12,IF(AND($P12>1,AG$4=$L12),$P12,IF(AND($U12=$U11,Z12=Z11),AG11,IF(AND($L12=AG$4,P12=1),P12,0)))) -> 0 | AH12: =IF(AND($P12=1,$L12=AH$4),2,IF(AND($L12<>AH$4,AH11=2),AH11,IF($L12<>AH$4,0,1))) -> 2 | AI12: =IF(OR(ROW()=5,$U11<>$U12),0,IF(AND($P12=1,$L12=AI$4),2,IF(AND($L12<>AI$4,AI11=2),AI11,IF($L12<>AI$4,0,1)))) -> 2 | AJ12: =IF(OR(ROW()=5,$U11<>$U12),0,IF(AND($P12=1,$L12=AJ$4),2,IF(AND($L12<>AJ$4,AJ11=2),AJ11,IF($L12<>AJ$4,0,1)))) -> 0 | AK12: =IF(OR(ROW()=5,$U11<>$U12),0,IF(AND($P12=1,$L12=AK$4),2,IF(AND($L12<>AK$4,AK11=2),AK11,IF($L12<>AK$4,0,1)))) -> 0 | AL12: =IF(OR(ROW()=5,$U11<>$U12),0,IF(AND($P12=1,$L12=AL$4),2,IF(AND($L12<>AL$4,AL11=2),AL11,IF($L12<>AL$4,0,1)))) -> 0
A13: 5837 | B13: A.1.9 | C13: Does the risk governance plan include the identification of the systems/products/services that support organizational priorities? | D13: Yes | G13: Enterprise Risk Management | H13: Risk Governance Plan | L13: 2 | M13: 3 | P13: =IF($L13="","",IF($D13="Yes",1,IF($D13="No",2,IF($D13="N/A",3,0)))) -> 1 | Q13: =IF(AND(Drops!$D$45>1,OR(U13<>U12,AND(ROW()=5,U12=U13))),VLOOKUP(U13,Drops!$D$26:$E$44,2,FALSE),"") | R13: =IF(Q13<>"",ROW(),"") | S13: =OFFSET(AC13,,L13-1) -> 1 | T13: =IF(OR(V13<>V12,U13<>U12,AND(V13<>V12,W13<>W12),AND(V13<>V12,W13<>W12,X13<>X12),AND(V13<>V12,W13<>W12,X13<>X12,Y13<>Y12),AND(V13<>V12,W13<>W12,X13<>X12,Y13<>Y12,Z13<>Z12),L13-L12>1),1,0) -> 0 | U13: A | V13: 1 | W13: 9 | X13: 0 | Y13: 0 | Z13: 0 | AA13: =IF(ROW()=5,1,IF(OR(AH13=1,P13>0,T13=1),1,IF(OR(AND(AH13=2,AI13=1),AND(AI13=2,AJ13=1),AND(AJ13=2,AK13=1),AND(AK13=2,AL13=1)),1,0))) -> 1 | AB13: =IF(L14>L13,1,0) -> 0 | AC13: =IF(ROW()=5,P13,IF(AND($P13>1,AC$4=$L13),$P13,IF(AND($U13=$U12,V13=V12),AC12,IF(AND($L13=AC$4,P13=1),P13,0)))) -> 1 | AD13: =IF(AC13>1,AC13,IF(AND($P13>1,AD$4=$L13),$P13,IF(AND($U13=$U12,W13=W12),AD12,IF(AND($L13=AD$4,P13=1),P13,0)))) -> 1 | AE13: =IF(AD13>1,AD13,IF(AND($P13>1,AE$4=$L13),$P13,IF(AND($U13=$U12,X13=X12),AE12,IF(AND($L13=AE$4,P13=1),P13,0)))) -> 0 | AF13: =IF(AE13>1,AE13,IF(AND($P13>1,AF$4=$L13),$P13,IF(AND($U13=$U12,Y13=Y12),AF12,IF(AND($L13=AF$4,P13=1),P13,0)))) -> 0 | AG13: =IF(AF13>1,AF13,IF(AND($P13>1,AG$4=$L13),$P13,IF(AND($U13=$U12,Z13=Z12),AG12,IF(AND($L13=AG$4,P13=1),P13,0)))) -> 0 | AH13: =IF(AND($P13=1,$L13=AH$4),2,IF(AND($L13<>AH$4,AH12=2),AH12,IF($L13<>AH$4,0,1))) -> 2 | AI13: =IF(OR(ROW()=5,$U12<>$U13),0,IF(AND($P13=1,$L13=AI$4),2,IF(AND($L13<>AI$4,AI12=2),AI12,IF($L13<>AI$4,0,1)))) -> 2 | AJ13: =IF(OR(ROW()=5,$U12<>$U13),0,IF(AND($P13=1,$L13=AJ$4),2,IF(AND($L13<>AJ$4,AJ12=2),AJ12,IF($L13<>AJ$4,0,1)))) -> 0 | AK13: =IF(OR(ROW()=5,$U12<>$U13),0,IF(AND($P13=1,$L13=AK$4),2,IF(AND($L13<>AK$4,AK12=2),AK12,IF($L13<>AK$4,0,1)))) -> 0 | AL13: =IF(OR(ROW()=5,$U12<>$U13),0,IF(AND($P13=1,$L13=AL$4),2,IF(AND($L13<>AL$4,AL12=2),AL12,IF($L13<>AL$4,0,1)))) -> 0
A14: 5838 | B14: A.1.10 | C14: Does the risk governance plan include the alignment to the organization's mission, objectives, and stakeholders to inform roles and responsibilities for risk management decisions? | D14: Yes | G14: Enterprise Risk Management | H14: Risk Governance Plan | L14: 2 | M14: 3 | P14: =IF($L14="","",IF($D14="Yes",1,IF($D14="No",2,IF($D14="N/A",3,0)))) -> 1 | Q14: =IF(AND(Drops!$D$45>1,OR(U14<>U13,AND(ROW()=5,U13=U14))),VLOOKUP(U14,Drops!$D$26:$E$44,2,FALSE),"") | R14: =IF(Q14<>"",ROW(),"") | S14: =OFFSET(AC14,,L14-1) -> 1 | T14: =IF(OR(V14<>V13,U14<>U13,AND(V14<>V13,W14<>W13),AND(V14<>V13,W14<>W13,X14<>X13),AND(V14<>V13,W14<>W13,X14<>X13,Y14<>Y13),AND(V14<>V13,W14<>W13,X14<>X13,Y14<>Y13,Z14<>Z13),L14-L13>1),1,0) -> 0 | U14: A | V14: 1 | W14: 10 | X14: 0 | Y14: 0 | Z14: 0 | AA14: =IF(ROW()=5,1,IF(OR(AH14=1,P14>0,T14=1),1,IF(OR(AND(AH14=2,AI14=1),AND(AI14=2,AJ14=1),AND(AJ14=2,AK14=1),AND(AK14=2,AL14=1)),1,0))) -> 1 | AB14: =IF(L15>L14,1,0) -> 0 | AC14: =IF(ROW()=5,P14,IF(AND($P14>1,AC$4=$L14),$P14,IF(AND($U14=$U13,V14=V13),AC13,IF(AND($L14=AC$4,P14=1),P14,0)))) -> 1 | AD14: =IF(AC14>1,AC14,IF(AND($P14>1,AD$4=$L14),$P14,IF(AND($U14=$U13,W14=W13),AD13,IF(AND($L14=AD$4,P14=1),P14,0)))) -> 1 | AE14: =IF(AD14>1,AD14,IF(AND($P14>1,AE$4=$L14),$P14,IF(AND($U14=$U13,X14=X13),AE13,IF(AND($L14=AE$4,P14=1),P14,0)))) -> 0 | AF14: =IF(AE14>1,AE14,IF(AND($P14>1,AF$4=$L14),$P14,IF(AND($U14=$U13,Y14=Y13),AF13,IF(AND($L14=AF$4,P14=1),P14,0)))) -> 0 | AG14: =IF(AF14>1,AF14,IF(AND($P14>1,AG$4=$L14),$P14,IF(AND($U14=$U13,Z14=Z13),AG13,IF(AND($L14=AG$4,P14=1),P14,0)))) -> 0 | AH14: =IF(AND($P14=1,$L14=AH$4),2,IF(AND($L14<>AH$4,AH13=2),AH13,IF($L14<>AH$4,0,1))) -> 2 | AI14: =IF(OR(ROW()=5,$U13<>$U14),0,IF(AND($P14=1,$L14=AI$4),2,IF(AND($L14<>AI$4,AI13=2),AI13,IF($L14<>AI$4,0,1)))) -> 2 | AJ14: =IF(OR(ROW()=5,$U13<>$U14),0,IF(AND($P14=1,$L14=AJ$4),2,IF(AND($L14<>AJ$4,AJ13=2),AJ13,IF($L14<>AJ$4,0,1)))) -> 0 | AK14: =IF(OR(ROW()=5,$U13<>$U14),0,IF(AND($P14=1,$L14=AK$4),2,IF(AND($L14<>AK$4,AK13=2),AK13,IF($L14<>AK$4,0,1)))) -> 0 | AL14: =IF(OR(ROW()=5,$U13<>$U14),0,IF(AND($P14=1,$L14=AL$4),2,IF(AND($L14<>AL$4,AL13=2),AL13,IF($L14<>AL$4,0,1)))) -> 0
A15: 5839 | B15: A.1.11 | C15: Does the risk governance plan include the establishment and communication of the priorities of activities? | D15: Yes | G15: Enterprise Risk Management | H15: Risk Governance Plan | L15: 2 | M15: 3 | P15: =IF($L15="","",IF($D15="Yes",1,IF($D15="No",2,IF($D15="N/A",3,0)))) -> 1 | Q15: =IF(AND(Drops!$D$45>1,OR(U15<>U14,AND(ROW()=5,U14=U15))),VLOOKUP(U15,Drops!$D$26:$E$44,2,FALSE),"") | R15: =IF(Q15<>"",ROW(),"") | S15: =OFFSET(AC15,,L15-1) -> 1 | T15: =IF(OR(V15<>V14,U15<>U14,AND(V15<>V14,W15<>W14),AND(V15<>V14,W15<>W14,X15<>X14),AND(V15<>V14,W15<>W14,X15<>X14,Y15<>Y14),AND(V15<>V14,W15<>W14,X15<>X14,Y15<>Y14,Z15<>Z14),L15-L14>1),1,0) -> 0 | U15: A | V15: 1 | W15: 11 | X15: 0 | Y15: 0 | Z15: 0 | AA15: =IF(ROW()=5,1,IF(OR(AH15=1,P15>0,T15=1),1,IF(OR(AND(AH15=2,AI15=1),AND(AI15=2,AJ15=1),AND(AJ15=2,AK15=1),AND(AK15=2,AL15=1)),1,0))) -> 1 | AB15: =IF(L16>L15,1,0) -> 0 | AC15: =IF(ROW()=5,P15,IF(AND($P15>1,AC$4=$L15),$P15,IF(AND($U15=$U14,V15=V14),AC14,IF(AND($L15=AC$4,P15=1),P15,0)))) -> 1 | AD15: =IF(AC15>1,AC15,IF(AND($P15>1,AD$4=$L15),$P15,IF(AND($U15=$U14,W15=W14),AD14,IF(AND($L15=AD$4,P15=1),P15,0)))) -> 1 | AE15: =IF(AD15>1,AD15,IF(AND($P15>1,AE$4=$L15),$P15,IF(AND($U15=$U14,X15=X14),AE14,IF(AND($L15=AE$4,P15=1),P15,0)))) -> 0 | AF15: =IF(AE15>1,AE15,IF(AND($P15>1,AF$4=$L15),$P15,IF(AND($U15=$U14,Y15=Y14),AF14,IF(AND($L15=AF$4,P15=1),P15,0)))) -> 0 | AG15: =IF(AF15>1,AF15,IF(AND($P15>1,AG$4=$L15),$P15,IF(AND($U15=$U14,Z15=Z14),AG14,IF(AND($L15=AG$4,P15=1),P15,0)))) -> 0 | AH15: =IF(AND($P15=1,$L15=AH$4),2,IF(AND($L15<>AH$4,AH14=2),AH14,IF($L15<>AH$4,0,1))) -> 2 | AI15: =IF(OR(ROW()=5,$U14<>$U15),0,IF(AND($P15=1,$L15=AI$4),2,IF(AND($L15<>AI$4,AI14=2),AI14,IF($L15<>AI$4,0,1)))) -> 2 | AJ15: =IF(OR(ROW()=5,$U14<>$U15),0,IF(AND($P15=1,$L15=AJ$4),2,IF(AND($L15<>AJ$4,AJ14=2),AJ14,IF($L15<>AJ$4,0,1)))) -> 0 | AK15: =IF(OR(ROW()=5,$U14<>$U15),0,IF(AND($P15=1,$L15=AK$4),2,IF(AND($L15<>AK$4,AK14=2),AK14,IF($L15<>AK$4,0,1)))) -> 0 | AL15: =IF(OR(ROW()=5,$U14<>$U15),0,IF(AND($P15=1,$L15=AL$4),2,IF(AND($L15<>AL$4,AL14=2),AL14,IF($L15<>AL$4,0,1)))) -> 0
A16: 4412 | B16: A.2 | C16: Are there Subject Matter Experts and/or groups assigned to assess risk for different categories e.g., operational, reputational, regulatory, technology, privacy, financial, etc.? If no, please explain any exclusions in the additional information field. | D16: Yes | G16: Enterprise Risk Management | H16: Risk Governance - Personnel | I16: A.1 Enterprise Risk Governance | J16: 6.1.2 Information Security Risk Asssessment|8.2 Information Security Risk Assessment | L16: 1 | M16: 3 | P16: =IF($L16="","",IF($D16="Yes",1,IF($D16="No",2,IF($D16="N/A",3,0)))) -> 1 | Q16: =IF(AND(Drops!$D$45>1,OR(U16<>U15,AND(ROW()=5,U15=U16))),VLOOKUP(U16,Drops!$D$26:$E$44,2,FALSE),"") | R16: =IF(Q16<>"",ROW(),"") | S16: =OFFSET(AC16,,L16-1) -> 1 | T16: =IF(OR(V16<>V15,U16<>U15,AND(V16<>V15,W16<>W15),AND(V16<>V15,W16<>W15,X16<>X15),AND(V16<>V15,W16<>W15,X16<>X15,Y16<>Y15),AND(V16<>V15,W16<>W15,X16<>X15,Y16<>Y15,Z16<>Z15),L16-L15>1),1,0) -> 1 | U16: A | V16: 2 | W16: 0 | X16: 0 | Y16: 0 | Z16: 0 | AA16: =IF(ROW()=5,1,IF(OR(AH16=1,P16>0,T16=1),1,IF(OR(AND(AH16=2,AI16=1),AND(AI16=2,AJ16=1),AND(AJ16=2,AK16=1),AND(AK16=2,AL16=1)),1,0))) -> 1 | AB16: =IF(L17>L16,1,0) -> 1 | AC16: =IF(ROW()=5,P16,IF(AND($P16>1,AC$4=$L16),$P16,IF(AND($U16=$U15,V16=V15),AC15,IF(AND($L16=AC$4,P16=1),P16,0)))) -> 1 | AD16: =IF(AC16>1,AC16,IF(AND($P16>1,AD$4=$L16),$P16,IF(AND($U16=$U15,W16=W15),AD15,IF(AND($L16=AD$4,P16=1),P16,0)))) -> 0 | AE16: =IF(AD16>1,AD16,IF(AND($P16>1,AE$4=$L16),$P16,IF(AND($U16=$U15,X16=X15),AE15,IF(AND($L16=AE$4,P16=1),P16,0)))) -> 0 | AF16: =IF(AE16>1,AE16,IF(AND($P16>1,AF$4=$L16),$P16,IF(AND($U16=$U15,Y16=Y15),AF15,IF(AND($L16=AF$4,P16=1),P16,0)))) -> 0 | AG16: =IF(AF16>1,AF16,IF(AND($P16>1,AG$4=$L16),$P16,IF(AND($U16=$U15,Z16=Z15),AG15,IF(AND($L16=AG$4,P16=1),P16,0)))) -> 0 | AH16: =IF(AND($P16=1,$L16=AH$4),2,IF(AND($L16<>AH$4,AH15=2),AH15,IF($L16<>AH$4,0,1))) -> 2 | AI16: =IF(OR(ROW()=5,$U15<>$U16),0,IF(AND($P16=1,$L16=AI$4),2,IF(AND($L16<>AI$4,AI15=2),AI15,IF($L16<>AI$4,0,1)))) -> 2 | AJ16: =IF(OR(ROW()=5,$U15<>$U16),0,IF(AND($P16=1,$L16=AJ$4),2,IF(AND($L16<>AJ$4,AJ15=2),AJ15,IF($L16<>AJ$4,0,1)))) -> 0 | AK16: =IF(OR(ROW()=5,$U15<>$U16),0,IF(AND($P16=1,$L16=AK$4),2,IF(AND($L16<>AK$4,AK15=2),AK15,IF($L16<>AK$4,0,1)))) -> 0 | AL16: =IF(OR(ROW()=5,$U15<>$U16),0,IF(AND($P16=1,$L16=AL$4),2,IF(AND($L16<>AL$4,AL15=2),AL15,IF($L16<>AL$4,0,1)))) -> 0
A17: 4637 | B17: A.2.1 | C17: Do risk assessment personnel maintain relevant professional certifications? | D17: Yes | G17: Enterprise Risk Management | H17: Risk Governance - Personnel | L17: 2 | M17: 3 | P17: =IF($L17="","",IF($D17="Yes",1,IF($D17="No",2,IF($D17="N/A",3,0)))) -> 1 | Q17: =IF(AND(Drops!$D$45>1,OR(U17<>U16,AND(ROW()=5,U16=U17))),VLOOKUP(U17,Drops!$D$26:$E$44,2,FALSE),"") | R17: =IF(Q17<>"",ROW(),"") | S17: =OFFSET(AC17,,L17-1) -> 1 | T17: =IF(OR(V17<>V16,U17<>U16,AND(V17<>V16,W17<>W16),AND(V17<>V16,W17<>W16,X17<>X16),AND(V17<>V16,W17<>W16,X17<>X16,Y17<>Y16),AND(V17<>V16,W17<>W16,X17<>X16,Y17<>Y16,Z17<>Z16),L17-L16>1),1,0) -> 0 | U17: A | V17: 2 | W17: 1 | X17: 0 | Y17: 0 | Z17: 0 | AA17: =IF(ROW()=5,1,IF(OR(AH17=1,P17>0,T17=1),1,IF(OR(AND(AH17=2,AI17=1),AND(AI17=2,AJ17=1),AND(AJ17=2,AK17=1),AND(AK17=2,AL17=1)),1,0))) -> 1 | AB17: =IF(L18>L17,1,0) -> 0 | AC17: =IF(ROW()=5,P17,IF(AND($P17>1,AC$4=$L17),$P17,IF(AND($U17=$U16,V17=V16),AC16,IF(AND($L17=AC$4,P17=1),P17,0)))) -> 1 | AD17: =IF(AC17>1,AC17,IF(AND($P17>1,AD$4=$L17),$P17,IF(AND($U17=$U16,W17=W16),AD16,IF(AND($L17=AD$4,P17=1),P17,0)))) -> 1 | AE17: =IF(AD17>1,AD17,IF(AND($P17>1,AE$4=$L17),$P17,IF(AND($U17=$U16,X17=X16),AE16,IF(AND($L17=AE$4,P17=1),P17,0)))) -> 0 | AF17: =IF(AE17>1,AE17,IF(AND($P17>1,AF$4=$L17),$P17,IF(AND($U17=$U16,Y17=Y16),AF16,IF(AND($L17=AF$4,P17=1),P17,0)))) -> 0 | AG17: =IF(AF17>1,AF17,IF(AND($P17>1,AG$4=$L17),$P17,IF(AND($U17=$U16,Z17=Z16),AG16,IF(AND($L17=AG$4,P17=1),P17,0)))) -> 0 | AH17: =IF(AND($P17=1,$L17=AH$4),2,IF(AND($L17<>AH$4,AH16=2),AH16,IF($L17<>AH$4,0,1))) -> 2 | AI17: =IF(OR(ROW()=5,$U16<>$U17),0,IF(AND($P17=1,$L17=AI$4),2,IF(AND($L17<>AI$4,AI16=2),AI16,IF($L17<>AI$4,0,1)))) -> 2 | AJ17: =IF(OR(ROW()=5,$U16<>$U17),0,IF(AND($P17=1,$L17=AJ$4),2,IF(AND($L17<>AJ$4,AJ16=2),AJ16,IF($L17<>AJ$4,0,1)))) -> 0 | AK17: =IF(OR(ROW()=5,$U16<>$U17),0,IF(AND($P17=1,$L17=AK$4),2,IF(AND($L17<>AK$4,AK16=2),AK16,IF($L17<>AK$4,0,1)))) -> 0 | AL17: =IF(OR(ROW()=5,$U16<>$U17),0,IF(AND($P17=1,$L17=AL$4),2,IF(AND($L17<>AL$4,AL16=2),AL16,IF($L17<>AL$4,0,1)))) -> 0
A18: 4638 | B18: A.2.2 | C18: Do risk assessment personnel maintain contacts with relevant professional special interest groups, specialist forums or professional associations? | D18: Yes | G18: Enterprise Risk Management | H18: Risk Governance - Personnel | L18: 2 | M18: 3 | P18: =IF($L18="","",IF($D18="Yes",1,IF($D18="No",2,IF($D18="N/A",3,0)))) -> 1 | Q18: =IF(AND(Drops!$D$45>1,OR(U18<>U17,AND(ROW()=5,U17=U18))),VLOOKUP(U18,Drops!$D$26:$E$44,2,FALSE),"") | R18: =IF(Q18<>"",ROW(),"") | S18: =OFFSET(AC18,,L18-1) -> 1 | T18: =IF(OR(V18<>V17,U18<>U17,AND(V18<>V17,W18<>W17),AND(V18<>V17,W18<>W17,X18<>X17),AND(V18<>V17,W18<>W17,X18<>X17,Y18<>Y17),AND(V18<>V17,W18<>W17,X18<>X17,Y18<>Y17,Z18<>Z17),L18-L17>1),1,0) -> 0 | U18: A | V18: 2 | W18: 2 | X18: 0 | Y18: 0 | Z18: 0 | AA18: =IF(ROW()=5,1,IF(OR(AH18=1,P18>0,T18=1),1,IF(OR(AND(AH18=2,AI18=1),AND(AI18=2,AJ18=1),AND(AJ18=2,AK18=1),AND(AK18=2,AL18=1)),1,0))) -> 1 | AB18: =IF(L19>L18,1,0) -> 0 | AC18: =IF(ROW()=5,P18,IF(AND($P18>1,AC$4=$L18),$P18,IF(AND($U18=$U17,V18=V17),AC17,IF(AND($L18=AC$4,P18=1),P18,0)))) -> 1 | AD18: =IF(AC18>1,AC18,IF(AND($P18>1,AD$4=$L18),$P18,IF(AND($U18=$U17,W18=W17),AD17,IF(AND($L18=AD$4,P18=1),P18,0)))) -> 1 | AE18: =IF(AD18>1,AD18,IF(AND($P18>1,AE$4=$L18),$P18,IF(AND($U18=$U17,X18=X17),AE17,IF(AND($L18=AE$4,P18=1),P18,0)))) -> 0 | AF18: =IF(AE18>1,AE18,IF(AND($P18>1,AF$4=$L18),$P18,IF(AND($U18=$U17,Y18=Y17),AF17,IF(AND($L18=AF$4,P18=1),P18,0)))) -> 0 | AG18: =IF(AF18>1,AF18,IF(AND($P18>1,AG$4=$L18),$P18,IF(AND($U18=$U17,Z18=Z17),AG17,IF(AND($L18=AG$4,P18=1),P18,0)))) -> 0 | AH18: =IF(AND($P18=1,$L18=AH$4),2,IF(AND($L18<>AH$4,AH17=2),AH17,IF($L18<>AH$4,0,1))) -> 2 | AI18: =IF(OR(ROW()=5,$U17<>$U18),0,IF(AND($P18=1,$L18=AI$4),2,IF(AND($L18<>AI$4,AI17=2),AI17,IF($L18<>AI$4,0,1)))) -> 2 | AJ18: =IF(OR(ROW()=5,$U17<>$U18),0,IF(AND($P18=1,$L18=AJ$4),2,IF(AND($L18<>AJ$4,AJ17=2),AJ17,IF($L18<>AJ$4,0,1)))) -> 0 | AK18: =IF(OR(ROW()=5,$U17<>$U18),0,IF(AND($P18=1,$L18=AK$4),2,IF(AND($L18<>AK$4,AK17=2),AK17,IF($L18<>AK$4,0,1)))) -> 0 | AL18: =IF(OR(ROW()=5,$U17<>$U18),0,IF(AND($P18=1,$L18=AL$4),2,IF(AND($L18<>AL$4,AL17=2),AL17,IF($L18<>AL$4,0,1)))) -> 0
A19: 4639 | B19: A.2.3 | C19: Do risk assessment personnel participate in continuing education programs e.g., online training, webinars, seminars, etc.? | D19: Yes | G19: Enterprise Risk Management | H19: Risk Governance - Personnel | L19: 2 | M19: 3 | P19: =IF($L19="","",IF($D19="Yes",1,IF($D19="No",2,IF($D19="N/A",3,0)))) -> 1 | Q19: =IF(AND(Drops!$D$45>1,OR(U19<>U18,AND(ROW()=5,U18=U19))),VLOOKUP(U19,Drops!$D$26:$E$44,2,FALSE),"") | R19: =IF(Q19<>"",ROW(),"") | S19: =OFFSET(AC19,,L19-1) -> 1 | T19: =IF(OR(V19<>V18,U19<>U18,AND(V19<>V18,W19<>W18),AND(V19<>V18,W19<>W18,X19<>X18),AND(V19<>V18,W19<>W18,X19<>X18,Y19<>Y18),AND(V19<>V18,W19<>W18,X19<>X18,Y19<>Y18,Z19<>Z18),L19-L18>1),1,0) -> 0 | U19: A | V19: 2 | W19: 3 | X19: 0 | Y19: 0 | Z19: 0 | AA19: =IF(ROW()=5,1,IF(OR(AH19=1,P19>0,T19=1),1,IF(OR(AND(AH19=2,AI19=1),AND(AI19=2,AJ19=1),AND(AJ19=2,AK19=1),AND(AK19=2,AL19=1)),1,0))) -> 1 | AB19: =IF(L20>L19,1,0) -> 0 | AC19: =IF(ROW()=5,P19,IF(AND($P19>1,AC$4=$L19),$P19,IF(AND($U19=$U18,V19=V18),AC18,IF(AND($L19=AC$4,P19=1),P19,0)))) -> 1 | AD19: =IF(AC19>1,AC19,IF(AND($P19>1,AD$4=$L19),$P19,IF(AND($U19=$U18,W19=W18),AD18,IF(AND($L19=AD$4,P19=1),P19,0)))) -> 1 | AE19: =IF(AD19>1,AD19,IF(AND($P19>1,AE$4=$L19),$P19,IF(AND($U19=$U18,X19=X18),AE18,IF(AND($L19=AE$4,P19=1),P19,0)))) -> 0 | AF19: =IF(AE19>1,AE19,IF(AND($P19>1,AF$4=$L19),$P19,IF(AND($U19=$U18,Y19=Y18),AF18,IF(AND($L19=AF$4,P19=1),P19,0)))) -> 0 | AG19: =IF(AF19>1,AF19,IF(AND($P19>1,AG$4=$L19),$P19,IF(AND($U19=$U18,Z19=Z18),AG18,IF(AND($L19=AG$4,P19=1),P19,0)))) -> 0 | AH19: =IF(AND($P19=1,$L19=AH$4),2,IF(AND($L19<>AH$4,AH18=2),AH18,IF($L19<>AH$4,0,1))) -> 2 | AI19: =IF(OR(ROW()=5,$U18<>$U19),0,IF(AND($P19=1,$L19=AI$4),2,IF(AND($L19<>AI$4,AI18=2),AI18,IF($L19<>AI$4,0,1)))) -> 2 | AJ19: =IF(OR(ROW()=5,$U18<>$U19),0,IF(AND($P19=1,$L19=AJ$4),2,IF(AND($L19<>AJ$4,AJ18=2),AJ18,IF($L19<>AJ$4,0,1)))) -> 0 | AK19: =IF(OR(ROW()=5,$U18<>$U19),0,IF(AND($P19=1,$L19=AK$4),2,IF(AND($L19<>AK$4,AK18=2),AK18,IF($L19<>AK$4,0,1)))) -> 0 | AL19: =IF(OR(ROW()=5,$U18<>$U19),0,IF(AND($P19=1,$L19=AL$4),2,IF(AND($L19<>AL$4,AL18=2),AL18,IF($L19<>AL$4,0,1)))) -> 0
A20: 4413 | B20: A.2.5 | C20: Do all assessment groups utilize a consistent standardized framework for assessing risk? | D20: Yes | E20: Seismic's Risk Management Program is based off ISO 27005. | G20: Enterprise Risk Management | H20: Risk Governance - Personnel | J20: 6.1.2 Information Security Risk Asssessment|8.2 Information Security Risk Assessment | L20: 2 | M20: 3 | P20: =IF($L20="","",IF($D20="Yes",1,IF($D20="No",2,IF($D20="N/A",3,0)))) -> 1 | Q20: =IF(AND(Drops!$D$45>1,OR(U20<>U19,AND(ROW()=5,U19=U20))),VLOOKUP(U20,Drops!$D$26:$E$44,2,FALSE),"") | R20: =IF(Q20<>"",ROW(),"") | S20: =OFFSET(AC20,,L20-1) -> 1 | T20: =IF(OR(V20<>V19,U20<>U19,AND(V20<>V19,W20<>W19),AND(V20<>V19,W20<>W19,X20<>X19),AND(V20<>V19,W20<>W19,X20<>X19,Y20<>Y19),AND(V20<>V19,W20<>W19,X20<>X19,Y20<>Y19,Z20<>Z19),L20-L19>1),1,0) -> 0 | U20: A | V20: 2 | W20: 5 | X20: 0 | Y20: 0 | Z20: 0 | AA20: =IF(ROW()=5,1,IF(OR(AH20=1,P20>0,T20=1),1,IF(OR(AND(AH20=2,AI20=1),AND(AI20=2,AJ20=1),AND(AJ20=2,AK20=1),AND(AK20=2,AL20=1)),1,0))) -> 1 | AB20: =IF(L21>L20,1,0) -> 0 | AC20: =IF(ROW()=5,P20,IF(AND($P20>1,AC$4=$L20),$P20,IF(AND($U20=$U19,V20=V19),AC19,IF(AND($L20=AC$4,P20=1),P20,0)))) -> 1 | AD20: =IF(AC20>1,AC20,IF(AND($P20>1,AD$4=$L20),$P20,IF(AND($U20=$U19,W20=W19),AD19,IF(AND($L20=AD$4,P20=1),P20,0)))) -> 1 | AE20: =IF(AD20>1,AD20,IF(AND($P20>1,AE$4=$L20),$P20,IF(AND($U20=$U19,X20=X19),AE19,IF(AND($L20=AE$4,P20=1),P20,0)))) -> 0 | AF20: =IF(AE20>1,AE20,IF(AND($P20>1,AF$4=$L20),$P20,IF(AND($U20=$U19,Y20=Y19),AF19,IF(AND($L20=AF$4,P20=1),P20,0)))) -> 0 | AG20: =IF(AF20>1,AF20,IF(AND($P20>1,AG$4=$L20),$P20,IF(AND($U20=$U19,Z20=Z19),AG19,IF(AND($L20=AG$4,P20=1),P20,0)))) -> 0 | AH20: =IF(AND($P20=1,$L20=AH$4),2,IF(AND($L20<>AH$4,AH19=2),AH19,IF($L20<>AH$4,0,1))) -> 2 | AI20: =IF(OR(ROW()=5,$U19<>$U20),0,IF(AND($P20=1,$L20=AI$4),2,IF(AND($L20<>AI$4,AI19=2),AI19,IF($L20<>AI$4,0,1)))) -> 2 | AJ20: =IF(OR(ROW()=5,$U19<>$U20),0,IF(AND($P20=1,$L20=AJ$4),2,IF(AND($L20<>AJ$4,AJ19=2),AJ19,IF($L20<>AJ$4,0,1)))) -> 0 | AK20: =IF(OR(ROW()=5,$U19<>$U20),0,IF(AND($P20=1,$L20=AK$4),2,IF(AND($L20<>AK$4,AK19=2),AK19,IF($L20<>AK$4,0,1)))) -> 0 | AL20: =IF(OR(ROW()=5,$U19<>$U20),0,IF(AND($P20=1,$L20=AL$4),2,IF(AND($L20<>AL$4,AL19=2),AL19,IF($L20<>AL$4,0,1)))) -> 0
A21: 4640 | B21: A.3 | C21: Is there a formalized Risk Assessment process that identifies, quantifies, and prioritizes risks based on the risk acceptance levels relevant to the organization? | D21: Yes | G21: Enterprise Risk Management | H21: Risk Assessments | I21: A.4 IT Risk Assessments | J21: 6.1.2 Information Security Risk Asssessment|8.2 Information Security Risk Assessment | L21: 1 | M21: 2 | P21: =IF($L21="","",IF($D21="Yes",1,IF($D21="No",2,IF($D21="N/A",3,0)))) -> 1 | Q21: =IF(AND(Drops!$D$45>1,OR(U21<>U20,AND(ROW()=5,U20=U21))),VLOOKUP(U21,Drops!$D$26:$E$44,2,FALSE),"") | R21: =IF(Q21<>"",ROW(),"") | S21: =OFFSET(AC21,,L21-1) -> 1 | T21: =IF(OR(V21<>V20,U21<>U20,AND(V21<>V20,W21<>W20),AND(V21<>V20,W21<>W20,X21<>X20),AND(V21<>V20,W21<>W20,X21<>X20,Y21<>Y20),AND(V21<>V20,W21<>W20,X21<>X20,Y21<>Y20,Z21<>Z20),L21-L20>1),1,0) -> 1 | U21: A | V21: 3 | W21: 0 | X21: 0 | Y21: 0 | Z21: 0 | AA21: =IF(ROW()=5,1,IF(OR(AH21=1,P21>0,T21=1),1,IF(OR(AND(AH21=2,AI21=1),AND(AI21=2,AJ21=1),AND(AJ21=2,AK21=1),AND(AK21=2,AL21=1)),1,0))) -> 1 | AB21: =IF(L22>L21,1,0) -> 1 | AC21: =IF(ROW()=5,P21,IF(AND($P21>1,AC$4=$L21),$P21,IF(AND($U21=$U20,V21=V20),AC20,IF(AND($L21=AC$4,P21=1),P21,0)))) -> 1 | AD21: =IF(AC21>1,AC21,IF(AND($P21>1,AD$4=$L21),$P21,IF(AND($U21=$U20,W21=W20),AD20,IF(AND($L21=AD$4,P21=1),P21,0)))) -> 0 | AE21: =IF(AD21>1,AD21,IF(AND($P21>1,AE$4=$L21),$P21,IF(AND($U21=$U20,X21=X20),AE20,IF(AND($L21=AE$4,P21=1),P21,0)))) -> 0 | AF21: =IF(AE21>1,AE21,IF(AND($P21>1,AF$4=$L21),$P21,IF(AND($U21=$U20,Y21=Y20),AF20,IF(AND($L21=AF$4,P21=1),P21,0)))) -> 0 | AG21: =IF(AF21>1,AF21,IF(AND($P21>1,AG$4=$L21),$P21,IF(AND($U21=$U20,Z21=Z20),AG20,IF(AND($L21=AG$4,P21=1),P21,0)))) -> 0 | AH21: =IF(AND($P21=1,$L21=AH$4),2,IF(AND($L21<>AH$4,AH20=2),AH20,IF($L21<>AH$4,0,1))) -> 2 | AI21: =IF(OR(ROW()=5,$U20<>$U21),0,IF(AND($P21=1,$L21=AI$4),2,IF(AND($L21<>AI$4,AI20=2),AI20,IF($L21<>AI$4,0,1)))) -> 2 | AJ21: =IF(OR(ROW()=5,$U20<>$U21),0,IF(AND($P21=1,$L21=AJ$4),2,IF(AND($L21<>AJ$4,AJ20=2),AJ20,IF($L21<>AJ$4,0,1)))) -> 0 | AK21: =IF(OR(ROW()=5,$U20<>$U21),0,IF(AND($P21=1,$L21=AK$4),2,IF(AND($L21<>AK$4,AK20=2),AK20,IF($L21<>AK$4,0,1)))) -> 0 | AL21: =IF(OR(ROW()=5,$U20<>$U21),0,IF(AND($P21=1,$L21=AL$4),2,IF(AND($L21<>AL$4,AL20=2),AL20,IF($L21<>AL$4,0,1)))) -> 0
A22: 4641 | B22: A.3.1 | C22: Does the organization maintain an inventory of the applicable risks and controls included in the Enterprise Risk Management program? | D22: Yes | G22: Enterprise Risk Management | H22: Risk Assessments | I22: A.2 Risk Assessment Life Cycle | J22: 8.2 Information Security Risk Assessment | L22: 2 | M22: 3 | P22: =IF($L22="","",IF($D22="Yes",1,IF($D22="No",2,IF($D22="N/A",3,0)))) -> 1 | Q22: =IF(AND(Drops!$D$45>1,OR(U22<>U21,AND(ROW()=5,U21=U22))),VLOOKUP(U22,Drops!$D$26:$E$44,2,FALSE),"") | R22: =IF(Q22<>"",ROW(),"") | S22: =OFFSET(AC22,,L22-1) -> 1 | T22: =IF(OR(V22<>V21,U22<>U21,AND(V22<>V21,W22<>W21),AND(V22<>V21,W22<>W21,X22<>X21),AND(V22<>V21,W22<>W21,X22<>X21,Y22<>Y21),AND(V22<>V21,W22<>W21,X22<>X21,Y22<>Y21,Z22<>Z21),L22-L21>1),1,0) -> 0 | U22: A | V22: 3 | W22: 1 | X22: 0 | Y22: 0 | Z22: 0 | AA22: =IF(ROW()=5,1,IF(OR(AH22=1,P22>0,T22=1),1,IF(OR(AND(AH22=2,AI22=1),AND(AI22=2,AJ22=1),AND(AJ22=2,AK22=1),AND(AK22=2,AL22=1)),1,0))) -> 1 | AB22: =IF(L23>L22,1,0) -> 0 | AC22: =IF(ROW()=5,P22,IF(AND($P22>1,AC$4=$L22),$P22,IF(AND($U22=$U21,V22=V21),AC21,IF(AND($L22=AC$4,P22=1),P22,0)))) -> 1 | AD22: =IF(AC22>1,AC22,IF(AND($P22>1,AD$4=$L22),$P22,IF(AND($U22=$U21,W22=W21),AD21,IF(AND($L22=AD$4,P22=1),P22,0)))) -> 1 | AE22: =IF(AD22>1,AD22,IF(AND($P22>1,AE$4=$L22),$P22,IF(AND($U22=$U21,X22=X21),AE21,IF(AND($L22=AE$4,P22=1),P22,0)))) -> 0 | AF22: =IF(AE22>1,AE22,IF(AND($P22>1,AF$4=$L22),$P22,IF(AND($U22=$U21,Y22=Y21),AF21,IF(AND($L22=AF$4,P22=1),P22,0)))) -> 0 | AG22: =IF(AF22>1,AF22,IF(AND($P22>1,AG$4=$L22),$P22,IF(AND($U22=$U21,Z22=Z21),AG21,IF(AND($L22=AG$4,P22=1),P22,0)))) -> 0 | AH22: =IF(AND($P22=1,$L22=AH$4),2,IF(AND($L22<>AH$4,AH21=2),AH21,IF($L22<>AH$4,0,1))) -> 2 | AI22: =IF(OR(ROW()=5,$U21<>$U22),0,IF(AND($P22=1,$L22=AI$4),2,IF(AND($L22<>AI$4,AI21=2),AI21,IF($L22<>AI$4,0,1)))) -> 2 | AJ22: =IF(OR(ROW()=5,$U21<>$U22),0,IF(AND($P22=1,$L22=AJ$4),2,IF(AND($L22<>AJ$4,AJ21=2),AJ21,IF($L22<>AJ$4,0,1)))) -> 0 | AK22: =IF(OR(ROW()=5,$U21<>$U22),0,IF(AND($P22=1,$L22=AK$4),2,IF(AND($L22<>AK$4,AK21=2),AK21,IF($L22<>AK$4,0,1)))) -> 0 | AL22: =IF(OR(ROW()=5,$U21<>$U22),0,IF(AND($P22=1,$L22=AL$4),2,IF(AND($L22<>AL$4,AL21=2),AL21,IF($L22<>AL$4,0,1)))) -> 0
A23: 2409 | B23: A.3.6 | C23: Are critical processes and entities reassessed annually? | D23: Yes | G23: Enterprise Risk Management | H23: Risk Assessments | I23: A.4 IT Risk Assessments | J23: 8.2 Information Security Risk Assessment | L23: 2 | M23: 3 | P23: =IF($L23="","",IF($D23="Yes",1,IF($D23="No",2,IF($D23="N/A",3,0)))) -> 1 | Q23: =IF(AND(Drops!$D$45>1,OR(U23<>U22,AND(ROW()=5,U22=U23))),VLOOKUP(U23,Drops!$D$26:$E$44,2,FALSE),"") | R23: =IF(Q23<>"",ROW(),"") | S23: =OFFSET(AC23,,L23-1) -> 1 | T23: =IF(OR(V23<>V22,U23<>U22,AND(V23<>V22,W23<>W22),AND(V23<>V22,W23<>W22,X23<>X22),AND(V23<>V22,W23<>W22,X23<>X22,Y23<>Y22),AND(V23<>V22,W23<>W22,X23<>X22,Y23<>Y22,Z23<>Z22),L23-L22>1),1,0) -> 0 | U23: A | V23: 3 | W23: 6 | X23: 0 | Y23: 0 | Z23: 0 | AA23: =IF(ROW()=5,1,IF(OR(AH23=1,P23>0,T23=1),1,IF(OR(AND(AH23=2,AI23=1),AND(AI23=2,AJ23=1),AND(AJ23=2,AK23=1),AND(AK23=2,AL23=1)),1,0))) -> 1 | AB23: =IF(L24>L23,1,0) -> 0 | AC23: =IF(ROW()=5,P23,IF(AND($P23>1,AC$4=$L23),$P23,IF(AND($U23=$U22,V23=V22),AC22,IF(AND($L23=AC$4,P23=1),P23,0)))) -> 1 | AD23: =IF(AC23>1,AC23,IF(AND($P23>1,AD$4=$L23),$P23,IF(AND($U23=$U22,W23=W22),AD22,IF(AND($L23=AD$4,P23=1),P23,0)))) -> 1 | AE23: =IF(AD23>1,AD23,IF(AND($P23>1,AE$4=$L23),$P23,IF(AND($U23=$U22,X23=X22),AE22,IF(AND($L23=AE$4,P23=1),P23,0)))) -> 0 | AF23: =IF(AE23>1,AE23,IF(AND($P23>1,AF$4=$L23),$P23,IF(AND($U23=$U22,Y23=Y22),AF22,IF(AND($L23=AF$4,P23=1),P23,0)))) -> 0 | AG23: =IF(AF23>1,AF23,IF(AND($P23>1,AG$4=$L23),$P23,IF(AND($U23=$U22,Z23=Z22),AG22,IF(AND($L23=AG$4,P23=1),P23,0)))) -> 0 | AH23: =IF(AND($P23=1,$L23=AH$4),2,IF(AND($L23<>AH$4,AH22=2),AH22,IF($L23<>AH$4,0,1))) -> 2 | AI23: =IF(OR(ROW()=5,$U22<>$U23),0,IF(AND($P23=1,$L23=AI$4),2,IF(AND($L23<>AI$4,AI22=2),AI22,IF($L23<>AI$4,0,1)))) -> 2 | AJ23: =IF(OR(ROW()=5,$U22<>$U23),0,IF(AND($P23=1,$L23=AJ$4),2,IF(AND($L23<>AJ$4,AJ22=2),AJ22,IF($L23<>AJ$4,0,1)))) -> 0 | AK23: =IF(OR(ROW()=5,$U22<>$U23),0,IF(AND($P23=1,$L23=AK$4),2,IF(AND($L23<>AK$4,AK22=2),AK22,IF($L23<>AK$4,0,1)))) -> 0 | AL23: =IF(OR(ROW()=5,$U22<>$U23),0,IF(AND($P23=1,$L23=AL$4),2,IF(AND($L23<>AL$4,AL22=2),AL22,IF($L23<>AL$4,0,1)))) -> 0
A24: 5843 | B24: A.3.7 | C24: Does the organization have a process in place for justifying why a specific control may be omitted from its information security risk treatment program? | D24: Yes | G24: Enterprise Risk Management | H24: Risk Assessments | J24: 6.1.3 Information Security Risk Treatment | L24: 2 | M24: 3 | P24: =IF($L24="","",IF($D24="Yes",1,IF($D24="No",2,IF($D24="N/A",3,0)))) -> 1 | Q24: =IF(AND(Drops!$D$45>1,OR(U24<>U23,AND(ROW()=5,U23=U24))),VLOOKUP(U24,Drops!$D$26:$E$44,2,FALSE),"") | R24: =IF(Q24<>"",ROW(),"") | S24: =OFFSET(AC24,,L24-1) -> 1 | T24: =IF(OR(V24<>V23,U24<>U23,AND(V24<>V23,W24<>W23),AND(V24<>V23,W24<>W23,X24<>X23),AND(V24<>V23,W24<>W23,X24<>X23,Y24<>Y23),AND(V24<>V23,W24<>W23,X24<>X23,Y24<>Y23,Z24<>Z23),L24-L23>1),1,0) -> 0 | U24: A | V24: 3 | W24: 7 | X24: 0 | Y24: 0 | Z24: 0 | AA24: =IF(ROW()=5,1,IF(OR(AH24=1,P24>0,T24=1),1,IF(OR(AND(AH24=2,AI24=1),AND(AI24=2,AJ24=1),AND(AJ24=2,AK24=1),AND(AK24=2,AL24=1)),1,0))) -> 1 | AB24: =IF(L25>L24,1,0) -> 0 | AC24: =IF(ROW()=5,P24,IF(AND($P24>1,AC$4=$L24),$P24,IF(AND($U24=$U23,V24=V23),AC23,IF(AND($L24=AC$4,P24=1),P24,0)))) -> 1 | AD24: =IF(AC24>1,AC24,IF(AND($P24>1,AD$4=$L24),$P24,IF(AND($U24=$U23,W24=W23),AD23,IF(AND($L24=AD$4,P24=1),P24,0)))) -> 1 | AE24: =IF(AD24>1,AD24,IF(AND($P24>1,AE$4=$L24),$P24,IF(AND($U24=$U23,X24=X23),AE23,IF(AND($L24=AE$4,P24=1),P24,0)))) -> 0 | AF24: =IF(AE24>1,AE24,IF(AND($P24>1,AF$4=$L24),$P24,IF(AND($U24=$U23,Y24=Y23),AF23,IF(AND($L24=AF$4,P24=1),P24,0)))) -> 0 | AG24: =IF(AF24>1,AF24,IF(AND($P24>1,AG$4=$L24),$P24,IF(AND($U24=$U23,Z24=Z23),AG23,IF(AND($L24=AG$4,P24=1),P24,0)))) -> 0 | AH24: =IF(AND($P24=1,$L24=AH$4),2,IF(AND($L24<>AH$4,AH23=2),AH23,IF($L24<>AH$4,0,1))) -> 2 | AI24: =IF(OR(ROW()=5,$U23<>$U24),0,IF(AND($P24=1,$L24=AI$4),2,IF(AND($L24<>AI$4,AI23=2),AI23,IF($L24<>AI$4,0,1)))) -> 2 | AJ24: =IF(OR(ROW()=5,$U23<>$U24),0,IF(AND($P24=1,$L24=AJ$4),2,IF(AND($L24<>AJ$4,AJ23=2),AJ23,IF($L24<>AJ$4,0,1)))) -> 0 | AK24: =IF(OR(ROW()=5,$U23<>$U24),0,IF(AND($P24=1,$L24=AK$4),2,IF(AND($L24<>AK$4,AK23=2),AK23,IF($L24<>AK$4,0,1)))) -> 0 | AL24: =IF(OR(ROW()=5,$U23<>$U24),0,IF(AND($P24=1,$L24=AL$4),2,IF(AND($L24<>AL$4,AL23=2),AL23,IF($L24<>AL$4,0,1)))) -> 0
A25: 3286 | B25: A.3.8 | C25: Is there a process to identify and manage the risk response and treatment of risks? | D25: Yes | E25: For areas where new risks are identified or existing controls are assessed as insufficient, the risk may be dealt with by: eliminating the risk by discontinuing the activity associated with the risk or declining to begin a new activity associated with the risk; removing the source of the risk; putting measures in place (policies, procedures, tools, patches) to mitigate the risk and reduce it to acceptable levels; sharing the risk with other parties; and/or proceeding with an informed decision and plan to monitor risk. | G25: Enterprise Risk Management | H25: Risk Treatment | I25: A.4 IT Risk Assessments | J25: 6.1.1 General|6.1.2 Information Security Risk Asssessment|6.1.3 Information Security Risk Treatment|8.3 Information Security Risk Treatment | L25: 2 | M25: 2 | P25: =IF($L25="","",IF($D25="Yes",1,IF($D25="No",2,IF($D25="N/A",3,0)))) -> 1 | Q25: =IF(AND(Drops!$D$45>1,OR(U25<>U24,AND(ROW()=5,U24=U25))),VLOOKUP(U25,Drops!$D$26:$E$44,2,FALSE),"") | R25: =IF(Q25<>"",ROW(),"") | S25: =OFFSET(AC25,,L25-1) -> 1 | T25: =IF(OR(V25<>V24,U25<>U24,AND(V25<>V24,W25<>W24),AND(V25<>V24,W25<>W24,X25<>X24),AND(V25<>V24,W25<>W24,X25<>X24,Y25<>Y24),AND(V25<>V24,W25<>W24,X25<>X24,Y25<>Y24,Z25<>Z24),L25-L24>1),1,0) -> 0 | U25: A | V25: 3 | W25: 8 | X25: 0 | Y25: 0 | Z25: 0 | AA25: =IF(ROW()=5,1,IF(OR(AH25=1,P25>0,T25=1),1,IF(OR(AND(AH25=2,AI25=1),AND(AI25=2,AJ25=1),AND(AJ25=2,AK25=1),AND(AK25=2,AL25=1)),1,0))) -> 1 | AB25: =IF(L26>L25,1,0) -> 0 | AC25: =IF(ROW()=5,P25,IF(AND($P25>1,AC$4=$L25),$P25,IF(AND($U25=$U24,V25=V24),AC24,IF(AND($L25=AC$4,P25=1),P25,0)))) -> 1 | AD25: =IF(AC25>1,AC25,IF(AND($P25>1,AD$4=$L25),$P25,IF(AND($U25=$U24,W25=W24),AD24,IF(AND($L25=AD$4,P25=1),P25,0)))) -> 1 | AE25: =IF(AD25>1,AD25,IF(AND($P25>1,AE$4=$L25),$P25,IF(AND($U25=$U24,X25=X24),AE24,IF(AND($L25=AE$4,P25=1),P25,0)))) -> 0 | AF25: =IF(AE25>1,AE25,IF(AND($P25>1,AF$4=$L25),$P25,IF(AND($U25=$U24,Y25=Y24),AF24,IF(AND($L25=AF$4,P25=1),P25,0)))) -> 0 | AG25: =IF(AF25>1,AF25,IF(AND($P25>1,AG$4=$L25),$P25,IF(AND($U25=$U24,Z25=Z24),AG24,IF(AND($L25=AG$4,P25=1),P25,0)))) -> 0 | AH25: =IF(AND($P25=1,$L25=AH$4),2,IF(AND($L25<>AH$4,AH24=2),AH24,IF($L25<>AH$4,0,1))) -> 2 | AI25: =IF(OR(ROW()=5,$U24<>$U25),0,IF(AND($P25=1,$L25=AI$4),2,IF(AND($L25<>AI$4,AI24=2),AI24,IF($L25<>AI$4,0,1)))) -> 2 | AJ25: =IF(OR(ROW()=5,$U24<>$U25),0,IF(AND($P25=1,$L25=AJ$4),2,IF(AND($L25<>AJ$4,AJ24=2),AJ24,IF($L25<>AJ$4,0,1)))) -> 0 | AK25: =IF(OR(ROW()=5,$U24<>$U25),0,IF(AND($P25=1,$L25=AK$4),2,IF(AND($L25<>AK$4,AK24=2),AK24,IF($L25<>AK$4,0,1)))) -> 0 | AL25: =IF(OR(ROW()=5,$U24<>$U25),0,IF(AND($P25=1,$L25=AL$4),2,IF(AND($L25<>AL$4,AL24=2),AL24,IF($L25<>AL$4,0,1)))) -> 0
A26: 4158 | B26: A.3.9 | C26: Does the risk treatment program include a formal process for assigning appropriate management ownership for risk decisions? | D26: Yes | G26: Enterprise Risk Management | H26: Risk Treatment | I26: A.1 Enterprise Risk Governance | J26: 6.1.1 General|6.1.3 Information Security Risk Treatment|8.3 Information Security Risk Treatment | L26: 2 | M26: 3 | P26: =IF($L26="","",IF($D26="Yes",1,IF($D26="No",2,IF($D26="N/A",3,0)))) -> 1 | Q26: =IF(AND(Drops!$D$45>1,OR(U26<>U25,AND(ROW()=5,U25=U26))),VLOOKUP(U26,Drops!$D$26:$E$44,2,FALSE),"") | R26: =IF(Q26<>"",ROW(),"") | S26: =OFFSET(AC26,,L26-1) -> 1 | T26: =IF(OR(V26<>V25,U26<>U25,AND(V26<>V25,W26<>W25),AND(V26<>V25,W26<>W25,X26<>X25),AND(V26<>V25,W26<>W25,X26<>X25,Y26<>Y25),AND(V26<>V25,W26<>W25,X26<>X25,Y26<>Y25,Z26<>Z25),L26-L25>1),1,0) -> 0 | U26: A | V26: 3 | W26: 9 | X26: 0 | Y26: 0 | Z26: 0 | AA26: =IF(ROW()=5,1,IF(OR(AH26=1,P26>0,T26=1),1,IF(OR(AND(AH26=2,AI26=1),AND(AI26=2,AJ26=1),AND(AJ26=2,AK26=1),AND(AK26=2,AL26=1)),1,0))) -> 1 | AB26: =IF(L27>L26,1,0) -> 0 | AC26: =IF(ROW()=5,P26,IF(AND($P26>1,AC$4=$L26),$P26,IF(AND($U26=$U25,V26=V25),AC25,IF(AND($L26=AC$4,P26=1),P26,0)))) -> 1 | AD26: =IF(AC26>1,AC26,IF(AND($P26>1,AD$4=$L26),$P26,IF(AND($U26=$U25,W26=W25),AD25,IF(AND($L26=AD$4,P26=1),P26,0)))) -> 1 | AE26: =IF(AD26>1,AD26,IF(AND($P26>1,AE$4=$L26),$P26,IF(AND($U26=$U25,X26=X25),AE25,IF(AND($L26=AE$4,P26=1),P26,0)))) -> 0 | AF26: =IF(AE26>1,AE26,IF(AND($P26>1,AF$4=$L26),$P26,IF(AND($U26=$U25,Y26=Y25),AF25,IF(AND($L26=AF$4,P26=1),P26,0)))) -> 0 | AG26: =IF(AF26>1,AF26,IF(AND($P26>1,AG$4=$L26),$P26,IF(AND($U26=$U25,Z26=Z25),AG25,IF(AND($L26=AG$4,P26=1),P26,0)))) -> 0 | AH26: =IF(AND($P26=1,$L26=AH$4),2,IF(AND($L26<>AH$4,AH25=2),AH25,IF($L26<>AH$4,0,1))) -> 2 | AI26: =IF(OR(ROW()=5,$U25<>$U26),0,IF(AND($P26=1,$L26=AI$4),2,IF(AND($L26<>AI$4,AI25=2),AI25,IF($L26<>AI$4,0,1)))) -> 2 | AJ26: =IF(OR(ROW()=5,$U25<>$U26),0,IF(AND($P26=1,$L26=AJ$4),2,IF(AND($L26<>AJ$4,AJ25=2),AJ25,IF($L26<>AJ$4,0,1)))) -> 0 | AK26: =IF(OR(ROW()=5,$U25<>$U26),0,IF(AND($P26=1,$L26=AK$4),2,IF(AND($L26<>AK$4,AK25=2),AK25,IF($L26<>AK$4,0,1)))) -> 0 | AL26: =IF(OR(ROW()=5,$U25<>$U26),0,IF(AND($P26=1,$L26=AL$4),2,IF(AND($L26<>AL$4,AL25=2),AL25,IF($L26<>AL$4,0,1)))) -> 0
A27: 4159 | B27: A.3.10 | C27: Does the risk treatment program include a formal process for accepting risks and approving action plans? | D27: Yes | G27: Enterprise Risk Management | H27: Risk Treatment | I27: A.2 Risk Assessment Life Cycle | J27: 6.1.1 General|6.1.3 Information Security Risk Treatment|8.3 Information Security Risk Treatment | L27: 2 | M27: 3 | P27: =IF($L27="","",IF($D27="Yes",1,IF($D27="No",2,IF($D27="N/A",3,0)))) -> 1 | Q27: =IF(AND(Drops!$D$45>1,OR(U27<>U26,AND(ROW()=5,U26=U27))),VLOOKUP(U27,Drops!$D$26:$E$44,2,FALSE),"") | R27: =IF(Q27<>"",ROW(),"") | S27: =OFFSET(AC27,,L27-1) -> 1 | T27: =IF(OR(V27<>V26,U27<>U26,AND(V27<>V26,W27<>W26),AND(V27<>V26,W27<>W26,X27<>X26),AND(V27<>V26,W27<>W26,X27<>X26,Y27<>Y26),AND(V27<>V26,W27<>W26,X27<>X26,Y27<>Y26,Z27<>Z26),L27-L26>1),1,0) -> 0 | U27: A | V27: 3 | W27: 10 | X27: 0 | Y27: 0 | Z27: 0 | AA27: =IF(ROW()=5,1,IF(OR(AH27=1,P27>0,T27=1),1,IF(OR(AND(AH27=2,AI27=1),AND(AI27=2,AJ27=1),AND(AJ27=2,AK27=1),AND(AK27=2,AL27=1)),1,0))) -> 1 | AB27: =IF(L28>L27,1,0) -> 0 | AC27: =IF(ROW()=5,P27,IF(AND($P27>1,AC$4=$L27),$P27,IF(AND($U27=$U26,V27=V26),AC26,IF(AND($L27=AC$4,P27=1),P27,0)))) -> 1 | AD27: =IF(AC27>1,AC27,IF(AND($P27>1,AD$4=$L27),$P27,IF(AND($U27=$U26,W27=W26),AD26,IF(AND($L27=AD$4,P27=1),P27,0)))) -> 1 | AE27: =IF(AD27>1,AD27,IF(AND($P27>1,AE$4=$L27),$P27,IF(AND($U27=$U26,X27=X26),AE26,IF(AND($L27=AE$4,P27=1),P27,0)))) -> 0 | AF27: =IF(AE27>1,AE27,IF(AND($P27>1,AF$4=$L27),$P27,IF(AND($U27=$U26,Y27=Y26),AF26,IF(AND($L27=AF$4,P27=1),P27,0)))) -> 0 | AG27: =IF(AF27>1,AF27,IF(AND($P27>1,AG$4=$L27),$P27,IF(AND($U27=$U26,Z27=Z26),AG26,IF(AND($L27=AG$4,P27=1),P27,0)))) -> 0 | AH27: =IF(AND($P27=1,$L27=AH$4),2,IF(AND($L27<>AH$4,AH26=2),AH26,IF($L27<>AH$4,0,1))) -> 2 | AI27: =IF(OR(ROW()=5,$U26<>$U27),0,IF(AND($P27=1,$L27=AI$4),2,IF(AND($L27<>AI$4,AI26=2),AI26,IF($L27<>AI$4,0,1)))) -> 2 | AJ27: =IF(OR(ROW()=5,$U26<>$U27),0,IF(AND($P27=1,$L27=AJ$4),2,IF(AND($L27<>AJ$4,AJ26=2),AJ26,IF($L27<>AJ$4,0,1)))) -> 0 | AK27: =IF(OR(ROW()=5,$U26<>$U27),0,IF(AND($P27=1,$L27=AK$4),2,IF(AND($L27<>AK$4,AK26=2),AK26,IF($L27<>AK$4,0,1)))) -> 0 | AL27: =IF(OR(ROW()=5,$U26<>$U27),0,IF(AND($P27=1,$L27=AL$4),2,IF(AND($L27<>AL$4,AL26=2),AL26,IF($L27<>AL$4,0,1)))) -> 0
A28: 4160 | B28: A.3.11 | C28: Does the risk treatment program include a formal program for accepting risks and prioritizing and approving action plans? | D28: Yes | G28: Enterprise Risk Management | H28: Risk Treatment | I28: A.1 Enterprise Risk Governance | J28: 6.1.1 General|6.1.2 Information Security Risk Asssessment|6.1.3 Information Security Risk Treatment|8.3 Information Security Risk Treatment | L28: 2 | M28: 3 | P28: =IF($L28="","",IF($D28="Yes",1,IF($D28="No",2,IF($D28="N/A",3,0)))) -> 1 | Q28: =IF(AND(Drops!$D$45>1,OR(U28<>U27,AND(ROW()=5,U27=U28))),VLOOKUP(U28,Drops!$D$26:$E$44,2,FALSE),"") | R28: =IF(Q28<>"",ROW(),"") | S28: =OFFSET(AC28,,L28-1) -> 1 | T28: =IF(OR(V28<>V27,U28<>U27,AND(V28<>V27,W28<>W27),AND(V28<>V27,W28<>W27,X28<>X27),AND(V28<>V27,W28<>W27,X28<>X27,Y28<>Y27),AND(V28<>V27,W28<>W27,X28<>X27,Y28<>Y27,Z28<>Z27),L28-L27>1),1,0) -> 0 | U28: A | V28: 3 | W28: 11 | X28: 0 | Y28: 0 | Z28: 0 | AA28: =IF(ROW()=5,1,IF(OR(AH28=1,P28>0,T28=1),1,IF(OR(AND(AH28=2,AI28=1),AND(AI28=2,AJ28=1),AND(AJ28=2,AK28=1),AND(AK28=2,AL28=1)),1,0))) -> 1 | AB28: =IF(L29>L28,1,0) -> 0 | AC28: =IF(ROW()=5,P28,IF(AND($P28>1,AC$4=$L28),$P28,IF(AND($U28=$U27,V28=V27),AC27,IF(AND($L28=AC$4,P28=1),P28,0)))) -> 1 | AD28: =IF(AC28>1,AC28,IF(AND($P28>1,AD$4=$L28),$P28,IF(AND($U28=$U27,W28=W27),AD27,IF(AND($L28=AD$4,P28=1),P28,0)))) -> 1 | AE28: =IF(AD28>1,AD28,IF(AND($P28>1,AE$4=$L28),$P28,IF(AND($U28=$U27,X28=X27),AE27,IF(AND($L28=AE$4,P28=1),P28,0)))) -> 0 | AF28: =IF(AE28>1,AE28,IF(AND($P28>1,AF$4=$L28),$P28,IF(AND($U28=$U27,Y28=Y27),AF27,IF(AND($L28=AF$4,P28=1),P28,0)))) -> 0 | AG28: =IF(AF28>1,AF28,IF(AND($P28>1,AG$4=$L28),$P28,IF(AND($U28=$U27,Z28=Z27),AG27,IF(AND($L28=AG$4,P28=1),P28,0)))) -> 0 | AH28: =IF(AND($P28=1,$L28=AH$4),2,IF(AND($L28<>AH$4,AH27=2),AH27,IF($L28<>AH$4,0,1))) -> 2 | AI28: =IF(OR(ROW()=5,$U27<>$U28),0,IF(AND($P28=1,$L28=AI$4),2,IF(AND($L28<>AI$4,AI27=2),AI27,IF($L28<>AI$4,0,1)))) -> 2 | AJ28: =IF(OR(ROW()=5,$U27<>$U28),0,IF(AND($P28=1,$L28=AJ$4),2,IF(AND($L28<>AJ$4,AJ27=2),AJ27,IF($L28<>AJ$4,0,1)))) -> 0 | AK28: =IF(OR(ROW()=5,$U27<>$U28),0,IF(AND($P28=1,$L28=AK$4),2,IF(AND($L28<>AK$4,AK27=2),AK27,IF($L28<>AK$4,0,1)))) -> 0 | AL28: =IF(OR(ROW()=5,$U27<>$U28),0,IF(AND($P28=1,$L28=AL$4),2,IF(AND($L28<>AL$4,AL27=2),AL27,IF($L28<>AL$4,0,1)))) -> 0
A29: 4161 | B29: A.3.12 | C29: Does the risk treatment program include creation of internal controls if material risks are identified? | D29: Yes | G29: Enterprise Risk Management | H29: Risk Treatment | J29: 6.1.1 General|6.1.3 Information Security Risk Treatment|8.3 Information Security Risk Treatment | L29: 2 | M29: 3 | P29: =IF($L29="","",IF($D29="Yes",1,IF($D29="No",2,IF($D29="N/A",3,0)))) -> 1 | Q29: =IF(AND(Drops!$D$45>1,OR(U29<>U28,AND(ROW()=5,U28=U29))),VLOOKUP(U29,Drops!$D$26:$E$44,2,FALSE),"") | R29: =IF(Q29<>"",ROW(),"") | S29: =OFFSET(AC29,,L29-1) -> 1 | T29: =IF(OR(V29<>V28,U29<>U28,AND(V29<>V28,W29<>W28),AND(V29<>V28,W29<>W28,X29<>X28),AND(V29<>V28,W29<>W28,X29<>X28,Y29<>Y28),AND(V29<>V28,W29<>W28,X29<>X28,Y29<>Y28,Z29<>Z28),L29-L28>1),1,0) -> 0 | U29: A | V29: 3 | W29: 12 | X29: 0 | Y29: 0 | Z29: 0 | AA29: =IF(ROW()=5,1,IF(OR(AH29=1,P29>0,T29=1),1,IF(OR(AND(AH29=2,AI29=1),AND(AI29=2,AJ29=1),AND(AJ29=2,AK29=1),AND(AK29=2,AL29=1)),1,0))) -> 1 | AB29: =IF(L30>L29,1,0) -> 0 | AC29: =IF(ROW()=5,P29,IF(AND($P29>1,AC$4=$L29),$P29,IF(AND($U29=$U28,V29=V28),AC28,IF(AND($L29=AC$4,P29=1),P29,0)))) -> 1 | AD29: =IF(AC29>1,AC29,IF(AND($P29>1,AD$4=$L29),$P29,IF(AND($U29=$U28,W29=W28),AD28,IF(AND($L29=AD$4,P29=1),P29,0)))) -> 1 | AE29: =IF(AD29>1,AD29,IF(AND($P29>1,AE$4=$L29),$P29,IF(AND($U29=$U28,X29=X28),AE28,IF(AND($L29=AE$4,P29=1),P29,0)))) -> 0 | AF29: =IF(AE29>1,AE29,IF(AND($P29>1,AF$4=$L29),$P29,IF(AND($U29=$U28,Y29=Y28),AF28,IF(AND($L29=AF$4,P29=1),P29,0)))) -> 0 | AG29: =IF(AF29>1,AF29,IF(AND($P29>1,AG$4=$L29),$P29,IF(AND($U29=$U28,Z29=Z28),AG28,IF(AND($L29=AG$4,P29=1),P29,0)))) -> 0 | AH29: =IF(AND($P29=1,$L29=AH$4),2,IF(AND($L29<>AH$4,AH28=2),AH28,IF($L29<>AH$4,0,1))) -> 2 | AI29: =IF(OR(ROW()=5,$U28<>$U29),0,IF(AND($P29=1,$L29=AI$4),2,IF(AND($L29<>AI$4,AI28=2),AI28,IF($L29<>AI$4,0,1)))) -> 2 | AJ29: =IF(OR(ROW()=5,$U28<>$U29),0,IF(AND($P29=1,$L29=AJ$4),2,IF(AND($L29<>AJ$4,AJ28=2),AJ28,IF($L29<>AJ$4,0,1)))) -> 0 | AK29: =IF(OR(ROW()=5,$U28<>$U29),0,IF(AND($P29=1,$L29=AK$4),2,IF(AND($L29<>AK$4,AK28=2),AK28,IF($L29<>AK$4,0,1)))) -> 0 | AL29: =IF(OR(ROW()=5,$U28<>$U29),0,IF(AND($P29=1,$L29=AL$4),2,IF(AND($L29<>AL$4,AL28=2),AL28,IF($L29<>AL$4,0,1)))) -> 0
A30: 4162 | B30: A.4 | C30: Does the Enterprise Risk Management program include measures for defining, monitoring, and reporting risk metrics? | D30: Yes | G30: Enterprise Risk Management | H30: Risk Reporting | I30: A.1 Enterprise Risk Governance | J30: 6.1.1 General|6.1.3 Information Security Risk Treatment | L30: 1 | M30: 3 | P30: =IF($L30="","",IF($D30="Yes",1,IF($D30="No",2,IF($D30="N/A",3,0)))) -> 1 | Q30: =IF(AND(Drops!$D$45>1,OR(U30<>U29,AND(ROW()=5,U29=U30))),VLOOKUP(U30,Drops!$D$26:$E$44,2,FALSE),"") | R30: =IF(Q30<>"",ROW(),"") | S30: =OFFSET(AC30,,L30-1) -> 1 | T30: =IF(OR(V30<>V29,U30<>U29,AND(V30<>V29,W30<>W29),AND(V30<>V29,W30<>W29,X30<>X29),AND(V30<>V29,W30<>W29,X30<>X29,Y30<>Y29),AND(V30<>V29,W30<>W29,X30<>X29,Y30<>Y29,Z30<>Z29),L30-L29>1),1,0) -> 1 | U30: A | V30: 4 | W30: 0 | X30: 0 | Y30: 0 | Z30: 0 | AA30: =IF(ROW()=5,1,IF(OR(AH30=1,P30>0,T30=1),1,IF(OR(AND(AH30=2,AI30=1),AND(AI30=2,AJ30=1),AND(AJ30=2,AK30=1),AND(AK30=2,AL30=1)),1,0))) -> 1 | AB30: =IF(L31>L30,1,0) -> 0 | AC30: =IF(ROW()=5,P30,IF(AND($P30>1,AC$4=$L30),$P30,IF(AND($U30=$U29,V30=V29),AC29,IF(AND($L30=AC$4,P30=1),P30,0)))) -> 1 | AD30: =IF(AC30>1,AC30,IF(AND($P30>1,AD$4=$L30),$P30,IF(AND($U30=$U29,W30=W29),AD29,IF(AND($L30=AD$4,P30=1),P30,0)))) -> 0 | AE30: =IF(AD30>1,AD30,IF(AND($P30>1,AE$4=$L30),$P30,IF(AND($U30=$U29,X30=X29),AE29,IF(AND($L30=AE$4,P30=1),P30,0)))) -> 0 | AF30: =IF(AE30>1,AE30,IF(AND($P30>1,AF$4=$L30),$P30,IF(AND($U30=$U29,Y30=Y29),AF29,IF(AND($L30=AF$4,P30=1),P30,0)))) -> 0 | AG30: =IF(AF30>1,AF30,IF(AND($P30>1,AG$4=$L30),$P30,IF(AND($U30=$U29,Z30=Z29),AG29,IF(AND($L30=AG$4,P30=1),P30,0)))) -> 0 | AH30: =IF(AND($P30=1,$L30=AH$4),2,IF(AND($L30<>AH$4,AH29=2),AH29,IF($L30<>AH$4,0,1))) -> 2 | AI30: =IF(OR(ROW()=5,$U29<>$U30),0,IF(AND($P30=1,$L30=AI$4),2,IF(AND($L30<>AI$4,AI29=2),AI29,IF($L30<>AI$4,0,1)))) -> 2 | AJ30: =IF(OR(ROW()=5,$U29<>$U30),0,IF(AND($P30=1,$L30=AJ$4),2,IF(AND($L30<>AJ$4,AJ29=2),AJ29,IF($L30<>AJ$4,0,1)))) -> 0 | AK30: =IF(OR(ROW()=5,$U29<>$U30),0,IF(AND($P30=1,$L30=AK$4),2,IF(AND($L30<>AK$4,AK29=2),AK29,IF($L30<>AK$4,0,1)))) -> 0 | AL30: =IF(OR(ROW()=5,$U29<>$U30),0,IF(AND($P30=1,$L30=AL$4),2,IF(AND($L30<>AL$4,AL29=2),AL29,IF($L30<>AL$4,0,1)))) -> 0
A31: 71 | B31: A.5 | C31: Do subcontractors (e.g., backup vendors, service providers, equipment support maintenance, software maintenance vendors, data recovery vendors, hosting providers, etc.) have access to scoped systems and data or processing facilities? | D31: Yes | E31: AWS provides data center hosting | G31: Third Party Risk Management | H31: Subcontractor Selection and Management Process | L31: 1 | M31: 1 | P31: =IF($L31="","",IF($D31="Yes",1,IF($D31="No",2,IF($D31="N/A",3,0)))) -> 1 | Q31: =IF(AND(Drops!$D$45>1,OR(U31<>U30,AND(ROW()=5,U30=U31))),VLOOKUP(U31,Drops!$D$26:$E$44,2,FALSE),"") | R31: =IF(Q31<>"",ROW(),"") | S31: =OFFSET(AC31,,L31-1) -> 1 | T31: =IF(OR(V31<>V30,U31<>U30,AND(V31<>V30,W31<>W30),AND(V31<>V30,W31<>W30,X31<>X30),AND(V31<>V30,W31<>W30,X31<>X30,Y31<>Y30),AND(V31<>V30,W31<>W30,X31<>X30,Y31<>Y30,Z31<>Z30),L31-L30>1),1,0) -> 1 | U31: A | V31: 5 | W31: 0 | X31: 0 | Y31: 0 | Z31: 0 | AA31: =IF(ROW()=5,1,IF(OR(AH31=1,P31>0,T31=1),1,IF(OR(AND(AH31=2,AI31=1),AND(AI31=2,AJ31=1),AND(AJ31=2,AK31=1),AND(AK31=2,AL31=1)),1,0))) -> 1 | AB31: =IF(L32>L31,1,0) -> 1 | AC31: =IF(ROW()=5,P31,IF(AND($P31>1,AC$4=$L31),$P31,IF(AND($U31=$U30,V31=V30),AC30,IF(AND($L31=AC$4,P31=1),P31,0)))) -> 1 | AD31: =IF(AC31>1,AC31,IF(AND($P31>1,AD$4=$L31),$P31,IF(AND($U31=$U30,W31=W30),AD30,IF(AND($L31=AD$4,P31=1),P31,0)))) -> 0 | AE31: =IF(AD31>1,AD31,IF(AND($P31>1,AE$4=$L31),$P31,IF(AND($U31=$U30,X31=X30),AE30,IF(AND($L31=AE$4,P31=1),P31,0)))) -> 0 | AF31: =IF(AE31>1,AE31,IF(AND($P31>1,AF$4=$L31),$P31,IF(AND($U31=$U30,Y31=Y30),AF30,IF(AND($L31=AF$4,P31=1),P31,0)))) -> 0 | AG31: =IF(AF31>1,AF31,IF(AND($P31>1,AG$4=$L31),$P31,IF(AND($U31=$U30,Z31=Z30),AG30,IF(AND($L31=AG$4,P31=1),P31,0)))) -> 0 | AH31: =IF(AND($P31=1,$L31=AH$4),2,IF(AND($L31<>AH$4,AH30=2),AH30,IF($L31<>AH$4,0,1))) -> 2 | AI31: =IF(OR(ROW()=5,$U30<>$U31),0,IF(AND($P31=1,$L31=AI$4),2,IF(AND($L31<>AI$4,AI30=2),AI30,IF($L31<>AI$4,0,1)))) -> 2 | AJ31: =IF(OR(ROW()=5,$U30<>$U31),0,IF(AND($P31=1,$L31=AJ$4),2,IF(AND($L31<>AJ$4,AJ30=2),AJ30,IF($L31<>AJ$4,0,1)))) -> 0 | AK31: =IF(OR(ROW()=5,$U30<>$U31),0,IF(AND($P31=1,$L31=AK$4),2,IF(AND($L31<>AK$4,AK30=2),AK30,IF($L31<>AK$4,0,1)))) -> 0 | AL31: =IF(OR(ROW()=5,$U30<>$U31),0,IF(AND($P31=1,$L31=AL$4),2,IF(AND($L31<>AL$4,AL30=2),AL30,IF($L31<>AL$4,0,1)))) -> 0
A32: 3897 | B32: A.5.1 | C32: Is there a documented third party risk management program in place for the selection, oversight and risk assessment of Subcontractors e.g., service providers, dependent service providers, sub-processors? | D32: Yes | G32: Third Party Risk Management | H32: Subcontractor Selection and Management Process | I32: A.5 Third Party Risk Management Program | J32: 15.1.1 Information Security Policy for Supplier Relationships|15.2.1 Monitoring and Review of Supplier Services|15.2.2 Managing Changes to Supplier Services | L32: 2 | M32: 2 | P32: =IF($L32="","",IF($D32="Yes",1,IF($D32="No",2,IF($D32="N/A",3,0)))) -> 1 | Q32: =IF(AND(Drops!$D$45>1,OR(U32<>U31,AND(ROW()=5,U31=U32))),VLOOKUP(U32,Drops!$D$26:$E$44,2,FALSE),"") | R32: =IF(Q32<>"",ROW(),"") | S32: =OFFSET(AC32,,L32-1) -> 1 | T32: =IF(OR(V32<>V31,U32<>U31,AND(V32<>V31,W32<>W31),AND(V32<>V31,W32<>W31,X32<>X31),AND(V32<>V31,W32<>W31,X32<>X31,Y32<>Y31),AND(V32<>V31,W32<>W31,X32<>X31,Y32<>Y31,Z32<>Z31),L32-L31>1),1,0) -> 0 | U32: A | V32: 5 | W32: 1 | X32: 0 | Y32: 0 | Z32: 0 | AA32: =IF(ROW()=5,1,IF(OR(AH32=1,P32>0,T32=1),1,IF(OR(AND(AH32=2,AI32=1),AND(AI32=2,AJ32=1),AND(AJ32=2,AK32=1),AND(AK32=2,AL32=1)),1,0))) -> 1 | AB32: =IF(L33>L32,1,0) -> 1 | AC32: =IF(ROW()=5,P32,IF(AND($P32>1,AC$4=$L32),$P32,IF(AND($U32=$U31,V32=V31),AC31,IF(AND($L32=AC$4,P32=1),P32,0)))) -> 1 | AD32: =IF(AC32>1,AC32,IF(AND($P32>1,AD$4=$L32),$P32,IF(AND($U32=$U31,W32=W31),AD31,IF(AND($L32=AD$4,P32=1),P32,0)))) -> 1 | AE32: =IF(AD32>1,AD32,IF(AND($P32>1,AE$4=$L32),$P32,IF(AND($U32=$U31,X32=X31),AE31,IF(AND($L32=AE$4,P32=1),P32,0)))) -> 0 | AF32: =IF(AE32>1,AE32,IF(AND($P32>1,AF$4=$L32),$P32,IF(AND($U32=$U31,Y32=Y31),AF31,IF(AND($L32=AF$4,P32=1),P32,0)))) -> 0 | AG32: =IF(AF32>1,AF32,IF(AND($P32>1,AG$4=$L32),$P32,IF(AND($U32=$U31,Z32=Z31),AG31,IF(AND($L32=AG$4,P32=1),P32,0)))) -> 0 | AH32: =IF(AND($P32=1,$L32=AH$4),2,IF(AND($L32<>AH$4,AH31=2),AH31,IF($L32<>AH$4,0,1))) -> 2 | AI32: =IF(OR(ROW()=5,$U31<>$U32),0,IF(AND($P32=1,$L32=AI$4),2,IF(AND($L32<>AI$4,AI31=2),AI31,IF($L32<>AI$4,0,1)))) -> 2 | AJ32: =IF(OR(ROW()=5,$U31<>$U32),0,IF(AND($P32=1,$L32=AJ$4),2,IF(AND($L32<>AJ$4,AJ31=2),AJ31,IF($L32<>AJ$4,0,1)))) -> 0 | AK32: =IF(OR(ROW()=5,$U31<>$U32),0,IF(AND($P32=1,$L32=AK$4),2,IF(AND($L32<>AK$4,AK31=2),AK31,IF($L32<>AK$4,0,1)))) -> 0 | AL32: =IF(OR(ROW()=5,$U31<>$U32),0,IF(AND($P32=1,$L32=AL$4),2,IF(AND($L32<>AL$4,AL31=2),AL31,IF($L32<>AL$4,0,1)))) -> 0
A33: 4647 | B33: A.5.1.1 | C33: Does the third party risk management program have a governing body accountable for the selection, oversight and risk assessment of subcontractors? | D33: Yes | G33: Third Party Risk Management | H33: Subcontractor Selection and Management Process | I33: A.5 Third Party Risk Management Program | L33: 3 | M33: 3 | P33: =IF($L33="","",IF($D33="Yes",1,IF($D33="No",2,IF($D33="N/A",3,0)))) -> 1 | Q33: =IF(AND(Drops!$D$45>1,OR(U33<>U32,AND(ROW()=5,U32=U33))),VLOOKUP(U33,Drops!$D$26:$E$44,2,FALSE),"") | R33: =IF(Q33<>"",ROW(),"") | S33: =OFFSET(AC33,,L33-1) -> 1 | T33: =IF(OR(V33<>V32,U33<>U32,AND(V33<>V32,W33<>W32),AND(V33<>V32,W33<>W32,X33<>X32),AND(V33<>V32,W33<>W32,X33<>X32,Y33<>Y32),AND(V33<>V32,W33<>W32,X33<>X32,Y33<>Y32,Z33<>Z32),L33-L32>1),1,0) -> 0 | U33: A | V33: 5 | W33: 1 | X33: 1 | Y33: 0 | Z33: 0 | AA33: =IF(ROW()=5,1,IF(OR(AH33=1,P33>0,T33=1),1,IF(OR(AND(AH33=2,AI33=1),AND(AI33=2,AJ33=1),AND(AJ33=2,AK33=1),AND(AK33=2,AL33=1)),1,0))) -> 1 | AB33: =IF(L34>L33,1,0) -> 0 | AC33: =IF(ROW()=5,P33,IF(AND($P33>1,AC$4=$L33),$P33,IF(AND($U33=$U32,V33=V32),AC32,IF(AND($L33=AC$4,P33=1),P33,0)))) -> 1 | AD33: =IF(AC33>1,AC33,IF(AND($P33>1,AD$4=$L33),$P33,IF(AND($U33=$U32,W33=W32),AD32,IF(AND($L33=AD$4,P33=1),P33,0)))) -> 1 | AE33: =IF(AD33>1,AD33,IF(AND($P33>1,AE$4=$L33),$P33,IF(AND($U33=$U32,X33=X32),AE32,IF(AND($L33=AE$4,P33=1),P33,0)))) -> 1 | AF33: =IF(AE33>1,AE33,IF(AND($P33>1,AF$4=$L33),$P33,IF(AND($U33=$U32,Y33=Y32),AF32,IF(AND($L33=AF$4,P33=1),P33,0)))) -> 0 | AG33: =IF(AF33>1,AF33,IF(AND($P33>1,AG$4=$L33),$P33,IF(AND($U33=$U32,Z33=Z32),AG32,IF(AND($L33=AG$4,P33=1),P33,0)))) -> 0 | AH33: =IF(AND($P33=1,$L33=AH$4),2,IF(AND($L33<>AH$4,AH32=2),AH32,IF($L33<>AH$4,0,1))) -> 2 | AI33: =IF(OR(ROW()=5,$U32<>$U33),0,IF(AND($P33=1,$L33=AI$4),2,IF(AND($L33<>AI$4,AI32=2),AI32,IF($L33<>AI$4,0,1)))) -> 2 | AJ33: =IF(OR(ROW()=5,$U32<>$U33),0,IF(AND($P33=1,$L33=AJ$4),2,IF(AND($L33<>AJ$4,AJ32=2),AJ32,IF($L33<>AJ$4,0,1)))) -> 2 | AK33: =IF(OR(ROW()=5,$U32<>$U33),0,IF(AND($P33=1,$L33=AK$4),2,IF(AND($L33<>AK$4,AK32=2),AK32,IF($L33<>AK$4,0,1)))) -> 0 | AL33: =IF(OR(ROW()=5,$U32<>$U33),0,IF(AND($P33=1,$L33=AL$4),2,IF(AND($L33<>AL$4,AL32=2),AL32,IF($L33<>AL$4,0,1)))) -> 0
A34: 4648 | B34: A.5.1.2 | C34: Have policies, standards, and procedures for implementing the third party risk management program been reviewed and approved by senior management? | D34: Yes | G34: Third Party Risk Management | H34: Subcontractor Selection and Management Process | I34: A.5 Third Party Risk Management Program | L34: 3 | M34: 3 | P34: =IF($L34="","",IF($D34="Yes",1,IF($D34="No",2,IF($D34="N/A",3,0)))) -> 1 | Q34: =IF(AND(Drops!$D$45>1,OR(U34<>U33,AND(ROW()=5,U33=U34))),VLOOKUP(U34,Drops!$D$26:$E$44,2,FALSE),"") | R34: =IF(Q34<>"",ROW(),"") | S34: =OFFSET(AC34,,L34-1) -> 1 | T34: =IF(OR(V34<>V33,U34<>U33,AND(V34<>V33,W34<>W33),AND(V34<>V33,W34<>W33,X34<>X33),AND(V34<>V33,W34<>W33,X34<>X33,Y34<>Y33),AND(V34<>V33,W34<>W33,X34<>X33,Y34<>Y33,Z34<>Z33),L34-L33>1),1,0) -> 0 | U34: A | V34: 5 | W34: 1 | X34: 2 | Y34: 0 | Z34: 0 | AA34: =IF(ROW()=5,1,IF(OR(AH34=1,P34>0,T34=1),1,IF(OR(AND(AH34=2,AI34=1),AND(AI34=2,AJ34=1),AND(AJ34=2,AK34=1),AND(AK34=2,AL34=1)),1,0))) -> 1 | AB34: =IF(L35>L34,1,0) -> 0 | AC34: =IF(ROW()=5,P34,IF(AND($P34>1,AC$4=$L34),$P34,IF(AND($U34=$U33,V34=V33),AC33,IF(AND($L34=AC$4,P34=1),P34,0)))) -> 1 | AD34: =IF(AC34>1,AC34,IF(AND($P34>1,AD$4=$L34),$P34,IF(AND($U34=$U33,W34=W33),AD33,IF(AND($L34=AD$4,P34=1),P34,0)))) -> 1 | AE34: =IF(AD34>1,AD34,IF(AND($P34>1,AE$4=$L34),$P34,IF(AND($U34=$U33,X34=X33),AE33,IF(AND($L34=AE$4,P34=1),P34,0)))) -> 1 | AF34: =IF(AE34>1,AE34,IF(AND($P34>1,AF$4=$L34),$P34,IF(AND($U34=$U33,Y34=Y33),AF33,IF(AND($L34=AF$4,P34=1),P34,0)))) -> 0 | AG34: =IF(AF34>1,AF34,IF(AND($P34>1,AG$4=$L34),$P34,IF(AND($U34=$U33,Z34=Z33),AG33,IF(AND($L34=AG$4,P34=1),P34,0)))) -> 0 | AH34: =IF(AND($P34=1,$L34=AH$4),2,IF(AND($L34<>AH$4,AH33=2),AH33,IF($L34<>AH$4,0,1))) -> 2 | AI34: =IF(OR(ROW()=5,$U33<>$U34),0,IF(AND($P34=1,$L34=AI$4),2,IF(AND($L34<>AI$4,AI33=2),AI33,IF($L34<>AI$4,0,1)))) -> 2 | AJ34: =IF(OR(ROW()=5,$U33<>$U34),0,IF(AND($P34=1,$L34=AJ$4),2,IF(AND($L34<>AJ$4,AJ33=2),AJ33,IF($L34<>AJ$4,0,1)))) -> 2 | AK34: =IF(OR(ROW()=5,$U33<>$U34),0,IF(AND($P34=1,$L34=AK$4),2,IF(AND($L34<>AK$4,AK33=2),AK33,IF($L34<>AK$4,0,1)))) -> 0 | AL34: =IF(OR(ROW()=5,$U33<>$U34),0,IF(AND($P34=1,$L34=AL$4),2,IF(AND($L34<>AL$4,AL33=2),AL33,IF($L34<>AL$4,0,1)))) -> 0
A35: 4649 | B35: A.5.1.3 | C35: Does the third party risk management program include creating and maintaining a third party inventory based on information and/or risk classification? | D35: Yes | G35: Third Party Risk Management | H35: Subcontractor Selection and Management Process | I35: A.5 Third Party Risk Management Program | L35: 3 | M35: 3 | P35: =IF($L35="","",IF($D35="Yes",1,IF($D35="No",2,IF($D35="N/A",3,0)))) -> 1 | Q35: =IF(AND(Drops!$D$45>1,OR(U35<>U34,AND(ROW()=5,U34=U35))),VLOOKUP(U35,Drops!$D$26:$E$44,2,FALSE),"") | R35: =IF(Q35<>"",ROW(),"") | S35: =OFFSET(AC35,,L35-1) -> 1 | T35: =IF(OR(V35<>V34,U35<>U34,AND(V35<>V34,W35<>W34),AND(V35<>V34,W35<>W34,X35<>X34),AND(V35<>V34,W35<>W34,X35<>X34,Y35<>Y34),AND(V35<>V34,W35<>W34,X35<>X34,Y35<>Y34,Z35<>Z34),L35-L34>1),1,0) -> 0 | U35: A | V35: 5 | W35: 1 | X35: 3 | Y35: 0 | Z35: 0 | AA35: =IF(ROW()=5,1,IF(OR(AH35=1,P35>0,T35=1),1,IF(OR(AND(AH35=2,AI35=1),AND(AI35=2,AJ35=1),AND(AJ35=2,AK35=1),AND(AK35=2,AL35=1)),1,0))) -> 1 | AB35: =IF(L36>L35,1,0) -> 0 | AC35: =IF(ROW()=5,P35,IF(AND($P35>1,AC$4=$L35),$P35,IF(AND($U35=$U34,V35=V34),AC34,IF(AND($L35=AC$4,P35=1),P35,0)))) -> 1 | AD35: =IF(AC35>1,AC35,IF(AND($P35>1,AD$4=$L35),$P35,IF(AND($U35=$U34,W35=W34),AD34,IF(AND($L35=AD$4,P35=1),P35,0)))) -> 1 | AE35: =IF(AD35>1,AD35,IF(AND($P35>1,AE$4=$L35),$P35,IF(AND($U35=$U34,X35=X34),AE34,IF(AND($L35=AE$4,P35=1),P35,0)))) -> 1 | AF35: =IF(AE35>1,AE35,IF(AND($P35>1,AF$4=$L35),$P35,IF(AND($U35=$U34,Y35=Y34),AF34,IF(AND($L35=AF$4,P35=1),P35,0)))) -> 0 | AG35: =IF(AF35>1,AF35,IF(AND($P35>1,AG$4=$L35),$P35,IF(AND($U35=$U34,Z35=Z34),AG34,IF(AND($L35=AG$4,P35=1),P35,0)))) -> 0 | AH35: =IF(AND($P35=1,$L35=AH$4),2,IF(AND($L35<>AH$4,AH34=2),AH34,IF($L35<>AH$4,0,1))) -> 2 | AI35: =IF(OR(ROW()=5,$U34<>$U35),0,IF(AND($P35=1,$L35=AI$4),2,IF(AND($L35<>AI$4,AI34=2),AI34,IF($L35<>AI$4,0,1)))) -> 2 | AJ35: =IF(OR(ROW()=5,$U34<>$U35),0,IF(AND($P35=1,$L35=AJ$4),2,IF(AND($L35<>AJ$4,AJ34=2),AJ34,IF($L35<>AJ$4,0,1)))) -> 2 | AK35: =IF(OR(ROW()=5,$U34<>$U35),0,IF(AND($P35=1,$L35=AK$4),2,IF(AND($L35<>AK$4,AK34=2),AK34,IF($L35<>AK$4,0,1)))) -> 0 | AL35: =IF(OR(ROW()=5,$U34<>$U35),0,IF(AND($P35=1,$L35=AL$4),2,IF(AND($L35<>AL$4,AL34=2),AL34,IF($L35<>AL$4,0,1)))) -> 0
A36: 4650 | B36: A.5.1.4 | C36: Does the program include definition of required contract development, adherence and management policies and processes? | D36: Yes | G36: Third Party Risk Management | H36: Subcontractor Selection and Management Process | I36: A.5 Third Party Risk Management Program | L36: 3 | M36: 3 | P36: =IF($L36="","",IF($D36="Yes",1,IF($D36="No",2,IF($D36="N/A",3,0)))) -> 1 | Q36: =IF(AND(Drops!$D$45>1,OR(U36<>U35,AND(ROW()=5,U35=U36))),VLOOKUP(U36,Drops!$D$26:$E$44,2,FALSE),"") | R36: =IF(Q36<>"",ROW(),"") | S36: =OFFSET(AC36,,L36-1) -> 1 | T36: =IF(OR(V36<>V35,U36<>U35,AND(V36<>V35,W36<>W35),AND(V36<>V35,W36<>W35,X36<>X35),AND(V36<>V35,W36<>W35,X36<>X35,Y36<>Y35),AND(V36<>V35,W36<>W35,X36<>X35,Y36<>Y35,Z36<>Z35),L36-L35>1),1,0) -> 0 | U36: A | V36: 5 | W36: 1 | X36: 4 | Y36: 0 | Z36: 0 | AA36: =IF(ROW()=5,1,IF(OR(AH36=1,P36>0,T36=1),1,IF(OR(AND(AH36=2,AI36=1),AND(AI36=2,AJ36=1),AND(AJ36=2,AK36=1),AND(AK36=2,AL36=1)),1,0))) -> 1 | AB36: =IF(L37>L36,1,0) -> 0 | AC36: =IF(ROW()=5,P36,IF(AND($P36>1,AC$4=$L36),$P36,IF(AND($U36=$U35,V36=V35),AC35,IF(AND($L36=AC$4,P36=1),P36,0)))) -> 1 | AD36: =IF(AC36>1,AC36,IF(AND($P36>1,AD$4=$L36),$P36,IF(AND($U36=$U35,W36=W35),AD35,IF(AND($L36=AD$4,P36=1),P36,0)))) -> 1 | AE36: =IF(AD36>1,AD36,IF(AND($P36>1,AE$4=$L36),$P36,IF(AND($U36=$U35,X36=X35),AE35,IF(AND($L36=AE$4,P36=1),P36,0)))) -> 1 | AF36: =IF(AE36>1,AE36,IF(AND($P36>1,AF$4=$L36),$P36,IF(AND($U36=$U35,Y36=Y35),AF35,IF(AND($L36=AF$4,P36=1),P36,0)))) -> 0 | AG36: =IF(AF36>1,AF36,IF(AND($P36>1,AG$4=$L36),$P36,IF(AND($U36=$U35,Z36=Z35),AG35,IF(AND($L36=AG$4,P36=1),P36,0)))) -> 0 | AH36: =IF(AND($P36=1,$L36=AH$4),2,IF(AND($L36<>AH$4,AH35=2),AH35,IF($L36<>AH$4,0,1))) -> 2 | AI36: =IF(OR(ROW()=5,$U35<>$U36),0,IF(AND($P36=1,$L36=AI$4),2,IF(AND($L36<>AI$4,AI35=2),AI35,IF($L36<>AI$4,0,1)))) -> 2 | AJ36: =IF(OR(ROW()=5,$U35<>$U36),0,IF(AND($P36=1,$L36=AJ$4),2,IF(AND($L36<>AJ$4,AJ35=2),AJ35,IF($L36<>AJ$4,0,1)))) -> 2 | AK36: =IF(OR(ROW()=5,$U35<>$U36),0,IF(AND($P36=1,$L36=AK$4),2,IF(AND($L36<>AK$4,AK35=2),AK35,IF($L36<>AK$4,0,1)))) -> 0 | AL36: =IF(OR(ROW()=5,$U35<>$U36),0,IF(AND($P36=1,$L36=AL$4),2,IF(AND($L36<>AL$4,AL35=2),AL35,IF($L36<>AL$4,0,1)))) -> 0
A37: 4651 | B37: A.5.1.5 | C37: Does the program include the definition of a third party risk assessment process? | D37: Yes | G37: Third Party Risk Management | H37: Subcontractor Selection and Management Process | I37: A.5 Third Party Risk Management Program | L37: 3 | M37: 3 | P37: =IF($L37="","",IF($D37="Yes",1,IF($D37="No",2,IF($D37="N/A",3,0)))) -> 1 | Q37: =IF(AND(Drops!$D$45>1,OR(U37<>U36,AND(ROW()=5,U36=U37))),VLOOKUP(U37,Drops!$D$26:$E$44,2,FALSE),"") | R37: =IF(Q37<>"",ROW(),"") | S37: =OFFSET(AC37,,L37-1) -> 1 | T37: =IF(OR(V37<>V36,U37<>U36,AND(V37<>V36,W37<>W36),AND(V37<>V36,W37<>W36,X37<>X36),AND(V37<>V36,W37<>W36,X37<>X36,Y37<>Y36),AND(V37<>V36,W37<>W36,X37<>X36,Y37<>Y36,Z37<>Z36),L37-L36>1),1,0) -> 0 | U37: A | V37: 5 | W37: 1 | X37: 5 | Y37: 0 | Z37: 0 | AA37: =IF(ROW()=5,1,IF(OR(AH37=1,P37>0,T37=1),1,IF(OR(AND(AH37=2,AI37=1),AND(AI37=2,AJ37=1),AND(AJ37=2,AK37=1),AND(AK37=2,AL37=1)),1,0))) -> 1 | AB37: =IF(L38>L37,1,0) -> 0 | AC37: =IF(ROW()=5,P37,IF(AND($P37>1,AC$4=$L37),$P37,IF(AND($U37=$U36,V37=V36),AC36,IF(AND($L37=AC$4,P37=1),P37,0)))) -> 1 | AD37: =IF(AC37>1,AC37,IF(AND($P37>1,AD$4=$L37),$P37,IF(AND($U37=$U36,W37=W36),AD36,IF(AND($L37=AD$4,P37=1),P37,0)))) -> 1 | AE37: =IF(AD37>1,AD37,IF(AND($P37>1,AE$4=$L37),$P37,IF(AND($U37=$U36,X37=X36),AE36,IF(AND($L37=AE$4,P37=1),P37,0)))) -> 1 | AF37: =IF(AE37>1,AE37,IF(AND($P37>1,AF$4=$L37),$P37,IF(AND($U37=$U36,Y37=Y36),AF36,IF(AND($L37=AF$4,P37=1),P37,0)))) -> 0 | AG37: =IF(AF37>1,AF37,IF(AND($P37>1,AG$4=$L37),$P37,IF(AND($U37=$U36,Z37=Z36),AG36,IF(AND($L37=AG$4,P37=1),P37,0)))) -> 0 | AH37: =IF(AND($P37=1,$L37=AH$4),2,IF(AND($L37<>AH$4,AH36=2),AH36,IF($L37<>AH$4,0,1))) -> 2 | AI37: =IF(OR(ROW()=5,$U36<>$U37),0,IF(AND($P37=1,$L37=AI$4),2,IF(AND($L37<>AI$4,AI36=2),AI36,IF($L37<>AI$4,0,1)))) -> 2 | AJ37: =IF(OR(ROW()=5,$U36<>$U37),0,IF(AND($P37=1,$L37=AJ$4),2,IF(AND($L37<>AJ$4,AJ36=2),AJ36,IF($L37<>AJ$4,0,1)))) -> 2 | AK37: =IF(OR(ROW()=5,$U36<>$U37),0,IF(AND($P37=1,$L37=AK$4),2,IF(AND($L37<>AK$4,AK36=2),AK36,IF($L37<>AK$4,0,1)))) -> 0 | AL37: =IF(OR(ROW()=5,$U36<>$U37),0,IF(AND($P37=1,$L37=AL$4),2,IF(AND($L37<>AL$4,AL36=2),AL36,IF($L37<>AL$4,0,1)))) -> 0
A38: 4652 | B38: A.5.1.6 | C38: Does the program include consistently applied tools, measurements and criteria to evaluate third party risk? | D38: Yes | G38: Third Party Risk Management | H38: Subcontractor Selection and Management Process | L38: 3 | M38: 3 | P38: =IF($L38="","",IF($D38="Yes",1,IF($D38="No",2,IF($D38="N/A",3,0)))) -> 1 | Q38: =IF(AND(Drops!$D$45>1,OR(U38<>U37,AND(ROW()=5,U37=U38))),VLOOKUP(U38,Drops!$D$26:$E$44,2,FALSE),"") | R38: =IF(Q38<>"",ROW(),"") | S38: =OFFSET(AC38,,L38-1) -> 1 | T38: =IF(OR(V38<>V37,U38<>U37,AND(V38<>V37,W38<>W37),AND(V38<>V37,W38<>W37,X38<>X37),AND(V38<>V37,W38<>W37,X38<>X37,Y38<>Y37),AND(V38<>V37,W38<>W37,X38<>X37,Y38<>Y37,Z38<>Z37),L38-L37>1),1,0) -> 0 | U38: A | V38: 5 | W38: 1 | X38: 6 | Y38: 0 | Z38: 0 | AA38: =IF(ROW()=5,1,IF(OR(AH38=1,P38>0,T38=1),1,IF(OR(AND(AH38=2,AI38=1),AND(AI38=2,AJ38=1),AND(AJ38=2,AK38=1),AND(AK38=2,AL38=1)),1,0))) -> 1 | AB38: =IF(L39>L38,1,0) -> 0 | AC38: =IF(ROW()=5,P38,IF(AND($P38>1,AC$4=$L38),$P38,IF(AND($U38=$U37,V38=V37),AC37,IF(AND($L38=AC$4,P38=1),P38,0)))) -> 1 | AD38: =IF(AC38>1,AC38,IF(AND($P38>1,AD$4=$L38),$P38,IF(AND($U38=$U37,W38=W37),AD37,IF(AND($L38=AD$4,P38=1),P38,0)))) -> 1 | AE38: =IF(AD38>1,AD38,IF(AND($P38>1,AE$4=$L38),$P38,IF(AND($U38=$U37,X38=X37),AE37,IF(AND($L38=AE$4,P38=1),P38,0)))) -> 1 | AF38: =IF(AE38>1,AE38,IF(AND($P38>1,AF$4=$L38),$P38,IF(AND($U38=$U37,Y38=Y37),AF37,IF(AND($L38=AF$4,P38=1),P38,0)))) -> 0 | AG38: =IF(AF38>1,AF38,IF(AND($P38>1,AG$4=$L38),$P38,IF(AND($U38=$U37,Z38=Z37),AG37,IF(AND($L38=AG$4,P38=1),P38,0)))) -> 0 | AH38: =IF(AND($P38=1,$L38=AH$4),2,IF(AND($L38<>AH$4,AH37=2),AH37,IF($L38<>AH$4,0,1))) -> 2 | AI38: =IF(OR(ROW()=5,$U37<>$U38),0,IF(AND($P38=1,$L38=AI$4),2,IF(AND($L38<>AI$4,AI37=2),AI37,IF($L38<>AI$4,0,1)))) -> 2 | AJ38: =IF(OR(ROW()=5,$U37<>$U38),0,IF(AND($P38=1,$L38=AJ$4),2,IF(AND($L38<>AJ$4,AJ37=2),AJ37,IF($L38<>AJ$4,0,1)))) -> 2 | AK38: =IF(OR(ROW()=5,$U37<>$U38),0,IF(AND($P38=1,$L38=AK$4),2,IF(AND($L38<>AK$4,AK37=2),AK37,IF($L38<>AK$4,0,1)))) -> 0 | AL38: =IF(OR(ROW()=5,$U37<>$U38),0,IF(AND($P38=1,$L38=AL$4),2,IF(AND($L38<>AL$4,AL37=2),AL37,IF($L38<>AL$4,0,1)))) -> 0
A39: 4653 | B39: A.5.1.7 | C39: Does the program include definition and a process for ongoing monitoring and review of third party risk? | D39: Yes | G39: Third Party Risk Management | H39: Subcontractor Selection and Management Process | I39: A.5 Third Party Risk Management Program | L39: 3 | M39: 3 | P39: =IF($L39="","",IF($D39="Yes",1,IF($D39="No",2,IF($D39="N/A",3,0)))) -> 1 | Q39: =IF(AND(Drops!$D$45>1,OR(U39<>U38,AND(ROW()=5,U38=U39))),VLOOKUP(U39,Drops!$D$26:$E$44,2,FALSE),"") | R39: =IF(Q39<>"",ROW(),"") | S39: =OFFSET(AC39,,L39-1) -> 1 | T39: =IF(OR(V39<>V38,U39<>U38,AND(V39<>V38,W39<>W38),AND(V39<>V38,W39<>W38,X39<>X38),AND(V39<>V38,W39<>W38,X39<>X38,Y39<>Y38),AND(V39<>V38,W39<>W38,X39<>X38,Y39<>Y38,Z39<>Z38),L39-L38>1),1,0) -> 0 | U39: A | V39: 5 | W39: 1 | X39: 7 | Y39: 0 | Z39: 0 | AA39: =IF(ROW()=5,1,IF(OR(AH39=1,P39>0,T39=1),1,IF(OR(AND(AH39=2,AI39=1),AND(AI39=2,AJ39=1),AND(AJ39=2,AK39=1),AND(AK39=2,AL39=1)),1,0))) -> 1 | AB39: =IF(L40>L39,1,0) -> 0 | AC39: =IF(ROW()=5,P39,IF(AND($P39>1,AC$4=$L39),$P39,IF(AND($U39=$U38,V39=V38),AC38,IF(AND($L39=AC$4,P39=1),P39,0)))) -> 1 | AD39: =IF(AC39>1,AC39,IF(AND($P39>1,AD$4=$L39),$P39,IF(AND($U39=$U38,W39=W38),AD38,IF(AND($L39=AD$4,P39=1),P39,0)))) -> 1 | AE39: =IF(AD39>1,AD39,IF(AND($P39>1,AE$4=$L39),$P39,IF(AND($U39=$U38,X39=X38),AE38,IF(AND($L39=AE$4,P39=1),P39,0)))) -> 1 | AF39: =IF(AE39>1,AE39,IF(AND($P39>1,AF$4=$L39),$P39,IF(AND($U39=$U38,Y39=Y38),AF38,IF(AND($L39=AF$4,P39=1),P39,0)))) -> 0 | AG39: =IF(AF39>1,AF39,IF(AND($P39>1,AG$4=$L39),$P39,IF(AND($U39=$U38,Z39=Z38),AG38,IF(AND($L39=AG$4,P39=1),P39,0)))) -> 0 | AH39: =IF(AND($P39=1,$L39=AH$4),2,IF(AND($L39<>AH$4,AH38=2),AH38,IF($L39<>AH$4,0,1))) -> 2 | AI39: =IF(OR(ROW()=5,$U38<>$U39),0,IF(AND($P39=1,$L39=AI$4),2,IF(AND($L39<>AI$4,AI38=2),AI38,IF($L39<>AI$4,0,1)))) -> 2 | AJ39: =IF(OR(ROW()=5,$U38<>$U39),0,IF(AND($P39=1,$L39=AJ$4),2,IF(AND($L39<>AJ$4,AJ38=2),AJ38,IF($L39<>AJ$4,0,1)))) -> 2 | AK39: =IF(OR(ROW()=5,$U38<>$U39),0,IF(AND($P39=1,$L39=AK$4),2,IF(AND($L39<>AK$4,AK38=2),AK38,IF($L39<>AK$4,0,1)))) -> 0 | AL39: =IF(OR(ROW()=5,$U38<>$U39),0,IF(AND($P39=1,$L39=AL$4),2,IF(AND($L39<>AL$4,AL38=2),AL38,IF($L39<>AL$4,0,1)))) -> 0
A40: 2514 | B40: A.5.1.8 | C40: Does the third party risk management program include assessments performed on all potential subcontractors before entering contracts with them? | D40: Yes | E40: Information Security reviews all potential subcontractors before entering into contract through an established vendor risk management program. This includes assessment of security controls, negotiation of contract agreements, risk assessments, and identifying any security and privacy provisions required to comply with applicable laws and regulations. | G40: Third Party Risk Management | H40: Subcontractor Selection and Management Process | I40: A.7 Subcontractor Selection and Management Process | L40: 3 | M40: 3 | P40: =IF($L40="","",IF($D40="Yes",1,IF($D40="No",2,IF($D40="N/A",3,0)))) -> 1 | Q40: =IF(AND(Drops!$D$45>1,OR(U40<>U39,AND(ROW()=5,U39=U40))),VLOOKUP(U40,Drops!$D$26:$E$44,2,FALSE),"") | R40: =IF(Q40<>"",ROW(),"") | S40: =OFFSET(AC40,,L40-1) -> 1 | T40: =IF(OR(V40<>V39,U40<>U39,AND(V40<>V39,W40<>W39),AND(V40<>V39,W40<>W39,X40<>X39),AND(V40<>V39,W40<>W39,X40<>X39,Y40<>Y39),AND(V40<>V39,W40<>W39,X40<>X39,Y40<>Y39,Z40<>Z39),L40-L39>1),1,0) -> 0 | U40: A | V40: 5 | W40: 1 | X40: 8 | Y40: 0 | Z40: 0 | AA40: =IF(ROW()=5,1,IF(OR(AH40=1,P40>0,T40=1),1,IF(OR(AND(AH40=2,AI40=1),AND(AI40=2,AJ40=1),AND(AJ40=2,AK40=1),AND(AK40=2,AL40=1)),1,0))) -> 1 | AB40: =IF(L41>L40,1,0) -> 1 | AC40: =IF(ROW()=5,P40,IF(AND($P40>1,AC$4=$L40),$P40,IF(AND($U40=$U39,V40=V39),AC39,IF(AND($L40=AC$4,P40=1),P40,0)))) -> 1 | AD40: =IF(AC40>1,AC40,IF(AND($P40>1,AD$4=$L40),$P40,IF(AND($U40=$U39,W40=W39),AD39,IF(AND($L40=AD$4,P40=1),P40,0)))) -> 1 | AE40: =IF(AD40>1,AD40,IF(AND($P40>1,AE$4=$L40),$P40,IF(AND($U40=$U39,X40=X39),AE39,IF(AND($L40=AE$4,P40=1),P40,0)))) -> 1 | AF40: =IF(AE40>1,AE40,IF(AND($P40>1,AF$4=$L40),$P40,IF(AND($U40=$U39,Y40=Y39),AF39,IF(AND($L40=AF$4,P40=1),P40,0)))) -> 0 | AG40: =IF(AF40>1,AF40,IF(AND($P40>1,AG$4=$L40),$P40,IF(AND($U40=$U39,Z40=Z39),AG39,IF(AND($L40=AG$4,P40=1),P40,0)))) -> 0 | AH40: =IF(AND($P40=1,$L40=AH$4),2,IF(AND($L40<>AH$4,AH39=2),AH39,IF($L40<>AH$4,0,1))) -> 2 | AI40: =IF(OR(ROW()=5,$U39<>$U40),0,IF(AND($P40=1,$L40=AI$4),2,IF(AND($L40<>AI$4,AI39=2),AI39,IF($L40<>AI$4,0,1)))) -> 2 | AJ40: =IF(OR(ROW()=5,$U39<>$U40),0,IF(AND($P40=1,$L40=AJ$4),2,IF(AND($L40<>AJ$4,AJ39=2),AJ39,IF($L40<>AJ$4,0,1)))) -> 2 | AK40: =IF(OR(ROW()=5,$U39<>$U40),0,IF(AND($P40=1,$L40=AK$4),2,IF(AND($L40<>AK$4,AK39=2),AK39,IF($L40<>AK$4,0,1)))) -> 0 | AL40: =IF(OR(ROW()=5,$U39<>$U40),0,IF(AND($P40=1,$L40=AL$4),2,IF(AND($L40<>AL$4,AL39=2),AL39,IF($L40<>AL$4,0,1)))) -> 0
A41: 4168 | B41: A.5.1.8.1 | C41: Are subcontractors evaluated for reassessment when there are material changes to risk posture, service offerings or contracts? | D41: Yes | G41: Third Party Risk Management | H41: Subcontractor Selection and Management Process | J41: 15.2.2 Managing Changes to Supplier Services | L41: 4 | M41: 3 | P41: =IF($L41="","",IF($D41="Yes",1,IF($D41="No",2,IF($D41="N/A",3,0)))) -> 1 | Q41: =IF(AND(Drops!$D$45>1,OR(U41<>U40,AND(ROW()=5,U40=U41))),VLOOKUP(U41,Drops!$D$26:$E$44,2,FALSE),"") | R41: =IF(Q41<>"",ROW(),"") | S41: =OFFSET(AC41,,L41-1) -> 1 | T41: =IF(OR(V41<>V40,U41<>U40,AND(V41<>V40,W41<>W40),AND(V41<>V40,W41<>W40,X41<>X40),AND(V41<>V40,W41<>W40,X41<>X40,Y41<>Y40),AND(V41<>V40,W41<>W40,X41<>X40,Y41<>Y40,Z41<>Z40),L41-L40>1),1,0) -> 0 | U41: A | V41: 5 | W41: 1 | X41: 8 | Y41: 1 | Z41: 0 | AA41: =IF(ROW()=5,1,IF(OR(AH41=1,P41>0,T41=1),1,IF(OR(AND(AH41=2,AI41=1),AND(AI41=2,AJ41=1),AND(AJ41=2,AK41=1),AND(AK41=2,AL41=1)),1,0))) -> 1 | AB41: =IF(L42>L41,1,0) -> 0 | AC41: =IF(ROW()=5,P41,IF(AND($P41>1,AC$4=$L41),$P41,IF(AND($U41=$U40,V41=V40),AC40,IF(AND($L41=AC$4,P41=1),P41,0)))) -> 1 | AD41: =IF(AC41>1,AC41,IF(AND($P41>1,AD$4=$L41),$P41,IF(AND($U41=$U40,W41=W40),AD40,IF(AND($L41=AD$4,P41=1),P41,0)))) -> 1 | AE41: =IF(AD41>1,AD41,IF(AND($P41>1,AE$4=$L41),$P41,IF(AND($U41=$U40,X41=X40),AE40,IF(AND($L41=AE$4,P41=1),P41,0)))) -> 1 | AF41: =IF(AE41>1,AE41,IF(AND($P41>1,AF$4=$L41),$P41,IF(AND($U41=$U40,Y41=Y40),AF40,IF(AND($L41=AF$4,P41=1),P41,0)))) -> 1 | AG41: =IF(AF41>1,AF41,IF(AND($P41>1,AG$4=$L41),$P41,IF(AND($U41=$U40,Z41=Z40),AG40,IF(AND($L41=AG$4,P41=1),P41,0)))) -> 0 | AH41: =IF(AND($P41=1,$L41=AH$4),2,IF(AND($L41<>AH$4,AH40=2),AH40,IF($L41<>AH$4,0,1))) -> 2 | AI41: =IF(OR(ROW()=5,$U40<>$U41),0,IF(AND($P41=1,$L41=AI$4),2,IF(AND($L41<>AI$4,AI40=2),AI40,IF($L41<>AI$4,0,1)))) -> 2 | AJ41: =IF(OR(ROW()=5,$U40<>$U41),0,IF(AND($P41=1,$L41=AJ$4),2,IF(AND($L41<>AJ$4,AJ40=2),AJ40,IF($L41<>AJ$4,0,1)))) -> 2 | AK41: =IF(OR(ROW()=5,$U40<>$U41),0,IF(AND($P41=1,$L41=AK$4),2,IF(AND($L41<>AK$4,AK40=2),AK40,IF($L41<>AK$4,0,1)))) -> 2 | AL41: =IF(OR(ROW()=5,$U40<>$U41),0,IF(AND($P41=1,$L41=AL$4),2,IF(AND($L41<>AL$4,AL40=2),AL40,IF($L41<>AL$4,0,1)))) -> 0
A42: 3909 | B42: A.5.1.13 | C42: Does the third party risk management program require business units to notify if there are new or changed subcontractors? | D42: Yes | G42: Third Party Risk Management | H42: Subcontractor Selection and Management Process | I42: A.7 Subcontractor Selection and Management Process | J42: 15.2.2 Managing Changes to Supplier Services | L42: 3 | M42: 2 | P42: =IF($L42="","",IF($D42="Yes",1,IF($D42="No",2,IF($D42="N/A",3,0)))) -> 1 | Q42: =IF(AND(Drops!$D$45>1,OR(U42<>U41,AND(ROW()=5,U41=U42))),VLOOKUP(U42,Drops!$D$26:$E$44,2,FALSE),"") | R42: =IF(Q42<>"",ROW(),"") | S42: =OFFSET(AC42,,L42-1) -> 1 | T42: =IF(OR(V42<>V41,U42<>U41,AND(V42<>V41,W42<>W41),AND(V42<>V41,W42<>W41,X42<>X41),AND(V42<>V41,W42<>W41,X42<>X41,Y42<>Y41),AND(V42<>V41,W42<>W41,X42<>X41,Y42<>Y41,Z42<>Z41),L42-L41>1),1,0) -> 0 | U42: A | V42: 5 | W42: 1 | X42: 13 | Y42: 0 | Z42: 0 | AA42: =IF(ROW()=5,1,IF(OR(AH42=1,P42>0,T42=1),1,IF(OR(AND(AH42=2,AI42=1),AND(AI42=2,AJ42=1),AND(AJ42=2,AK42=1),AND(AK42=2,AL42=1)),1,0))) -> 1 | AB42: =IF(L43>L42,1,0) -> 0 | AC42: =IF(ROW()=5,P42,IF(AND($P42>1,AC$4=$L42),$P42,IF(AND($U42=$U41,V42=V41),AC41,IF(AND($L42=AC$4,P42=1),P42,0)))) -> 1 | AD42: =IF(AC42>1,AC42,IF(AND($P42>1,AD$4=$L42),$P42,IF(AND($U42=$U41,W42=W41),AD41,IF(AND($L42=AD$4,P42=1),P42,0)))) -> 1 | AE42: =IF(AD42>1,AD42,IF(AND($P42>1,AE$4=$L42),$P42,IF(AND($U42=$U41,X42=X41),AE41,IF(AND($L42=AE$4,P42=1),P42,0)))) -> 1 | AF42: =IF(AE42>1,AE42,IF(AND($P42>1,AF$4=$L42),$P42,IF(AND($U42=$U41,Y42=Y41),AF41,IF(AND($L42=AF$4,P42=1),P42,0)))) -> 0 | AG42: =IF(AF42>1,AF42,IF(AND($P42>1,AG$4=$L42),$P42,IF(AND($U42=$U41,Z42=Z41),AG41,IF(AND($L42=AG$4,P42=1),P42,0)))) -> 0 | AH42: =IF(AND($P42=1,$L42=AH$4),2,IF(AND($L42<>AH$4,AH41=2),AH41,IF($L42<>AH$4,0,1))) -> 2 | AI42: =IF(OR(ROW()=5,$U41<>$U42),0,IF(AND($P42=1,$L42=AI$4),2,IF(AND($L42<>AI$4,AI41=2),AI41,IF($L42<>AI$4,0,1)))) -> 2 | AJ42: =IF(OR(ROW()=5,$U41<>$U42),0,IF(AND($P42=1,$L42=AJ$4),2,IF(AND($L42<>AJ$4,AJ41=2),AJ41,IF($L42<>AJ$4,0,1)))) -> 2 | AK42: =IF(OR(ROW()=5,$U41<>$U42),0,IF(AND($P42=1,$L42=AK$4),2,IF(AND($L42<>AK$4,AK41=2),AK41,IF($L42<>AK$4,0,1)))) -> 2 | AL42: =IF(OR(ROW()=5,$U41<>$U42),0,IF(AND($P42=1,$L42=AL$4),2,IF(AND($L42<>AL$4,AL41=2),AL41,IF($L42<>AL$4,0,1)))) -> 0
A43: 3910 | B43: A.5.1.15 | C43: Does the subcontractor third party risk management program include defined procedures for subcontractor management? | D43: Yes | G43: Third Party Risk Management | H43: Subcontractor Selection and Management Process | I43: A.7 Subcontractor Selection and Management Process | J43: 15.2.1 Monitoring and Review of Supplier Services | L43: 3 | M43: 3 | P43: =IF($L43="","",IF($D43="Yes",1,IF($D43="No",2,IF($D43="N/A",3,0)))) -> 1 | Q43: =IF(AND(Drops!$D$45>1,OR(U43<>U42,AND(ROW()=5,U42=U43))),VLOOKUP(U43,Drops!$D$26:$E$44,2,FALSE),"") | R43: =IF(Q43<>"",ROW(),"") | S43: =OFFSET(AC43,,L43-1) -> 1 | T43: =IF(OR(V43<>V42,U43<>U42,AND(V43<>V42,W43<>W42),AND(V43<>V42,W43<>W42,X43<>X42),AND(V43<>V42,W43<>W42,X43<>X42,Y43<>Y42),AND(V43<>V42,W43<>W42,X43<>X42,Y43<>Y42,Z43<>Z42),L43-L42>1),1,0) -> 0 | U43: A | V43: 5 | W43: 1 | X43: 15 | Y43: 0 | Z43: 0 | AA43: =IF(ROW()=5,1,IF(OR(AH43=1,P43>0,T43=1),1,IF(OR(AND(AH43=2,AI43=1),AND(AI43=2,AJ43=1),AND(AJ43=2,AK43=1),AND(AK43=2,AL43=1)),1,0))) -> 1 | AB43: =IF(L44>L43,1,0) -> 1 | AC43: =IF(ROW()=5,P43,IF(AND($P43>1,AC$4=$L43),$P43,IF(AND($U43=$U42,V43=V42),AC42,IF(AND($L43=AC$4,P43=1),P43,0)))) -> 1 | AD43: =IF(AC43>1,AC43,IF(AND($P43>1,AD$4=$L43),$P43,IF(AND($U43=$U42,W43=W42),AD42,IF(AND($L43=AD$4,P43=1),P43,0)))) -> 1 | AE43: =IF(AD43>1,AD43,IF(AND($P43>1,AE$4=$L43),$P43,IF(AND($U43=$U42,X43=X42),AE42,IF(AND($L43=AE$4,P43=1),P43,0)))) -> 1 | AF43: =IF(AE43>1,AE43,IF(AND($P43>1,AF$4=$L43),$P43,IF(AND($U43=$U42,Y43=Y42),AF42,IF(AND($L43=AF$4,P43=1),P43,0)))) -> 0 | AG43: =IF(AF43>1,AF43,IF(AND($P43>1,AG$4=$L43),$P43,IF(AND($U43=$U42,Z43=Z42),AG42,IF(AND($L43=AG$4,P43=1),P43,0)))) -> 0 | AH43: =IF(AND($P43=1,$L43=AH$4),2,IF(AND($L43<>AH$4,AH42=2),AH42,IF($L43<>AH$4,0,1))) -> 2 | AI43: =IF(OR(ROW()=5,$U42<>$U43),0,IF(AND($P43=1,$L43=AI$4),2,IF(AND($L43<>AI$4,AI42=2),AI42,IF($L43<>AI$4,0,1)))) -> 2 | AJ43: =IF(OR(ROW()=5,$U42<>$U43),0,IF(AND($P43=1,$L43=AJ$4),2,IF(AND($L43<>AJ$4,AJ42=2),AJ42,IF($L43<>AJ$4,0,1)))) -> 2 | AK43: =IF(OR(ROW()=5,$U42<>$U43),0,IF(AND($P43=1,$L43=AK$4),2,IF(AND($L43<>AK$4,AK42=2),AK42,IF($L43<>AK$4,0,1)))) -> 2 | AL43: =IF(OR(ROW()=5,$U42<>$U43),0,IF(AND($P43=1,$L43=AL$4),2,IF(AND($L43<>AL$4,AL42=2),AL42,IF($L43<>AL$4,0,1)))) -> 0
A44: 3900 | B44: A.5.1.15.1 | C44: Does the subcontractor third party risk management program include review of subcontractors' third party risk program? | D44: Yes | G44: Third Party Risk Management | H44: Subcontractors' Third Party Risk Management | I44: A.9 Documenting Information Security Assessments for Subcontractors | J44: 15.1.2 Addressing Security Within Supplier Agreements | L44: 4 | M44: 3 | P44: =IF($L44="","",IF($D44="Yes",1,IF($D44="No",2,IF($D44="N/A",3,0)))) -> 1 | Q44: =IF(AND(Drops!$D$45>1,OR(U44<>U43,AND(ROW()=5,U43=U44))),VLOOKUP(U44,Drops!$D$26:$E$44,2,FALSE),"") | R44: =IF(Q44<>"",ROW(),"") | S44: =OFFSET(AC44,,L44-1) -> 1 | T44: =IF(OR(V44<>V43,U44<>U43,AND(V44<>V43,W44<>W43),AND(V44<>V43,W44<>W43,X44<>X43),AND(V44<>V43,W44<>W43,X44<>X43,Y44<>Y43),AND(V44<>V43,W44<>W43,X44<>X43,Y44<>Y43,Z44<>Z43),L44-L43>1),1,0) -> 0 | U44: A | V44: 5 | W44: 1 | X44: 15 | Y44: 1 | Z44: 0 | AA44: =IF(ROW()=5,1,IF(OR(AH44=1,P44>0,T44=1),1,IF(OR(AND(AH44=2,AI44=1),AND(AI44=2,AJ44=1),AND(AJ44=2,AK44=1),AND(AK44=2,AL44=1)),1,0))) -> 1 | AB44: =IF(L45>L44,1,0) -> 0 | AC44: =IF(ROW()=5,P44,IF(AND($P44>1,AC$4=$L44),$P44,IF(AND($U44=$U43,V44=V43),AC43,IF(AND($L44=AC$4,P44=1),P44,0)))) -> 1 | AD44: =IF(AC44>1,AC44,IF(AND($P44>1,AD$4=$L44),$P44,IF(AND($U44=$U43,W44=W43),AD43,IF(AND($L44=AD$4,P44=1),P44,0)))) -> 1 | AE44: =IF(AD44>1,AD44,IF(AND($P44>1,AE$4=$L44),$P44,IF(AND($U44=$U43,X44=X43),AE43,IF(AND($L44=AE$4,P44=1),P44,0)))) -> 1 | AF44: =IF(AE44>1,AE44,IF(AND($P44>1,AF$4=$L44),$P44,IF(AND($U44=$U43,Y44=Y43),AF43,IF(AND($L44=AF$4,P44=1),P44,0)))) -> 1 | AG44: =IF(AF44>1,AF44,IF(AND($P44>1,AG$4=$L44),$P44,IF(AND($U44=$U43,Z44=Z43),AG43,IF(AND($L44=AG$4,P44=1),P44,0)))) -> 0 | AH44: =IF(AND($P44=1,$L44=AH$4),2,IF(AND($L44<>AH$4,AH43=2),AH43,IF($L44<>AH$4,0,1))) -> 2 | AI44: =IF(OR(ROW()=5,$U43<>$U44),0,IF(AND($P44=1,$L44=AI$4),2,IF(AND($L44<>AI$4,AI43=2),AI43,IF($L44<>AI$4,0,1)))) -> 2 | AJ44: =IF(OR(ROW()=5,$U43<>$U44),0,IF(AND($P44=1,$L44=AJ$4),2,IF(AND($L44<>AJ$4,AJ43=2),AJ43,IF($L44<>AJ$4,0,1)))) -> 2 | AK44: =IF(OR(ROW()=5,$U43<>$U44),0,IF(AND($P44=1,$L44=AK$4),2,IF(AND($L44<>AK$4,AK43=2),AK43,IF($L44<>AK$4,0,1)))) -> 2 | AL44: =IF(OR(ROW()=5,$U43<>$U44),0,IF(AND($P44=1,$L44=AL$4),2,IF(AND($L44<>AL$4,AL43=2),AL43,IF($L44<>AL$4,0,1)))) -> 0
A45: 5644 | B45: A.5.1.15.2 | C45: Does the third party risk management program require subcontractors to perform risk and security assessments on their subcontractors prior to engaging their services (logical, physical, other controls)? | D45: Yes | G45: Third Party Risk Management | H45: Subcontractors' Third Party Risk Management | I45: A.9 Documenting Information Security Assessments for Subcontractors | L45: 4 | M45: 3 | P45: =IF($L45="","",IF($D45="Yes",1,IF($D45="No",2,IF($D45="N/A",3,0)))) -> 1 | Q45: =IF(AND(Drops!$D$45>1,OR(U45<>U44,AND(ROW()=5,U44=U45))),VLOOKUP(U45,Drops!$D$26:$E$44,2,FALSE),"") | R45: =IF(Q45<>"",ROW(),"") | S45: =OFFSET(AC45,,L45-1) -> 1 | T45: =IF(OR(V45<>V44,U45<>U44,AND(V45<>V44,W45<>W44),AND(V45<>V44,W45<>W44,X45<>X44),AND(V45<>V44,W45<>W44,X45<>X44,Y45<>Y44),AND(V45<>V44,W45<>W44,X45<>X44,Y45<>Y44,Z45<>Z44),L45-L44>1),1,0) -> 0 | U45: A | V45: 5 | W45: 1 | X45: 15 | Y45: 2 | Z45: 0 | AA45: =IF(ROW()=5,1,IF(OR(AH45=1,P45>0,T45=1),1,IF(OR(AND(AH45=2,AI45=1),AND(AI45=2,AJ45=1),AND(AJ45=2,AK45=1),AND(AK45=2,AL45=1)),1,0))) -> 1 | AB45: =IF(L46>L45,1,0) -> 0 | AC45: =IF(ROW()=5,P45,IF(AND($P45>1,AC$4=$L45),$P45,IF(AND($U45=$U44,V45=V44),AC44,IF(AND($L45=AC$4,P45=1),P45,0)))) -> 1 | AD45: =IF(AC45>1,AC45,IF(AND($P45>1,AD$4=$L45),$P45,IF(AND($U45=$U44,W45=W44),AD44,IF(AND($L45=AD$4,P45=1),P45,0)))) -> 1 | AE45: =IF(AD45>1,AD45,IF(AND($P45>1,AE$4=$L45),$P45,IF(AND($U45=$U44,X45=X44),AE44,IF(AND($L45=AE$4,P45=1),P45,0)))) -> 1 | AF45: =IF(AE45>1,AE45,IF(AND($P45>1,AF$4=$L45),$P45,IF(AND($U45=$U44,Y45=Y44),AF44,IF(AND($L45=AF$4,P45=1),P45,0)))) -> 1 | AG45: =IF(AF45>1,AF45,IF(AND($P45>1,AG$4=$L45),$P45,IF(AND($U45=$U44,Z45=Z44),AG44,IF(AND($L45=AG$4,P45=1),P45,0)))) -> 0 | AH45: =IF(AND($P45=1,$L45=AH$4),2,IF(AND($L45<>AH$4,AH44=2),AH44,IF($L45<>AH$4,0,1))) -> 2 | AI45: =IF(OR(ROW()=5,$U44<>$U45),0,IF(AND($P45=1,$L45=AI$4),2,IF(AND($L45<>AI$4,AI44=2),AI44,IF($L45<>AI$4,0,1)))) -> 2 | AJ45: =IF(OR(ROW()=5,$U44<>$U45),0,IF(AND($P45=1,$L45=AJ$4),2,IF(AND($L45<>AJ$4,AJ44=2),AJ44,IF($L45<>AJ$4,0,1)))) -> 2 | AK45: =IF(OR(ROW()=5,$U44<>$U45),0,IF(AND($P45=1,$L45=AK$4),2,IF(AND($L45<>AK$4,AK44=2),AK44,IF($L45<>AK$4,0,1)))) -> 2 | AL45: =IF(OR(ROW()=5,$U44<>$U45),0,IF(AND($P45=1,$L45=AL$4),2,IF(AND($L45<>AL$4,AL44=2),AL44,IF($L45<>AL$4,0,1)))) -> 0
A46: 5647 | B46: A.5.1.15.5 | C46: Does the third party risk management program require Confidentiality and/or Non-Disclosure Agreements from subcontractors? | D46: Yes | G46: Third Party Risk Management | H46: Subcontractors' Third Party Risk Management | I46: A.8 Subcontractor Contracting Process | J46: 13.2.4 Confidentiality or Non-Disclosure Agreements|15.1.2 Addressing Security Within Supplier Agreements | L46: 4 | M46: 2 | P46: =IF($L46="","",IF($D46="Yes",1,IF($D46="No",2,IF($D46="N/A",3,0)))) -> 1 | Q46: =IF(AND(Drops!$D$45>1,OR(U46<>U45,AND(ROW()=5,U45=U46))),VLOOKUP(U46,Drops!$D$26:$E$44,2,FALSE),"") | R46: =IF(Q46<>"",ROW(),"") | S46: =OFFSET(AC46,,L46-1) -> 1 | T46: =IF(OR(V46<>V45,U46<>U45,AND(V46<>V45,W46<>W45),AND(V46<>V45,W46<>W45,X46<>X45),AND(V46<>V45,W46<>W45,X46<>X45,Y46<>Y45),AND(V46<>V45,W46<>W45,X46<>X45,Y46<>Y45,Z46<>Z45),L46-L45>1),1,0) -> 0 | U46: A | V46: 5 | W46: 1 | X46: 15 | Y46: 5 | Z46: 0 | AA46: =IF(ROW()=5,1,IF(OR(AH46=1,P46>0,T46=1),1,IF(OR(AND(AH46=2,AI46=1),AND(AI46=2,AJ46=1),AND(AJ46=2,AK46=1),AND(AK46=2,AL46=1)),1,0))) -> 1 | AB46: =IF(L47>L46,1,0) -> 0 | AC46: =IF(ROW()=5,P46,IF(AND($P46>1,AC$4=$L46),$P46,IF(AND($U46=$U45,V46=V45),AC45,IF(AND($L46=AC$4,P46=1),P46,0)))) -> 1 | AD46: =IF(AC46>1,AC46,IF(AND($P46>1,AD$4=$L46),$P46,IF(AND($U46=$U45,W46=W45),AD45,IF(AND($L46=AD$4,P46=1),P46,0)))) -> 1 | AE46: =IF(AD46>1,AD46,IF(AND($P46>1,AE$4=$L46),$P46,IF(AND($U46=$U45,X46=X45),AE45,IF(AND($L46=AE$4,P46=1),P46,0)))) -> 1 | AF46: =IF(AE46>1,AE46,IF(AND($P46>1,AF$4=$L46),$P46,IF(AND($U46=$U45,Y46=Y45),AF45,IF(AND($L46=AF$4,P46=1),P46,0)))) -> 1 | AG46: =IF(AF46>1,AF46,IF(AND($P46>1,AG$4=$L46),$P46,IF(AND($U46=$U45,Z46=Z45),AG45,IF(AND($L46=AG$4,P46=1),P46,0)))) -> 0 | AH46: =IF(AND($P46=1,$L46=AH$4),2,IF(AND($L46<>AH$4,AH45=2),AH45,IF($L46<>AH$4,0,1))) -> 2 | AI46: =IF(OR(ROW()=5,$U45<>$U46),0,IF(AND($P46=1,$L46=AI$4),2,IF(AND($L46<>AI$4,AI45=2),AI45,IF($L46<>AI$4,0,1)))) -> 2 | AJ46: =IF(OR(ROW()=5,$U45<>$U46),0,IF(AND($P46=1,$L46=AJ$4),2,IF(AND($L46<>AJ$4,AJ45=2),AJ45,IF($L46<>AJ$4,0,1)))) -> 2 | AK46: =IF(OR(ROW()=5,$U45<>$U46),0,IF(AND($P46=1,$L46=AK$4),2,IF(AND($L46<>AK$4,AK45=2),AK45,IF($L46<>AK$4,0,1)))) -> 2 | AL46: =IF(OR(ROW()=5,$U45<>$U46),0,IF(AND($P46=1,$L46=AL$4),2,IF(AND($L46<>AL$4,AL45=2),AL45,IF($L46<>AL$4,0,1)))) -> 0
A47: 5648 | B47: A.5.1.15.6 | C47: Does the third party risk program require subcontractors to notify if there are changes affecting services rendered? | D47: Yes | G47: Third Party Risk Management | H47: Subcontractors' Third Party Risk Management | L47: 4 | M47: 2 | P47: =IF($L47="","",IF($D47="Yes",1,IF($D47="No",2,IF($D47="N/A",3,0)))) -> 1 | Q47: =IF(AND(Drops!$D$45>1,OR(U47<>U46,AND(ROW()=5,U46=U47))),VLOOKUP(U47,Drops!$D$26:$E$44,2,FALSE),"") | R47: =IF(Q47<>"",ROW(),"") | S47: =OFFSET(AC47,,L47-1) -> 1 | T47: =IF(OR(V47<>V46,U47<>U46,AND(V47<>V46,W47<>W46),AND(V47<>V46,W47<>W46,X47<>X46),AND(V47<>V46,W47<>W46,X47<>X46,Y47<>Y46),AND(V47<>V46,W47<>W46,X47<>X46,Y47<>Y46,Z47<>Z46),L47-L46>1),1,0) -> 0 | U47: A | V47: 5 | W47: 1 | X47: 15 | Y47: 6 | Z47: 0 | AA47: =IF(ROW()=5,1,IF(OR(AH47=1,P47>0,T47=1),1,IF(OR(AND(AH47=2,AI47=1),AND(AI47=2,AJ47=1),AND(AJ47=2,AK47=1),AND(AK47=2,AL47=1)),1,0))) -> 1 | AB47: =IF(L48>L47,1,0) -> 0 | AC47: =IF(ROW()=5,P47,IF(AND($P47>1,AC$4=$L47),$P47,IF(AND($U47=$U46,V47=V46),AC46,IF(AND($L47=AC$4,P47=1),P47,0)))) -> 1 | AD47: =IF(AC47>1,AC47,IF(AND($P47>1,AD$4=$L47),$P47,IF(AND($U47=$U46,W47=W46),AD46,IF(AND($L47=AD$4,P47=1),P47,0)))) -> 1 | AE47: =IF(AD47>1,AD47,IF(AND($P47>1,AE$4=$L47),$P47,IF(AND($U47=$U46,X47=X46),AE46,IF(AND($L47=AE$4,P47=1),P47,0)))) -> 1 | AF47: =IF(AE47>1,AE47,IF(AND($P47>1,AF$4=$L47),$P47,IF(AND($U47=$U46,Y47=Y46),AF46,IF(AND($L47=AF$4,P47=1),P47,0)))) -> 1 | AG47: =IF(AF47>1,AF47,IF(AND($P47>1,AG$4=$L47),$P47,IF(AND($U47=$U46,Z47=Z46),AG46,IF(AND($L47=AG$4,P47=1),P47,0)))) -> 0 | AH47: =IF(AND($P47=1,$L47=AH$4),2,IF(AND($L47<>AH$4,AH46=2),AH46,IF($L47<>AH$4,0,1))) -> 2 | AI47: =IF(OR(ROW()=5,$U46<>$U47),0,IF(AND($P47=1,$L47=AI$4),2,IF(AND($L47<>AI$4,AI46=2),AI46,IF($L47<>AI$4,0,1)))) -> 2 | AJ47: =IF(OR(ROW()=5,$U46<>$U47),0,IF(AND($P47=1,$L47=AJ$4),2,IF(AND($L47<>AJ$4,AJ46=2),AJ46,IF($L47<>AJ$4,0,1)))) -> 2 | AK47: =IF(OR(ROW()=5,$U46<>$U47),0,IF(AND($P47=1,$L47=AK$4),2,IF(AND($L47<>AK$4,AK46=2),AK46,IF($L47<>AK$4,0,1)))) -> 2 | AL47: =IF(OR(ROW()=5,$U46<>$U47),0,IF(AND($P47=1,$L47=AL$4),2,IF(AND($L47<>AL$4,AL46=2),AL46,IF($L47<>AL$4,0,1)))) -> 0
A48: 5649 | B48: A.5.1.15.7 | C48: Does the third party risk management program require background checks performed for service provider contractors and subcontractors? | D48: Yes | G48: Third Party Risk Management | H48: Service Provider Background Checks | J48: 7.1.1 Screening | L48: 4 | M48: 2 | P48: =IF($L48="","",IF($D48="Yes",1,IF($D48="No",2,IF($D48="N/A",3,0)))) -> 1 | Q48: =IF(AND(Drops!$D$45>1,OR(U48<>U47,AND(ROW()=5,U47=U48))),VLOOKUP(U48,Drops!$D$26:$E$44,2,FALSE),"") | R48: =IF(Q48<>"",ROW(),"") | S48: =OFFSET(AC48,,L48-1) -> 1 | T48: =IF(OR(V48<>V47,U48<>U47,AND(V48<>V47,W48<>W47),AND(V48<>V47,W48<>W47,X48<>X47),AND(V48<>V47,W48<>W47,X48<>X47,Y48<>Y47),AND(V48<>V47,W48<>W47,X48<>X47,Y48<>Y47,Z48<>Z47),L48-L47>1),1,0) -> 0 | U48: A | V48: 5 | W48: 1 | X48: 15 | Y48: 7 | Z48: 0 | AA48: =IF(ROW()=5,1,IF(OR(AH48=1,P48>0,T48=1),1,IF(OR(AND(AH48=2,AI48=1),AND(AI48=2,AJ48=1),AND(AJ48=2,AK48=1),AND(AK48=2,AL48=1)),1,0))) -> 1 | AB48: =IF(L49>L48,1,0) -> 1 | AC48: =IF(ROW()=5,P48,IF(AND($P48>1,AC$4=$L48),$P48,IF(AND($U48=$U47,V48=V47),AC47,IF(AND($L48=AC$4,P48=1),P48,0)))) -> 1 | AD48: =IF(AC48>1,AC48,IF(AND($P48>1,AD$4=$L48),$P48,IF(AND($U48=$U47,W48=W47),AD47,IF(AND($L48=AD$4,P48=1),P48,0)))) -> 1 | AE48: =IF(AD48>1,AD48,IF(AND($P48>1,AE$4=$L48),$P48,IF(AND($U48=$U47,X48=X47),AE47,IF(AND($L48=AE$4,P48=1),P48,0)))) -> 1 | AF48: =IF(AE48>1,AE48,IF(AND($P48>1,AF$4=$L48),$P48,IF(AND($U48=$U47,Y48=Y47),AF47,IF(AND($L48=AF$4,P48=1),P48,0)))) -> 1 | AG48: =IF(AF48>1,AF48,IF(AND($P48>1,AG$4=$L48),$P48,IF(AND($U48=$U47,Z48=Z47),AG47,IF(AND($L48=AG$4,P48=1),P48,0)))) -> 0 | AH48: =IF(AND($P48=1,$L48=AH$4),2,IF(AND($L48<>AH$4,AH47=2),AH47,IF($L48<>AH$4,0,1))) -> 2 | AI48: =IF(OR(ROW()=5,$U47<>$U48),0,IF(AND($P48=1,$L48=AI$4),2,IF(AND($L48<>AI$4,AI47=2),AI47,IF($L48<>AI$4,0,1)))) -> 2 | AJ48: =IF(OR(ROW()=5,$U47<>$U48),0,IF(AND($P48=1,$L48=AJ$4),2,IF(AND($L48<>AJ$4,AJ47=2),AJ47,IF($L48<>AJ$4,0,1)))) -> 2 | AK48: =IF(OR(ROW()=5,$U47<>$U48),0,IF(AND($P48=1,$L48=AK$4),2,IF(AND($L48<>AK$4,AK47=2),AK47,IF($L48<>AK$4,0,1)))) -> 2 | AL48: =IF(OR(ROW()=5,$U47<>$U48),0,IF(AND($P48=1,$L48=AL$4),2,IF(AND($L48<>AL$4,AL47=2),AL47,IF($L48<>AL$4,0,1)))) -> 0
A49: 3522 | B49: A.5.1.15.7.1 | C49: Are background checks performed at time of hire? | D49: Yes | G49: Third Party Risk Management | H49: Service Provider Background Checks | J49: 7.1.1 Screening | L49: 5 | M49: 3 | P49: =IF($L49="","",IF($D49="Yes",1,IF($D49="No",2,IF($D49="N/A",3,0)))) -> 1 | Q49: =IF(AND(Drops!$D$45>1,OR(U49<>U48,AND(ROW()=5,U48=U49))),VLOOKUP(U49,Drops!$D$26:$E$44,2,FALSE),"") | R49: =IF(Q49<>"",ROW(),"") | S49: =OFFSET(AC49,,L49-1) -> 1 | T49: =IF(OR(V49<>V48,U49<>U48,AND(V49<>V48,W49<>W48),AND(V49<>V48,W49<>W48,X49<>X48),AND(V49<>V48,W49<>W48,X49<>X48,Y49<>Y48),AND(V49<>V48,W49<>W48,X49<>X48,Y49<>Y48,Z49<>Z48),L49-L48>1),1,0) -> 0 | U49: A | V49: 5 | W49: 1 | X49: 15 | Y49: 7 | Z49: 1 | AA49: =IF(ROW()=5,1,IF(OR(AH49=1,P49>0,T49=1),1,IF(OR(AND(AH49=2,AI49=1),AND(AI49=2,AJ49=1),AND(AJ49=2,AK49=1),AND(AK49=2,AL49=1)),1,0))) -> 1 | AB49: =IF(L50>L49,1,0) -> 0 | AC49: =IF(ROW()=5,P49,IF(AND($P49>1,AC$4=$L49),$P49,IF(AND($U49=$U48,V49=V48),AC48,IF(AND($L49=AC$4,P49=1),P49,0)))) -> 1 | AD49: =IF(AC49>1,AC49,IF(AND($P49>1,AD$4=$L49),$P49,IF(AND($U49=$U48,W49=W48),AD48,IF(AND($L49=AD$4,P49=1),P49,0)))) -> 1 | AE49: =IF(AD49>1,AD49,IF(AND($P49>1,AE$4=$L49),$P49,IF(AND($U49=$U48,X49=X48),AE48,IF(AND($L49=AE$4,P49=1),P49,0)))) -> 1 | AF49: =IF(AE49>1,AE49,IF(AND($P49>1,AF$4=$L49),$P49,IF(AND($U49=$U48,Y49=Y48),AF48,IF(AND($L49=AF$4,P49=1),P49,0)))) -> 1 | AG49: =IF(AF49>1,AF49,IF(AND($P49>1,AG$4=$L49),$P49,IF(AND($U49=$U48,Z49=Z48),AG48,IF(AND($L49=AG$4,P49=1),P49,0)))) -> 1 | AH49: =IF(AND($P49=1,$L49=AH$4),2,IF(AND($L49<>AH$4,AH48=2),AH48,IF($L49<>AH$4,0,1))) -> 2 | AI49: =IF(OR(ROW()=5,$U48<>$U49),0,IF(AND($P49=1,$L49=AI$4),2,IF(AND($L49<>AI$4,AI48=2),AI48,IF($L49<>AI$4,0,1)))) -> 2 | AJ49: =IF(OR(ROW()=5,$U48<>$U49),0,IF(AND($P49=1,$L49=AJ$4),2,IF(AND($L49<>AJ$4,AJ48=2),AJ48,IF($L49<>AJ$4,0,1)))) -> 2 | AK49: =IF(OR(ROW()=5,$U48<>$U49),0,IF(AND($P49=1,$L49=AK$4),2,IF(AND($L49<>AK$4,AK48=2),AK48,IF($L49<>AK$4,0,1)))) -> 2 | AL49: =IF(OR(ROW()=5,$U48<>$U49),0,IF(AND($P49=1,$L49=AL$4),2,IF(AND($L49<>AL$4,AL48=2),AL48,IF($L49<>AL$4,0,1)))) -> 2
A50: 3525 | B50: A.5.1.15.7.2 | C50: Are background checks performed periodically, at least as frequently as required by regulations? | D50: N/A | E50: Seismic is not required by regulations to complete background checks after hire. | G50: Third Party Risk Management | H50: Service Provider Background Checks | J50: 7.1.1 Screening | L50: 5 | M50: 3 | P50: =IF($L50="","",IF($D50="Yes",1,IF($D50="No",2,IF($D50="N/A",3,0)))) -> 3 | Q50: =IF(AND(Drops!$D$45>1,OR(U50<>U49,AND(ROW()=5,U49=U50))),VLOOKUP(U50,Drops!$D$26:$E$44,2,FALSE),"") | R50: =IF(Q50<>"",ROW(),"") | S50: =OFFSET(AC50,,L50-1) -> 3 | T50: =IF(OR(V50<>V49,U50<>U49,AND(V50<>V49,W50<>W49),AND(V50<>V49,W50<>W49,X50<>X49),AND(V50<>V49,W50<>W49,X50<>X49,Y50<>Y49),AND(V50<>V49,W50<>W49,X50<>X49,Y50<>Y49,Z50<>Z49),L50-L49>1),1,0) -> 0 | U50: A | V50: 5 | W50: 1 | X50: 15 | Y50: 7 | Z50: 2 | AA50: =IF(ROW()=5,1,IF(OR(AH50=1,P50>0,T50=1),1,IF(OR(AND(AH50=2,AI50=1),AND(AI50=2,AJ50=1),AND(AJ50=2,AK50=1),AND(AK50=2,AL50=1)),1,0))) -> 1 | AB50: =IF(L51>L50,1,0) -> 0 | AC50: =IF(ROW()=5,P50,IF(AND($P50>1,AC$4=$L50),$P50,IF(AND($U50=$U49,V50=V49),AC49,IF(AND($L50=AC$4,P50=1),P50,0)))) -> 1 | AD50: =IF(AC50>1,AC50,IF(AND($P50>1,AD$4=$L50),$P50,IF(AND($U50=$U49,W50=W49),AD49,IF(AND($L50=AD$4,P50=1),P50,0)))) -> 1 | AE50: =IF(AD50>1,AD50,IF(AND($P50>1,AE$4=$L50),$P50,IF(AND($U50=$U49,X50=X49),AE49,IF(AND($L50=AE$4,P50=1),P50,0)))) -> 1 | AF50: =IF(AE50>1,AE50,IF(AND($P50>1,AF$4=$L50),$P50,IF(AND($U50=$U49,Y50=Y49),AF49,IF(AND($L50=AF$4,P50=1),P50,0)))) -> 1 | AG50: =IF(AF50>1,AF50,IF(AND($P50>1,AG$4=$L50),$P50,IF(AND($U50=$U49,Z50=Z49),AG49,IF(AND($L50=AG$4,P50=1),P50,0)))) -> 3 | AH50: =IF(AND($P50=1,$L50=AH$4),2,IF(AND($L50<>AH$4,AH49=2),AH49,IF($L50<>AH$4,0,1))) -> 2 | AI50: =IF(OR(ROW()=5,$U49<>$U50),0,IF(AND($P50=1,$L50=AI$4),2,IF(AND($L50<>AI$4,AI49=2),AI49,IF($L50<>AI$4,0,1)))) -> 2 | AJ50: =IF(OR(ROW()=5,$U49<>$U50),0,IF(AND($P50=1,$L50=AJ$4),2,IF(AND($L50<>AJ$4,AJ49=2),AJ49,IF($L50<>AJ$4,0,1)))) -> 2 | AK50: =IF(OR(ROW()=5,$U49<>$U50),0,IF(AND($P50=1,$L50=AK$4),2,IF(AND($L50<>AK$4,AK49=2),AK49,IF($L50<>AK$4,0,1)))) -> 2 | AL50: =IF(OR(ROW()=5,$U49<>$U50),0,IF(AND($P50=1,$L50=AL$4),2,IF(AND($L50<>AL$4,AL49=2),AL49,IF($L50<>AL$4,0,1)))) -> 1
A51: 72 | B51: A.5.2 | C51: For all subcontractors requiring assessment, is there a contract? | D51: Yes | E51: AWS provides data center hosting | G51: Third Party Risk Management | H51: Service Provider Agreements | I51: A.6 Service Provider Agreements | J51: 15.1.1 Information Security Policy for Supplier Relationships|15.1.2 Addressing Security Within Supplier Agreements|15.1.3 Information and Communication Technology Supply Chain|15.2.1 Monitoring and Review of Supplier Services|7.1.2 Terms and Condition of Employment | L51: 2 | M51: 2 | P51: =IF($L51="","",IF($D51="Yes",1,IF($D51="No",2,IF($D51="N/A",3,0)))) -> 1 | Q51: =IF(AND(Drops!$D$45>1,OR(U51<>U50,AND(ROW()=5,U50=U51))),VLOOKUP(U51,Drops!$D$26:$E$44,2,FALSE),"") | R51: =IF(Q51<>"",ROW(),"") | S51: =OFFSET(AC51,,L51-1) -> 1 | T51: =IF(OR(V51<>V50,U51<>U50,AND(V51<>V50,W51<>W50),AND(V51<>V50,W51<>W50,X51<>X50),AND(V51<>V50,W51<>W50,X51<>X50,Y51<>Y50),AND(V51<>V50,W51<>W50,X51<>X50,Y51<>Y50,Z51<>Z50),L51-L50>1),1,0) -> 0 | U51: A | V51: 5 | W51: 2 | X51: 0 | Y51: 0 | Z51: 0 | AA51: =IF(ROW()=5,1,IF(OR(AH51=1,P51>0,T51=1),1,IF(OR(AND(AH51=2,AI51=1),AND(AI51=2,AJ51=1),AND(AJ51=2,AK51=1),AND(AK51=2,AL51=1)),1,0))) -> 1 | AB51: =IF(L52>L51,1,0) -> 1 | AC51: =IF(ROW()=5,P51,IF(AND($P51>1,AC$4=$L51),$P51,IF(AND($U51=$U50,V51=V50),AC50,IF(AND($L51=AC$4,P51=1),P51,0)))) -> 1 | AD51: =IF(AC51>1,AC51,IF(AND($P51>1,AD$4=$L51),$P51,IF(AND($U51=$U50,W51=W50),AD50,IF(AND($L51=AD$4,P51=1),P51,0)))) -> 1 | AE51: =IF(AD51>1,AD51,IF(AND($P51>1,AE$4=$L51),$P51,IF(AND($U51=$U50,X51=X50),AE50,IF(AND($L51=AE$4,P51=1),P51,0)))) -> 0 | AF51: =IF(AE51>1,AE51,IF(AND($P51>1,AF$4=$L51),$P51,IF(AND($U51=$U50,Y51=Y50),AF50,IF(AND($L51=AF$4,P51=1),P51,0)))) -> 0 | AG51: =IF(AF51>1,AF51,IF(AND($P51>1,AG$4=$L51),$P51,IF(AND($U51=$U50,Z51=Z50),AG50,IF(AND($L51=AG$4,P51=1),P51,0)))) -> 0 | AH51: =IF(AND($P51=1,$L51=AH$4),2,IF(AND($L51<>AH$4,AH50=2),AH50,IF($L51<>AH$4,0,1))) -> 2 | AI51: =IF(OR(ROW()=5,$U50<>$U51),0,IF(AND($P51=1,$L51=AI$4),2,IF(AND($L51<>AI$4,AI50=2),AI50,IF($L51<>AI$4,0,1)))) -> 2 | AJ51: =IF(OR(ROW()=5,$U50<>$U51),0,IF(AND($P51=1,$L51=AJ$4),2,IF(AND($L51<>AJ$4,AJ50=2),AJ50,IF($L51<>AJ$4,0,1)))) -> 2 | AK51: =IF(OR(ROW()=5,$U50<>$U51),0,IF(AND($P51=1,$L51=AK$4),2,IF(AND($L51<>AK$4,AK50=2),AK50,IF($L51<>AK$4,0,1)))) -> 2 | AL51: =IF(OR(ROW()=5,$U50<>$U51),0,IF(AND($P51=1,$L51=AL$4),2,IF(AND($L51<>AL$4,AL50=2),AL50,IF($L51<>AL$4,0,1)))) -> 0
A52: 74 | B52: A.5.2.1 | C52: Do contracts with all subcontractors include Non-Disclosure/Confidentiality Agreements? | D52: Yes | G52: Third Party Risk Management | H52: Service Provider Agreements | I52: A.6 Service Provider Agreements | J52: 13.2.2 Agreements on Information Transfer|13.2.4 Confidentiality or Non-Disclosure Agreements|15.1.1 Information Security Policy for Supplier Relationships|15.1.2 Addressing Security Within Supplier Agreements|7.1.2 Terms and Condition of Employment | L52: 3 | M52: 2 | P52: =IF($L52="","",IF($D52="Yes",1,IF($D52="No",2,IF($D52="N/A",3,0)))) -> 1 | Q52: =IF(AND(Drops!$D$45>1,OR(U52<>U51,AND(ROW()=5,U51=U52))),VLOOKUP(U52,Drops!$D$26:$E$44,2,FALSE),"") | R52: =IF(Q52<>"",ROW(),"") | S52: =OFFSET(AC52,,L52-1) -> 1 | T52: =IF(OR(V52<>V51,U52<>U51,AND(V52<>V51,W52<>W51),AND(V52<>V51,W52<>W51,X52<>X51),AND(V52<>V51,W52<>W51,X52<>X51,Y52<>Y51),AND(V52<>V51,W52<>W51,X52<>X51,Y52<>Y51,Z52<>Z51),L52-L51>1),1,0) -> 0 | U52: A | V52: 5 | W52: 2 | X52: 1 | Y52: 0 | Z52: 0 | AA52: =IF(ROW()=5,1,IF(OR(AH52=1,P52>0,T52=1),1,IF(OR(AND(AH52=2,AI52=1),AND(AI52=2,AJ52=1),AND(AJ52=2,AK52=1),AND(AK52=2,AL52=1)),1,0))) -> 1 | AB52: =IF(L53>L52,1,0) -> 0 | AC52: =IF(ROW()=5,P52,IF(AND($P52>1,AC$4=$L52),$P52,IF(AND($U52=$U51,V52=V51),AC51,IF(AND($L52=AC$4,P52=1),P52,0)))) -> 1 | AD52: =IF(AC52>1,AC52,IF(AND($P52>1,AD$4=$L52),$P52,IF(AND($U52=$U51,W52=W51),AD51,IF(AND($L52=AD$4,P52=1),P52,0)))) -> 1 | AE52: =IF(AD52>1,AD52,IF(AND($P52>1,AE$4=$L52),$P52,IF(AND($U52=$U51,X52=X51),AE51,IF(AND($L52=AE$4,P52=1),P52,0)))) -> 1 | AF52: =IF(AE52>1,AE52,IF(AND($P52>1,AF$4=$L52),$P52,IF(AND($U52=$U51,Y52=Y51),AF51,IF(AND($L52=AF$4,P52=1),P52,0)))) -> 0 | AG52: =IF(AF52>1,AF52,IF(AND($P52>1,AG$4=$L52),$P52,IF(AND($U52=$U51,Z52=Z51),AG51,IF(AND($L52=AG$4,P52=1),P52,0)))) -> 0 | AH52: =IF(AND($P52=1,$L52=AH$4),2,IF(AND($L52<>AH$4,AH51=2),AH51,IF($L52<>AH$4,0,1))) -> 2 | AI52: =IF(OR(ROW()=5,$U51<>$U52),0,IF(AND($P52=1,$L52=AI$4),2,IF(AND($L52<>AI$4,AI51=2),AI51,IF($L52<>AI$4,0,1)))) -> 2 | AJ52: =IF(OR(ROW()=5,$U51<>$U52),0,IF(AND($P52=1,$L52=AJ$4),2,IF(AND($L52<>AJ$4,AJ51=2),AJ51,IF($L52<>AJ$4,0,1)))) -> 2 | AK52: =IF(OR(ROW()=5,$U51<>$U52),0,IF(AND($P52=1,$L52=AK$4),2,IF(AND($L52<>AK$4,AK51=2),AK51,IF($L52<>AK$4,0,1)))) -> 2 | AL52: =IF(OR(ROW()=5,$U51<>$U52),0,IF(AND($P52=1,$L52=AL$4),2,IF(AND($L52<>AL$4,AL51=2),AL51,IF($L52<>AL$4,0,1)))) -> 0
A53: 2506 | B53: A.5.2.2 | C53: Do contracts with all subcontractors include ownership of information, trade secrets and intellectual property? | D53: Yes | G53: Third Party Risk Management | H53: Service Provider Agreements | I53: A.6 Service Provider Agreements | J53: 13.2.2 Agreements on Information Transfer|13.2.4 Confidentiality or Non-Disclosure Agreements|15.1.1 Information Security Policy for Supplier Relationships|15.1.2 Addressing Security Within Supplier Agreements|15.1.3 Information and Communication Technology Supply Chain|7.1.2 Terms and Condition of Employment | L53: 3 | M53: 2 | P53: =IF($L53="","",IF($D53="Yes",1,IF($D53="No",2,IF($D53="N/A",3,0)))) -> 1 | Q53: =IF(AND(Drops!$D$45>1,OR(U53<>U52,AND(ROW()=5,U52=U53))),VLOOKUP(U53,Drops!$D$26:$E$44,2,FALSE),"") | R53: =IF(Q53<>"",ROW(),"") | S53: =OFFSET(AC53,,L53-1) -> 1 | T53: =IF(OR(V53<>V52,U53<>U52,AND(V53<>V52,W53<>W52),AND(V53<>V52,W53<>W52,X53<>X52),AND(V53<>V52,W53<>W52,X53<>X52,Y53<>Y52),AND(V53<>V52,W53<>W52,X53<>X52,Y53<>Y52,Z53<>Z52),L53-L52>1),1,0) -> 0 | U53: A | V53: 5 | W53: 2 | X53: 2 | Y53: 0 | Z53: 0 | AA53: =IF(ROW()=5,1,IF(OR(AH53=1,P53>0,T53=1),1,IF(OR(AND(AH53=2,AI53=1),AND(AI53=2,AJ53=1),AND(AJ53=2,AK53=1),AND(AK53=2,AL53=1)),1,0))) -> 1 | AB53: =IF(L54>L53,1,0) -> 0 | AC53: =IF(ROW()=5,P53,IF(AND($P53>1,AC$4=$L53),$P53,IF(AND($U53=$U52,V53=V52),AC52,IF(AND($L53=AC$4,P53=1),P53,0)))) -> 1 | AD53: =IF(AC53>1,AC53,IF(AND($P53>1,AD$4=$L53),$P53,IF(AND($U53=$U52,W53=W52),AD52,IF(AND($L53=AD$4,P53=1),P53,0)))) -> 1 | AE53: =IF(AD53>1,AD53,IF(AND($P53>1,AE$4=$L53),$P53,IF(AND($U53=$U52,X53=X52),AE52,IF(AND($L53=AE$4,P53=1),P53,0)))) -> 1 | AF53: =IF(AE53>1,AE53,IF(AND($P53>1,AF$4=$L53),$P53,IF(AND($U53=$U52,Y53=Y52),AF52,IF(AND($L53=AF$4,P53=1),P53,0)))) -> 0 | AG53: =IF(AF53>1,AF53,IF(AND($P53>1,AG$4=$L53),$P53,IF(AND($U53=$U52,Z53=Z52),AG52,IF(AND($L53=AG$4,P53=1),P53,0)))) -> 0 | AH53: =IF(AND($P53=1,$L53=AH$4),2,IF(AND($L53<>AH$4,AH52=2),AH52,IF($L53<>AH$4,0,1))) -> 2 | AI53: =IF(OR(ROW()=5,$U52<>$U53),0,IF(AND($P53=1,$L53=AI$4),2,IF(AND($L53<>AI$4,AI52=2),AI52,IF($L53<>AI$4,0,1)))) -> 2 | AJ53: =IF(OR(ROW()=5,$U52<>$U53),0,IF(AND($P53=1,$L53=AJ$4),2,IF(AND($L53<>AJ$4,AJ52=2),AJ52,IF($L53<>AJ$4,0,1)))) -> 2 | AK53: =IF(OR(ROW()=5,$U52<>$U53),0,IF(AND($P53=1,$L53=AK$4),2,IF(AND($L53<>AK$4,AK52=2),AK52,IF($L53<>AK$4,0,1)))) -> 2 | AL53: =IF(OR(ROW()=5,$U52<>$U53),0,IF(AND($P53=1,$L53=AL$4),2,IF(AND($L53<>AL$4,AL52=2),AL52,IF($L53<>AL$4,0,1)))) -> 0
A54: 4170 | B54: A.5.2.3 | C54: Do contracts with all subcontractors include all applicable privacy and security requirements? | D54: Yes | G54: Third Party Risk Management | H54: Service Provider Agreements | I54: A.6 Service Provider Agreements | J54: 13.2.2 Agreements on Information Transfer|15.1.1 Information Security Policy for Supplier Relationships|15.1.2 Addressing Security Within Supplier Agreements|15.1.3 Information and Communication Technology Supply Chain|7.1.2 Terms and Condition of Employment|7.2.1 Management Responsibilities | L54: 3 | M54: 3 | P54: =IF($L54="","",IF($D54="Yes",1,IF($D54="No",2,IF($D54="N/A",3,0)))) -> 1 | Q54: =IF(AND(Drops!$D$45>1,OR(U54<>U53,AND(ROW()=5,U53=U54))),VLOOKUP(U54,Drops!$D$26:$E$44,2,FALSE),"") | R54: =IF(Q54<>"",ROW(),"") | S54: =OFFSET(AC54,,L54-1) -> 1 | T54: =IF(OR(V54<>V53,U54<>U53,AND(V54<>V53,W54<>W53),AND(V54<>V53,W54<>W53,X54<>X53),AND(V54<>V53,W54<>W53,X54<>X53,Y54<>Y53),AND(V54<>V53,W54<>W53,X54<>X53,Y54<>Y53,Z54<>Z53),L54-L53>1),1,0) -> 0 | U54: A | V54: 5 | W54: 2 | X54: 3 | Y54: 0 | Z54: 0 | AA54: =IF(ROW()=5,1,IF(OR(AH54=1,P54>0,T54=1),1,IF(OR(AND(AH54=2,AI54=1),AND(AI54=2,AJ54=1),AND(AJ54=2,AK54=1),AND(AK54=2,AL54=1)),1,0))) -> 1 | AB54: =IF(L55>L54,1,0) -> 0 | AC54: =IF(ROW()=5,P54,IF(AND($P54>1,AC$4=$L54),$P54,IF(AND($U54=$U53,V54=V53),AC53,IF(AND($L54=AC$4,P54=1),P54,0)))) -> 1 | AD54: =IF(AC54>1,AC54,IF(AND($P54>1,AD$4=$L54),$P54,IF(AND($U54=$U53,W54=W53),AD53,IF(AND($L54=AD$4,P54=1),P54,0)))) -> 1 | AE54: =IF(AD54>1,AD54,IF(AND($P54>1,AE$4=$L54),$P54,IF(AND($U54=$U53,X54=X53),AE53,IF(AND($L54=AE$4,P54=1),P54,0)))) -> 1 | AF54: =IF(AE54>1,AE54,IF(AND($P54>1,AF$4=$L54),$P54,IF(AND($U54=$U53,Y54=Y53),AF53,IF(AND($L54=AF$4,P54=1),P54,0)))) -> 0 | AG54: =IF(AF54>1,AF54,IF(AND($P54>1,AG$4=$L54),$P54,IF(AND($U54=$U53,Z54=Z53),AG53,IF(AND($L54=AG$4,P54=1),P54,0)))) -> 0 | AH54: =IF(AND($P54=1,$L54=AH$4),2,IF(AND($L54<>AH$4,AH53=2),AH53,IF($L54<>AH$4,0,1))) -> 2 | AI54: =IF(OR(ROW()=5,$U53<>$U54),0,IF(AND($P54=1,$L54=AI$4),2,IF(AND($L54<>AI$4,AI53=2),AI53,IF($L54<>AI$4,0,1)))) -> 2 | AJ54: =IF(OR(ROW()=5,$U53<>$U54),0,IF(AND($P54=1,$L54=AJ$4),2,IF(AND($L54<>AJ$4,AJ53=2),AJ53,IF($L54<>AJ$4,0,1)))) -> 2 | AK54: =IF(OR(ROW()=5,$U53<>$U54),0,IF(AND($P54=1,$L54=AK$4),2,IF(AND($L54<>AK$4,AK53=2),AK53,IF($L54<>AK$4,0,1)))) -> 2 | AL54: =IF(OR(ROW()=5,$U53<>$U54),0,IF(AND($P54=1,$L54=AL$4),2,IF(AND($L54<>AL$4,AL53=2),AL53,IF($L54<>AL$4,0,1)))) -> 0
A55: 4171 | B55: A.5.2.4 | C55: Do contracts with all subcontractors include permitted use and limitations of use of confidential information? | D55: Yes | G55: Third Party Risk Management | H55: Service Provider Agreements | J55: 13.2.2 Agreements on Information Transfer|13.2.4 Confidentiality or Non-Disclosure Agreements|15.1.1 Information Security Policy for Supplier Relationships|15.1.2 Addressing Security Within Supplier Agreements|15.1.3 Information and Communication Technology Supply Chain|7.1.2 Terms and Condition of Employment | L55: 3 | M55: 2 | P55: =IF($L55="","",IF($D55="Yes",1,IF($D55="No",2,IF($D55="N/A",3,0)))) -> 1 | Q55: =IF(AND(Drops!$D$45>1,OR(U55<>U54,AND(ROW()=5,U54=U55))),VLOOKUP(U55,Drops!$D$26:$E$44,2,FALSE),"") | R55: =IF(Q55<>"",ROW(),"") | S55: =OFFSET(AC55,,L55-1) -> 1 | T55: =IF(OR(V55<>V54,U55<>U54,AND(V55<>V54,W55<>W54),AND(V55<>V54,W55<>W54,X55<>X54),AND(V55<>V54,W55<>W54,X55<>X54,Y55<>Y54),AND(V55<>V54,W55<>W54,X55<>X54,Y55<>Y54,Z55<>Z54),L55-L54>1),1,0) -> 0 | U55: A | V55: 5 | W55: 2 | X55: 4 | Y55: 0 | Z55: 0 | AA55: =IF(ROW()=5,1,IF(OR(AH55=1,P55>0,T55=1),1,IF(OR(AND(AH55=2,AI55=1),AND(AI55=2,AJ55=1),AND(AJ55=2,AK55=1),AND(AK55=2,AL55=1)),1,0))) -> 1 | AB55: =IF(L56>L55,1,0) -> 0 | AC55: =IF(ROW()=5,P55,IF(AND($P55>1,AC$4=$L55),$P55,IF(AND($U55=$U54,V55=V54),AC54,IF(AND($L55=AC$4,P55=1),P55,0)))) -> 1 | AD55: =IF(AC55>1,AC55,IF(AND($P55>1,AD$4=$L55),$P55,IF(AND($U55=$U54,W55=W54),AD54,IF(AND($L55=AD$4,P55=1),P55,0)))) -> 1 | AE55: =IF(AD55>1,AD55,IF(AND($P55>1,AE$4=$L55),$P55,IF(AND($U55=$U54,X55=X54),AE54,IF(AND($L55=AE$4,P55=1),P55,0)))) -> 1 | AF55: =IF(AE55>1,AE55,IF(AND($P55>1,AF$4=$L55),$P55,IF(AND($U55=$U54,Y55=Y54),AF54,IF(AND($L55=AF$4,P55=1),P55,0)))) -> 0 | AG55: =IF(AF55>1,AF55,IF(AND($P55>1,AG$4=$L55),$P55,IF(AND($U55=$U54,Z55=Z54),AG54,IF(AND($L55=AG$4,P55=1),P55,0)))) -> 0 | AH55: =IF(AND($P55=1,$L55=AH$4),2,IF(AND($L55<>AH$4,AH54=2),AH54,IF($L55<>AH$4,0,1))) -> 2 | AI55: =IF(OR(ROW()=5,$U54<>$U55),0,IF(AND($P55=1,$L55=AI$4),2,IF(AND($L55<>AI$4,AI54=2),AI54,IF($L55<>AI$4,0,1)))) -> 2 | AJ55: =IF(OR(ROW()=5,$U54<>$U55),0,IF(AND($P55=1,$L55=AJ$4),2,IF(AND($L55<>AJ$4,AJ54=2),AJ54,IF($L55<>AJ$4,0,1)))) -> 2 | AK55: =IF(OR(ROW()=5,$U54<>$U55),0,IF(AND($P55=1,$L55=AK$4),2,IF(AND($L55<>AK$4,AK54=2),AK54,IF($L55<>AK$4,0,1)))) -> 2 | AL55: =IF(OR(ROW()=5,$U54<>$U55),0,IF(AND($P55=1,$L55=AL$4),2,IF(AND($L55<>AL$4,AL54=2),AL54,IF($L55<>AL$4,0,1)))) -> 0
A56: 81 | B56: A.5.2.5 | C56: Do contracts with all subcontractors include data breach notification? | D56: Yes | G56: Third Party Risk Management | H56: Service Provider Agreements | I56: A.6 Service Provider Agreements | J56: 15.1.1 Information Security Policy for Supplier Relationships|15.1.2 Addressing Security Within Supplier Agreements|15.1.3 Information and Communication Technology Supply Chain|16.1.3 Reporting Information Security Weaknesses|7.1.2 Terms and Condition of Employment | L56: 3 | M56: 2 | P56: =IF($L56="","",IF($D56="Yes",1,IF($D56="No",2,IF($D56="N/A",3,0)))) -> 1 | Q56: =IF(AND(Drops!$D$45>1,OR(U56<>U55,AND(ROW()=5,U55=U56))),VLOOKUP(U56,Drops!$D$26:$E$44,2,FALSE),"") | R56: =IF(Q56<>"",ROW(),"") | S56: =OFFSET(AC56,,L56-1) -> 1 | T56: =IF(OR(V56<>V55,U56<>U55,AND(V56<>V55,W56<>W55),AND(V56<>V55,W56<>W55,X56<>X55),AND(V56<>V55,W56<>W55,X56<>X55,Y56<>Y55),AND(V56<>V55,W56<>W55,X56<>X55,Y56<>Y55,Z56<>Z55),L56-L55>1),1,0) -> 0 | U56: A | V56: 5 | W56: 2 | X56: 5 | Y56: 0 | Z56: 0 | AA56: =IF(ROW()=5,1,IF(OR(AH56=1,P56>0,T56=1),1,IF(OR(AND(AH56=2,AI56=1),AND(AI56=2,AJ56=1),AND(AJ56=2,AK56=1),AND(AK56=2,AL56=1)),1,0))) -> 1 | AB56: =IF(L57>L56,1,0) -> 0 | AC56: =IF(ROW()=5,P56,IF(AND($P56>1,AC$4=$L56),$P56,IF(AND($U56=$U55,V56=V55),AC55,IF(AND($L56=AC$4,P56=1),P56,0)))) -> 1 | AD56: =IF(AC56>1,AC56,IF(AND($P56>1,AD$4=$L56),$P56,IF(AND($U56=$U55,W56=W55),AD55,IF(AND($L56=AD$4,P56=1),P56,0)))) -> 1 | AE56: =IF(AD56>1,AD56,IF(AND($P56>1,AE$4=$L56),$P56,IF(AND($U56=$U55,X56=X55),AE55,IF(AND($L56=AE$4,P56=1),P56,0)))) -> 1 | AF56: =IF(AE56>1,AE56,IF(AND($P56>1,AF$4=$L56),$P56,IF(AND($U56=$U55,Y56=Y55),AF55,IF(AND($L56=AF$4,P56=1),P56,0)))) -> 0 | AG56: =IF(AF56>1,AF56,IF(AND($P56>1,AG$4=$L56),$P56,IF(AND($U56=$U55,Z56=Z55),AG55,IF(AND($L56=AG$4,P56=1),P56,0)))) -> 0 | AH56: =IF(AND($P56=1,$L56=AH$4),2,IF(AND($L56<>AH$4,AH55=2),AH55,IF($L56<>AH$4,0,1))) -> 2 | AI56: =IF(OR(ROW()=5,$U55<>$U56),0,IF(AND($P56=1,$L56=AI$4),2,IF(AND($L56<>AI$4,AI55=2),AI55,IF($L56<>AI$4,0,1)))) -> 2 | AJ56: =IF(OR(ROW()=5,$U55<>$U56),0,IF(AND($P56=1,$L56=AJ$4),2,IF(AND($L56<>AJ$4,AJ55=2),AJ55,IF($L56<>AJ$4,0,1)))) -> 2 | AK56: =IF(OR(ROW()=5,$U55<>$U56),0,IF(AND($P56=1,$L56=AK$4),2,IF(AND($L56<>AK$4,AK55=2),AK55,IF($L56<>AK$4,0,1)))) -> 2 | AL56: =IF(OR(ROW()=5,$U55<>$U56),0,IF(AND($P56=1,$L56=AL$4),2,IF(AND($L56<>AL$4,AL55=2),AL55,IF($L56<>AL$4,0,1)))) -> 0
A57: 78 | B57: A.5.2.7 | C57: Do contracts with all subcontractors include Right to audit? | D57: Yes | G57: Third Party Risk Management | H57: Service Provider Agreements | I57: A.6 Service Provider Agreements | J57: 15.1.1 Information Security Policy for Supplier Relationships|15.1.2 Addressing Security Within Supplier Agreements|15.2.1 Monitoring and Review of Supplier Services | L57: 3 | M57: 3 | P57: =IF($L57="","",IF($D57="Yes",1,IF($D57="No",2,IF($D57="N/A",3,0)))) -> 1 | Q57: =IF(AND(Drops!$D$45>1,OR(U57<>U56,AND(ROW()=5,U56=U57))),VLOOKUP(U57,Drops!$D$26:$E$44,2,FALSE),"") | R57: =IF(Q57<>"",ROW(),"") | S57: =OFFSET(AC57,,L57-1) -> 1 | T57: =IF(OR(V57<>V56,U57<>U56,AND(V57<>V56,W57<>W56),AND(V57<>V56,W57<>W56,X57<>X56),AND(V57<>V56,W57<>W56,X57<>X56,Y57<>Y56),AND(V57<>V56,W57<>W56,X57<>X56,Y57<>Y56,Z57<>Z56),L57-L56>1),1,0) -> 0 | U57: A | V57: 5 | W57: 2 | X57: 7 | Y57: 0 | Z57: 0 | AA57: =IF(ROW()=5,1,IF(OR(AH57=1,P57>0,T57=1),1,IF(OR(AND(AH57=2,AI57=1),AND(AI57=2,AJ57=1),AND(AJ57=2,AK57=1),AND(AK57=2,AL57=1)),1,0))) -> 1 | AB57: =IF(L58>L57,1,0) -> 0 | AC57: =IF(ROW()=5,P57,IF(AND($P57>1,AC$4=$L57),$P57,IF(AND($U57=$U56,V57=V56),AC56,IF(AND($L57=AC$4,P57=1),P57,0)))) -> 1 | AD57: =IF(AC57>1,AC57,IF(AND($P57>1,AD$4=$L57),$P57,IF(AND($U57=$U56,W57=W56),AD56,IF(AND($L57=AD$4,P57=1),P57,0)))) -> 1 | AE57: =IF(AD57>1,AD57,IF(AND($P57>1,AE$4=$L57),$P57,IF(AND($U57=$U56,X57=X56),AE56,IF(AND($L57=AE$4,P57=1),P57,0)))) -> 1 | AF57: =IF(AE57>1,AE57,IF(AND($P57>1,AF$4=$L57),$P57,IF(AND($U57=$U56,Y57=Y56),AF56,IF(AND($L57=AF$4,P57=1),P57,0)))) -> 0 | AG57: =IF(AF57>1,AF57,IF(AND($P57>1,AG$4=$L57),$P57,IF(AND($U57=$U56,Z57=Z56),AG56,IF(AND($L57=AG$4,P57=1),P57,0)))) -> 0 | AH57: =IF(AND($P57=1,$L57=AH$4),2,IF(AND($L57<>AH$4,AH56=2),AH56,IF($L57<>AH$4,0,1))) -> 2 | AI57: =IF(OR(ROW()=5,$U56<>$U57),0,IF(AND($P57=1,$L57=AI$4),2,IF(AND($L57<>AI$4,AI56=2),AI56,IF($L57<>AI$4,0,1)))) -> 2 | AJ57: =IF(OR(ROW()=5,$U56<>$U57),0,IF(AND($P57=1,$L57=AJ$4),2,IF(AND($L57<>AJ$4,AJ56=2),AJ56,IF($L57<>AJ$4,0,1)))) -> 2 | AK57: =IF(OR(ROW()=5,$U56<>$U57),0,IF(AND($P57=1,$L57=AK$4),2,IF(AND($L57<>AK$4,AK56=2),AK56,IF($L57<>AK$4,0,1)))) -> 2 | AL57: =IF(OR(ROW()=5,$U56<>$U57),0,IF(AND($P57=1,$L57=AL$4),2,IF(AND($L57<>AL$4,AL56=2),AL56,IF($L57<>AL$4,0,1)))) -> 0
A58: 82 | B58: A.5.2.8 | C58: Do contracts with all subcontractors include Service Level Agreeements? | D58: Yes | G58: Third Party Risk Management | H58: Service Provider Agreements | I58: A.6 Service Provider Agreements | J58: 15.1.1 Information Security Policy for Supplier Relationships|15.2.1 Monitoring and Review of Supplier Services | L58: 3 | M58: 3 | P58: =IF($L58="","",IF($D58="Yes",1,IF($D58="No",2,IF($D58="N/A",3,0)))) -> 1 | Q58: =IF(AND(Drops!$D$45>1,OR(U58<>U57,AND(ROW()=5,U57=U58))),VLOOKUP(U58,Drops!$D$26:$E$44,2,FALSE),"") | R58: =IF(Q58<>"",ROW(),"") | S58: =OFFSET(AC58,,L58-1) -> 1 | T58: =IF(OR(V58<>V57,U58<>U57,AND(V58<>V57,W58<>W57),AND(V58<>V57,W58<>W57,X58<>X57),AND(V58<>V57,W58<>W57,X58<>X57,Y58<>Y57),AND(V58<>V57,W58<>W57,X58<>X57,Y58<>Y57,Z58<>Z57),L58-L57>1),1,0) -> 0 | U58: A | V58: 5 | W58: 2 | X58: 8 | Y58: 0 | Z58: 0 | AA58: =IF(ROW()=5,1,IF(OR(AH58=1,P58>0,T58=1),1,IF(OR(AND(AH58=2,AI58=1),AND(AI58=2,AJ58=1),AND(AJ58=2,AK58=1),AND(AK58=2,AL58=1)),1,0))) -> 1 | AB58: =IF(L59>L58,1,0) -> 0 | AC58: =IF(ROW()=5,P58,IF(AND($P58>1,AC$4=$L58),$P58,IF(AND($U58=$U57,V58=V57),AC57,IF(AND($L58=AC$4,P58=1),P58,0)))) -> 1 | AD58: =IF(AC58>1,AC58,IF(AND($P58>1,AD$4=$L58),$P58,IF(AND($U58=$U57,W58=W57),AD57,IF(AND($L58=AD$4,P58=1),P58,0)))) -> 1 | AE58: =IF(AD58>1,AD58,IF(AND($P58>1,AE$4=$L58),$P58,IF(AND($U58=$U57,X58=X57),AE57,IF(AND($L58=AE$4,P58=1),P58,0)))) -> 1 | AF58: =IF(AE58>1,AE58,IF(AND($P58>1,AF$4=$L58),$P58,IF(AND($U58=$U57,Y58=Y57),AF57,IF(AND($L58=AF$4,P58=1),P58,0)))) -> 0 | AG58: =IF(AF58>1,AF58,IF(AND($P58>1,AG$4=$L58),$P58,IF(AND($U58=$U57,Z58=Z57),AG57,IF(AND($L58=AG$4,P58=1),P58,0)))) -> 0 | AH58: =IF(AND($P58=1,$L58=AH$4),2,IF(AND($L58<>AH$4,AH57=2),AH57,IF($L58<>AH$4,0,1))) -> 2 | AI58: =IF(OR(ROW()=5,$U57<>$U58),0,IF(AND($P58=1,$L58=AI$4),2,IF(AND($L58<>AI$4,AI57=2),AI57,IF($L58<>AI$4,0,1)))) -> 2 | AJ58: =IF(OR(ROW()=5,$U57<>$U58),0,IF(AND($P58=1,$L58=AJ$4),2,IF(AND($L58<>AJ$4,AJ57=2),AJ57,IF($L58<>AJ$4,0,1)))) -> 2 | AK58: =IF(OR(ROW()=5,$U57<>$U58),0,IF(AND($P58=1,$L58=AK$4),2,IF(AND($L58<>AK$4,AK57=2),AK57,IF($L58<>AK$4,0,1)))) -> 2 | AL58: =IF(OR(ROW()=5,$U57<>$U58),0,IF(AND($P58=1,$L58=AL$4),2,IF(AND($L58<>AL$4,AL57=2),AL57,IF($L58<>AL$4,0,1)))) -> 0
A59: 85 | B59: A.5.2.9 | C59: Do contracts with all subcontractors include Indemnification/Liability? | D59: Yes | G59: Third Party Risk Management | H59: Service Provider Agreements | J59: 15.1.1 Information Security Policy for Supplier Relationships|15.1.2 Addressing Security Within Supplier Agreements | L59: 3 | M59: 2 | P59: =IF($L59="","",IF($D59="Yes",1,IF($D59="No",2,IF($D59="N/A",3,0)))) -> 1 | Q59: =IF(AND(Drops!$D$45>1,OR(U59<>U58,AND(ROW()=5,U58=U59))),VLOOKUP(U59,Drops!$D$26:$E$44,2,FALSE),"") | R59: =IF(Q59<>"",ROW(),"") | S59: =OFFSET(AC59,,L59-1) -> 1 | T59: =IF(OR(V59<>V58,U59<>U58,AND(V59<>V58,W59<>W58),AND(V59<>V58,W59<>W58,X59<>X58),AND(V59<>V58,W59<>W58,X59<>X58,Y59<>Y58),AND(V59<>V58,W59<>W58,X59<>X58,Y59<>Y58,Z59<>Z58),L59-L58>1),1,0) -> 0 | U59: A | V59: 5 | W59: 2 | X59: 9 | Y59: 0 | Z59: 0 | AA59: =IF(ROW()=5,1,IF(OR(AH59=1,P59>0,T59=1),1,IF(OR(AND(AH59=2,AI59=1),AND(AI59=2,AJ59=1),AND(AJ59=2,AK59=1),AND(AK59=2,AL59=1)),1,0))) -> 1 | AB59: =IF(L60>L59,1,0) -> 0 | AC59: =IF(ROW()=5,P59,IF(AND($P59>1,AC$4=$L59),$P59,IF(AND($U59=$U58,V59=V58),AC58,IF(AND($L59=AC$4,P59=1),P59,0)))) -> 1 | AD59: =IF(AC59>1,AC59,IF(AND($P59>1,AD$4=$L59),$P59,IF(AND($U59=$U58,W59=W58),AD58,IF(AND($L59=AD$4,P59=1),P59,0)))) -> 1 | AE59: =IF(AD59>1,AD59,IF(AND($P59>1,AE$4=$L59),$P59,IF(AND($U59=$U58,X59=X58),AE58,IF(AND($L59=AE$4,P59=1),P59,0)))) -> 1 | AF59: =IF(AE59>1,AE59,IF(AND($P59>1,AF$4=$L59),$P59,IF(AND($U59=$U58,Y59=Y58),AF58,IF(AND($L59=AF$4,P59=1),P59,0)))) -> 0 | AG59: =IF(AF59>1,AF59,IF(AND($P59>1,AG$4=$L59),$P59,IF(AND($U59=$U58,Z59=Z58),AG58,IF(AND($L59=AG$4,P59=1),P59,0)))) -> 0 | AH59: =IF(AND($P59=1,$L59=AH$4),2,IF(AND($L59<>AH$4,AH58=2),AH58,IF($L59<>AH$4,0,1))) -> 2 | AI59: =IF(OR(ROW()=5,$U58<>$U59),0,IF(AND($P59=1,$L59=AI$4),2,IF(AND($L59<>AI$4,AI58=2),AI58,IF($L59<>AI$4,0,1)))) -> 2 | AJ59: =IF(OR(ROW()=5,$U58<>$U59),0,IF(AND($P59=1,$L59=AJ$4),2,IF(AND($L59<>AJ$4,AJ58=2),AJ58,IF($L59<>AJ$4,0,1)))) -> 2 | AK59: =IF(OR(ROW()=5,$U58<>$U59),0,IF(AND($P59=1,$L59=AK$4),2,IF(AND($L59<>AK$4,AK58=2),AK58,IF($L59<>AK$4,0,1)))) -> 2 | AL59: =IF(OR(ROW()=5,$U58<>$U59),0,IF(AND($P59=1,$L59=AL$4),2,IF(AND($L59<>AL$4,AL58=2),AL58,IF($L59<>AL$4,0,1)))) -> 0
A60: 86 | B60: A.5.2.10 | C60: Do contracts with all subcontractors include termination/exit clause? | D60: Yes | G60: Third Party Risk Management | H60: Service Provider Agreements | I60: A.8 Subcontractor Contracting Process | J60: 15.1.1 Information Security Policy for Supplier Relationships|7.3.1 Termination or Change of Employment Responsibilities | L60: 3 | M60: 2 | P60: =IF($L60="","",IF($D60="Yes",1,IF($D60="No",2,IF($D60="N/A",3,0)))) -> 1 | Q60: =IF(AND(Drops!$D$45>1,OR(U60<>U59,AND(ROW()=5,U59=U60))),VLOOKUP(U60,Drops!$D$26:$E$44,2,FALSE),"") | R60: =IF(Q60<>"",ROW(),"") | S60: =OFFSET(AC60,,L60-1) -> 1 | T60: =IF(OR(V60<>V59,U60<>U59,AND(V60<>V59,W60<>W59),AND(V60<>V59,W60<>W59,X60<>X59),AND(V60<>V59,W60<>W59,X60<>X59,Y60<>Y59),AND(V60<>V59,W60<>W59,X60<>X59,Y60<>Y59,Z60<>Z59),L60-L59>1),1,0) -> 0 | U60: A | V60: 5 | W60: 2 | X60: 10 | Y60: 0 | Z60: 0 | AA60: =IF(ROW()=5,1,IF(OR(AH60=1,P60>0,T60=1),1,IF(OR(AND(AH60=2,AI60=1),AND(AI60=2,AJ60=1),AND(AJ60=2,AK60=1),AND(AK60=2,AL60=1)),1,0))) -> 1 | AB60: =IF(L61>L60,1,0) -> 0 | AC60: =IF(ROW()=5,P60,IF(AND($P60>1,AC$4=$L60),$P60,IF(AND($U60=$U59,V60=V59),AC59,IF(AND($L60=AC$4,P60=1),P60,0)))) -> 1 | AD60: =IF(AC60>1,AC60,IF(AND($P60>1,AD$4=$L60),$P60,IF(AND($U60=$U59,W60=W59),AD59,IF(AND($L60=AD$4,P60=1),P60,0)))) -> 1 | AE60: =IF(AD60>1,AD60,IF(AND($P60>1,AE$4=$L60),$P60,IF(AND($U60=$U59,X60=X59),AE59,IF(AND($L60=AE$4,P60=1),P60,0)))) -> 1 | AF60: =IF(AE60>1,AE60,IF(AND($P60>1,AF$4=$L60),$P60,IF(AND($U60=$U59,Y60=Y59),AF59,IF(AND($L60=AF$4,P60=1),P60,0)))) -> 0 | AG60: =IF(AF60>1,AF60,IF(AND($P60>1,AG$4=$L60),$P60,IF(AND($U60=$U59,Z60=Z59),AG59,IF(AND($L60=AG$4,P60=1),P60,0)))) -> 0 | AH60: =IF(AND($P60=1,$L60=AH$4),2,IF(AND($L60<>AH$4,AH59=2),AH59,IF($L60<>AH$4,0,1))) -> 2 | AI60: =IF(OR(ROW()=5,$U59<>$U60),0,IF(AND($P60=1,$L60=AI$4),2,IF(AND($L60<>AI$4,AI59=2),AI59,IF($L60<>AI$4,0,1)))) -> 2 | AJ60: =IF(OR(ROW()=5,$U59<>$U60),0,IF(AND($P60=1,$L60=AJ$4),2,IF(AND($L60<>AJ$4,AJ59=2),AJ59,IF($L60<>AJ$4,0,1)))) -> 2 | AK60: =IF(OR(ROW()=5,$U59<>$U60),0,IF(AND($P60=1,$L60=AK$4),2,IF(AND($L60<>AK$4,AK59=2),AK59,IF($L60<>AK$4,0,1)))) -> 2 | AL60: =IF(OR(ROW()=5,$U59<>$U60),0,IF(AND($P60=1,$L60=AL$4),2,IF(AND($L60<>AL$4,AL59=2),AL59,IF($L60<>AL$4,0,1)))) -> 0
A61: 4172 | B61: A.5.2.11 | C61: Do contracts with all subcontractors include breach of agreement terms? | D61: Yes | G61: Third Party Risk Management | H61: Service Provider Agreements | J61: 15.1.1 Information Security Policy for Supplier Relationships|15.1.2 Addressing Security Within Supplier Agreements | L61: 3 | M61: 2 | P61: =IF($L61="","",IF($D61="Yes",1,IF($D61="No",2,IF($D61="N/A",3,0)))) -> 1 | Q61: =IF(AND(Drops!$D$45>1,OR(U61<>U60,AND(ROW()=5,U60=U61))),VLOOKUP(U61,Drops!$D$26:$E$44,2,FALSE),"") | R61: =IF(Q61<>"",ROW(),"") | S61: =OFFSET(AC61,,L61-1) -> 1 | T61: =IF(OR(V61<>V60,U61<>U60,AND(V61<>V60,W61<>W60),AND(V61<>V60,W61<>W60,X61<>X60),AND(V61<>V60,W61<>W60,X61<>X60,Y61<>Y60),AND(V61<>V60,W61<>W60,X61<>X60,Y61<>Y60,Z61<>Z60),L61-L60>1),1,0) -> 0 | U61: A | V61: 5 | W61: 2 | X61: 11 | Y61: 0 | Z61: 0 | AA61: =IF(ROW()=5,1,IF(OR(AH61=1,P61>0,T61=1),1,IF(OR(AND(AH61=2,AI61=1),AND(AI61=2,AJ61=1),AND(AJ61=2,AK61=1),AND(AK61=2,AL61=1)),1,0))) -> 1 | AB61: =IF(L62>L61,1,0) -> 0 | AC61: =IF(ROW()=5,P61,IF(AND($P61>1,AC$4=$L61),$P61,IF(AND($U61=$U60,V61=V60),AC60,IF(AND($L61=AC$4,P61=1),P61,0)))) -> 1 | AD61: =IF(AC61>1,AC61,IF(AND($P61>1,AD$4=$L61),$P61,IF(AND($U61=$U60,W61=W60),AD60,IF(AND($L61=AD$4,P61=1),P61,0)))) -> 1 | AE61: =IF(AD61>1,AD61,IF(AND($P61>1,AE$4=$L61),$P61,IF(AND($U61=$U60,X61=X60),AE60,IF(AND($L61=AE$4,P61=1),P61,0)))) -> 1 | AF61: =IF(AE61>1,AE61,IF(AND($P61>1,AF$4=$L61),$P61,IF(AND($U61=$U60,Y61=Y60),AF60,IF(AND($L61=AF$4,P61=1),P61,0)))) -> 0 | AG61: =IF(AF61>1,AF61,IF(AND($P61>1,AG$4=$L61),$P61,IF(AND($U61=$U60,Z61=Z60),AG60,IF(AND($L61=AG$4,P61=1),P61,0)))) -> 0 | AH61: =IF(AND($P61=1,$L61=AH$4),2,IF(AND($L61<>AH$4,AH60=2),AH60,IF($L61<>AH$4,0,1))) -> 2 | AI61: =IF(OR(ROW()=5,$U60<>$U61),0,IF(AND($P61=1,$L61=AI$4),2,IF(AND($L61<>AI$4,AI60=2),AI60,IF($L61<>AI$4,0,1)))) -> 2 | AJ61: =IF(OR(ROW()=5,$U60<>$U61),0,IF(AND($P61=1,$L61=AJ$4),2,IF(AND($L61<>AJ$4,AJ60=2),AJ60,IF($L61<>AJ$4,0,1)))) -> 2 | AK61: =IF(OR(ROW()=5,$U60<>$U61),0,IF(AND($P61=1,$L61=AK$4),2,IF(AND($L61<>AK$4,AK60=2),AK60,IF($L61<>AK$4,0,1)))) -> 2 | AL61: =IF(OR(ROW()=5,$U60<>$U61),0,IF(AND($P61=1,$L61=AL$4),2,IF(AND($L61<>AL$4,AL60=2),AL60,IF($L61<>AL$4,0,1)))) -> 0
A62: 2524 | B62: A.5.2.13 | C62: Do contracts with all subcontractors include privacy and security control requirements for subcontractors? | D62: Yes | G62: Third Party Risk Management | H62: Service Provider Agreements | J62: 13.2.2 Agreements on Information Transfer|15.1.1 Information Security Policy for Supplier Relationships|15.1.2 Addressing Security Within Supplier Agreements|7.1.2 Terms and Condition of Employment|7.2.1 Management Responsibilities | L62: 3 | M62: 3 | P62: =IF($L62="","",IF($D62="Yes",1,IF($D62="No",2,IF($D62="N/A",3,0)))) -> 1 | Q62: =IF(AND(Drops!$D$45>1,OR(U62<>U61,AND(ROW()=5,U61=U62))),VLOOKUP(U62,Drops!$D$26:$E$44,2,FALSE),"") | R62: =IF(Q62<>"",ROW(),"") | S62: =OFFSET(AC62,,L62-1) -> 1 | T62: =IF(OR(V62<>V61,U62<>U61,AND(V62<>V61,W62<>W61),AND(V62<>V61,W62<>W61,X62<>X61),AND(V62<>V61,W62<>W61,X62<>X61,Y62<>Y61),AND(V62<>V61,W62<>W61,X62<>X61,Y62<>Y61,Z62<>Z61),L62-L61>1),1,0) -> 0 | U62: A | V62: 5 | W62: 2 | X62: 13 | Y62: 0 | Z62: 0 | AA62: =IF(ROW()=5,1,IF(OR(AH62=1,P62>0,T62=1),1,IF(OR(AND(AH62=2,AI62=1),AND(AI62=2,AJ62=1),AND(AJ62=2,AK62=1),AND(AK62=2,AL62=1)),1,0))) -> 1 | AB62: =IF(L63>L62,1,0) -> 0 | AC62: =IF(ROW()=5,P62,IF(AND($P62>1,AC$4=$L62),$P62,IF(AND($U62=$U61,V62=V61),AC61,IF(AND($L62=AC$4,P62=1),P62,0)))) -> 1 | AD62: =IF(AC62>1,AC62,IF(AND($P62>1,AD$4=$L62),$P62,IF(AND($U62=$U61,W62=W61),AD61,IF(AND($L62=AD$4,P62=1),P62,0)))) -> 1 | AE62: =IF(AD62>1,AD62,IF(AND($P62>1,AE$4=$L62),$P62,IF(AND($U62=$U61,X62=X61),AE61,IF(AND($L62=AE$4,P62=1),P62,0)))) -> 1 | AF62: =IF(AE62>1,AE62,IF(AND($P62>1,AF$4=$L62),$P62,IF(AND($U62=$U61,Y62=Y61),AF61,IF(AND($L62=AF$4,P62=1),P62,0)))) -> 0 | AG62: =IF(AF62>1,AF62,IF(AND($P62>1,AG$4=$L62),$P62,IF(AND($U62=$U61,Z62=Z61),AG61,IF(AND($L62=AG$4,P62=1),P62,0)))) -> 0 | AH62: =IF(AND($P62=1,$L62=AH$4),2,IF(AND($L62<>AH$4,AH61=2),AH61,IF($L62<>AH$4,0,1))) -> 2 | AI62: =IF(OR(ROW()=5,$U61<>$U62),0,IF(AND($P62=1,$L62=AI$4),2,IF(AND($L62<>AI$4,AI61=2),AI61,IF($L62<>AI$4,0,1)))) -> 2 | AJ62: =IF(OR(ROW()=5,$U61<>$U62),0,IF(AND($P62=1,$L62=AJ$4),2,IF(AND($L62<>AJ$4,AJ61=2),AJ61,IF($L62<>AJ$4,0,1)))) -> 2 | AK62: =IF(OR(ROW()=5,$U61<>$U62),0,IF(AND($P62=1,$L62=AK$4),2,IF(AND($L62<>AK$4,AK61=2),AK61,IF($L62<>AK$4,0,1)))) -> 2 | AL62: =IF(OR(ROW()=5,$U61<>$U62),0,IF(AND($P62=1,$L62=AL$4),2,IF(AND($L62<>AL$4,AL61=2),AL61,IF($L62<>AL$4,0,1)))) -> 0
A63: 4655 | B63: A.5.2.14 | C63: Do contracts with Subcontractors require negotiating the extension of contractual obligations to its subcontractors? | D63: Yes | G63: Third Party Risk Management | H63: Service Provider Agreements | J63: 15.1.1 Information Security Policy for Supplier Relationships | L63: 3 | M63: 3 | P63: =IF($L63="","",IF($D63="Yes",1,IF($D63="No",2,IF($D63="N/A",3,0)))) -> 1 | Q63: =IF(AND(Drops!$D$45>1,OR(U63<>U62,AND(ROW()=5,U62=U63))),VLOOKUP(U63,Drops!$D$26:$E$44,2,FALSE),"") | R63: =IF(Q63<>"",ROW(),"") | S63: =OFFSET(AC63,,L63-1) -> 1 | T63: =IF(OR(V63<>V62,U63<>U62,AND(V63<>V62,W63<>W62),AND(V63<>V62,W63<>W62,X63<>X62),AND(V63<>V62,W63<>W62,X63<>X62,Y63<>Y62),AND(V63<>V62,W63<>W62,X63<>X62,Y63<>Y62,Z63<>Z62),L63-L62>1),1,0) -> 0 | U63: A | V63: 5 | W63: 2 | X63: 14 | Y63: 0 | Z63: 0 | AA63: =IF(ROW()=5,1,IF(OR(AH63=1,P63>0,T63=1),1,IF(OR(AND(AH63=2,AI63=1),AND(AI63=2,AJ63=1),AND(AJ63=2,AK63=1),AND(AK63=2,AL63=1)),1,0))) -> 1 | AB63: =IF(L64>L63,1,0) -> 0 | AC63: =IF(ROW()=5,P63,IF(AND($P63>1,AC$4=$L63),$P63,IF(AND($U63=$U62,V63=V62),AC62,IF(AND($L63=AC$4,P63=1),P63,0)))) -> 1 | AD63: =IF(AC63>1,AC63,IF(AND($P63>1,AD$4=$L63),$P63,IF(AND($U63=$U62,W63=W62),AD62,IF(AND($L63=AD$4,P63=1),P63,0)))) -> 1 | AE63: =IF(AD63>1,AD63,IF(AND($P63>1,AE$4=$L63),$P63,IF(AND($U63=$U62,X63=X62),AE62,IF(AND($L63=AE$4,P63=1),P63,0)))) -> 1 | AF63: =IF(AE63>1,AE63,IF(AND($P63>1,AF$4=$L63),$P63,IF(AND($U63=$U62,Y63=Y62),AF62,IF(AND($L63=AF$4,P63=1),P63,0)))) -> 0 | AG63: =IF(AF63>1,AF63,IF(AND($P63>1,AG$4=$L63),$P63,IF(AND($U63=$U62,Z63=Z62),AG62,IF(AND($L63=AG$4,P63=1),P63,0)))) -> 0 | AH63: =IF(AND($P63=1,$L63=AH$4),2,IF(AND($L63<>AH$4,AH62=2),AH62,IF($L63<>AH$4,0,1))) -> 2 | AI63: =IF(OR(ROW()=5,$U62<>$U63),0,IF(AND($P63=1,$L63=AI$4),2,IF(AND($L63<>AI$4,AI62=2),AI62,IF($L63<>AI$4,0,1)))) -> 2 | AJ63: =IF(OR(ROW()=5,$U62<>$U63),0,IF(AND($P63=1,$L63=AJ$4),2,IF(AND($L63<>AJ$4,AJ62=2),AJ62,IF($L63<>AJ$4,0,1)))) -> 2 | AK63: =IF(OR(ROW()=5,$U62<>$U63),0,IF(AND($P63=1,$L63=AK$4),2,IF(AND($L63<>AK$4,AK62=2),AK62,IF($L63<>AK$4,0,1)))) -> 2 | AL63: =IF(OR(ROW()=5,$U62<>$U63),0,IF(AND($P63=1,$L63=AL$4),2,IF(AND($L63<>AL$4,AL62=2),AL62,IF($L63<>AL$4,0,1)))) -> 0
A64: 3887 | B64: A.5.3 | C64: Does the third party risk management program include an assigned individual or group responsible for capturing, maintaining, and tracking subcontractor Information Security, Privacy, or other issues? | D64: Yes | G64: Third Party Risk Management | H64: Issue Management | I64: A.5 Third Party Risk Management Program | L64: 2 | M64: 2 | P64: =IF($L64="","",IF($D64="Yes",1,IF($D64="No",2,IF($D64="N/A",3,0)))) -> 1 | Q64: =IF(AND(Drops!$D$45>1,OR(U64<>U63,AND(ROW()=5,U63=U64))),VLOOKUP(U64,Drops!$D$26:$E$44,2,FALSE),"") | R64: =IF(Q64<>"",ROW(),"") | S64: =OFFSET(AC64,,L64-1) -> 1 | T64: =IF(OR(V64<>V63,U64<>U63,AND(V64<>V63,W64<>W63),AND(V64<>V63,W64<>W63,X64<>X63),AND(V64<>V63,W64<>W63,X64<>X63,Y64<>Y63),AND(V64<>V63,W64<>W63,X64<>X63,Y64<>Y63,Z64<>Z63),L64-L63>1),1,0) -> 0 | U64: A | V64: 5 | W64: 3 | X64: 0 | Y64: 0 | Z64: 0 | AA64: =IF(ROW()=5,1,IF(OR(AH64=1,P64>0,T64=1),1,IF(OR(AND(AH64=2,AI64=1),AND(AI64=2,AJ64=1),AND(AJ64=2,AK64=1),AND(AK64=2,AL64=1)),1,0))) -> 1 | AB64: =IF(L65>L64,1,0) -> 1 | AC64: =IF(ROW()=5,P64,IF(AND($P64>1,AC$4=$L64),$P64,IF(AND($U64=$U63,V64=V63),AC63,IF(AND($L64=AC$4,P64=1),P64,0)))) -> 1 | AD64: =IF(AC64>1,AC64,IF(AND($P64>1,AD$4=$L64),$P64,IF(AND($U64=$U63,W64=W63),AD63,IF(AND($L64=AD$4,P64=1),P64,0)))) -> 1 | AE64: =IF(AD64>1,AD64,IF(AND($P64>1,AE$4=$L64),$P64,IF(AND($U64=$U63,X64=X63),AE63,IF(AND($L64=AE$4,P64=1),P64,0)))) -> 0 | AF64: =IF(AE64>1,AE64,IF(AND($P64>1,AF$4=$L64),$P64,IF(AND($U64=$U63,Y64=Y63),AF63,IF(AND($L64=AF$4,P64=1),P64,0)))) -> 0 | AG64: =IF(AF64>1,AF64,IF(AND($P64>1,AG$4=$L64),$P64,IF(AND($U64=$U63,Z64=Z63),AG63,IF(AND($L64=AG$4,P64=1),P64,0)))) -> 0 | AH64: =IF(AND($P64=1,$L64=AH$4),2,IF(AND($L64<>AH$4,AH63=2),AH63,IF($L64<>AH$4,0,1))) -> 2 | AI64: =IF(OR(ROW()=5,$U63<>$U64),0,IF(AND($P64=1,$L64=AI$4),2,IF(AND($L64<>AI$4,AI63=2),AI63,IF($L64<>AI$4,0,1)))) -> 2 | AJ64: =IF(OR(ROW()=5,$U63<>$U64),0,IF(AND($P64=1,$L64=AJ$4),2,IF(AND($L64<>AJ$4,AJ63=2),AJ63,IF($L64<>AJ$4,0,1)))) -> 2 | AK64: =IF(OR(ROW()=5,$U63<>$U64),0,IF(AND($P64=1,$L64=AK$4),2,IF(AND($L64<>AK$4,AK63=2),AK63,IF($L64<>AK$4,0,1)))) -> 2 | AL64: =IF(OR(ROW()=5,$U63<>$U64),0,IF(AND($P64=1,$L64=AL$4),2,IF(AND($L64<>AL$4,AL63=2),AL63,IF($L64<>AL$4,0,1)))) -> 0
A65: 3901 | B65: A.5.3.4.3 | C65: Does remediation reporting include a process to identify and log subcontractor information security, privacy and/or data breach issues? | D65: Yes | G65: Third Party Risk Management | H65: Issue Management | I65: A.11 Information Security Review Process - Tracking and Risk Rating Subcontractor Issues | J65: 12.4.1 Event Logging | L65: 4 | M65: 2 | P65: =IF($L65="","",IF($D65="Yes",1,IF($D65="No",2,IF($D65="N/A",3,0)))) -> 1 | Q65: =IF(AND(Drops!$D$45>1,OR(U65<>U64,AND(ROW()=5,U64=U65))),VLOOKUP(U65,Drops!$D$26:$E$44,2,FALSE),"") | R65: =IF(Q65<>"",ROW(),"") | S65: =OFFSET(AC65,,L65-1) -> 1 | T65: =IF(OR(V65<>V64,U65<>U64,AND(V65<>V64,W65<>W64),AND(V65<>V64,W65<>W64,X65<>X64),AND(V65<>V64,W65<>W64,X65<>X64,Y65<>Y64),AND(V65<>V64,W65<>W64,X65<>X64,Y65<>Y64,Z65<>Z64),L65-L64>1),1,0) -> 1 | U65: A | V65: 5 | W65: 3 | X65: 4 | Y65: 3 | Z65: 0 | AA65: =IF(ROW()=5,1,IF(OR(AH65=1,P65>0,T65=1),1,IF(OR(AND(AH65=2,AI65=1),AND(AI65=2,AJ65=1),AND(AJ65=2,AK65=1),AND(AK65=2,AL65=1)),1,0))) -> 1 | AB65: =IF(L66>L65,1,0) -> 0 | AC65: =IF(ROW()=5,P65,IF(AND($P65>1,AC$4=$L65),$P65,IF(AND($U65=$U64,V65=V64),AC64,IF(AND($L65=AC$4,P65=1),P65,0)))) -> 1 | AD65: =IF(AC65>1,AC65,IF(AND($P65>1,AD$4=$L65),$P65,IF(AND($U65=$U64,W65=W64),AD64,IF(AND($L65=AD$4,P65=1),P65,0)))) -> 1 | AE65: =IF(AD65>1,AD65,IF(AND($P65>1,AE$4=$L65),$P65,IF(AND($U65=$U64,X65=X64),AE64,IF(AND($L65=AE$4,P65=1),P65,0)))) -> 0 | AF65: =IF(AE65>1,AE65,IF(AND($P65>1,AF$4=$L65),$P65,IF(AND($U65=$U64,Y65=Y64),AF64,IF(AND($L65=AF$4,P65=1),P65,0)))) -> 1 | AG65: =IF(AF65>1,AF65,IF(AND($P65>1,AG$4=$L65),$P65,IF(AND($U65=$U64,Z65=Z64),AG64,IF(AND($L65=AG$4,P65=1),P65,0)))) -> 0 | AH65: =IF(AND($P65=1,$L65=AH$4),2,IF(AND($L65<>AH$4,AH64=2),AH64,IF($L65<>AH$4,0,1))) -> 2 | AI65: =IF(OR(ROW()=5,$U64<>$U65),0,IF(AND($P65=1,$L65=AI$4),2,IF(AND($L65<>AI$4,AI64=2),AI64,IF($L65<>AI$4,0,1)))) -> 2 | AJ65: =IF(OR(ROW()=5,$U64<>$U65),0,IF(AND($P65=1,$L65=AJ$4),2,IF(AND($L65<>AJ$4,AJ64=2),AJ64,IF($L65<>AJ$4,0,1)))) -> 2 | AK65: =IF(OR(ROW()=5,$U64<>$U65),0,IF(AND($P65=1,$L65=AK$4),2,IF(AND($L65<>AK$4,AK64=2),AK64,IF($L65<>AK$4,0,1)))) -> 2 | AL65: =IF(OR(ROW()=5,$U64<>$U65),0,IF(AND($P65=1,$L65=AL$4),2,IF(AND($L65<>AL$4,AL64=2),AL64,IF($L65<>AL$4,0,1)))) -> 0
A66: 3199 | B66: B.1 | C66: Is there a set of information security policies that have been approved by management, published and communicated to constituents? | D66: Yes | E66: Seismic's Information Security team manage over 15 different information security and privacy policies related to all aspects of business, to include but not limited to, Human Resource Management, Acceptable Use, Secure Technology Standards, Access Control Standards, Information Security Policy, Privacy Protection, and more. Seismic reviews policies at least annually or upon significant change to business structure. Policies are approved by a member of executive management before release. Policies and procedures are communicated through Seismic's intranet, and are acknowledged employees and contractors at least annually. | G66: Information Security Policy Management | H66: Information Security Policy Management | I66: B.1 Information Security Policy Maintenance | J66: 4.3 Scope of Information Security Management Systems|5.1 Leadership and Commitment|5.1.1 Policies for Information Security|5.2 Policy|6.2 Information Security Objectives and Planning to Achieve Them|7.4 Communication|7.5.1 General|8.1 Operational Planning and Control | L66: 1 | M66: 2 | P66: =IF($L66="","",IF($D66="Yes",1,IF($D66="No",2,IF($D66="N/A",3,0)))) -> 1 | Q66: =IF(AND(Drops!$D$45>1,OR(U66<>U65,AND(ROW()=5,U65=U66))),VLOOKUP(U66,Drops!$D$26:$E$44,2,FALSE),"") -> B. Security Policy | R66: =IF(Q66<>"",ROW(),"") -> 66 | S66: =OFFSET(AC66,,L66-1) -> 1 | T66: =IF(OR(V66<>V65,U66<>U65,AND(V66<>V65,W66<>W65),AND(V66<>V65,W66<>W65,X66<>X65),AND(V66<>V65,W66<>W65,X66<>X65,Y66<>Y65),AND(V66<>V65,W66<>W65,X66<>X65,Y66<>Y65,Z66<>Z65),L66-L65>1),1,0) -> 1 | U66: B | V66: 1 | W66: 0 | X66: 0 | Y66: 0 | Z66: 0 | AA66: =IF(ROW()=5,1,IF(OR(AH66=1,P66>0,T66=1),1,IF(OR(AND(AH66=2,AI66=1),AND(AI66=2,AJ66=1),AND(AJ66=2,AK66=1),AND(AK66=2,AL66=1)),1,0))) -> 1 | AB66: =IF(L67>L66,1,0) -> 1 | AC66: =IF(ROW()=5,P66,IF(AND($P66>1,AC$4=$L66),$P66,IF(AND($U66=$U65,V66=V65),AC65,IF(AND($L66=AC$4,P66=1),P66,0)))) -> 1 | AD66: =IF(AC66>1,AC66,IF(AND($P66>1,AD$4=$L66),$P66,IF(AND($U66=$U65,W66=W65),AD65,IF(AND($L66=AD$4,P66=1),P66,0)))) -> 0 | AE66: =IF(AD66>1,AD66,IF(AND($P66>1,AE$4=$L66),$P66,IF(AND($U66=$U65,X66=X65),AE65,IF(AND($L66=AE$4,P66=1),P66,0)))) -> 0 | AF66: =IF(AE66>1,AE66,IF(AND($P66>1,AF$4=$L66),$P66,IF(AND($U66=$U65,Y66=Y65),AF65,IF(AND($L66=AF$4,P66=1),P66,0)))) -> 0 | AG66: =IF(AF66>1,AF66,IF(AND($P66>1,AG$4=$L66),$P66,IF(AND($U66=$U65,Z66=Z65),AG65,IF(AND($L66=AG$4,P66=1),P66,0)))) -> 0 | AH66: =IF(AND($P66=1,$L66=AH$4),2,IF(AND($L66<>AH$4,AH65=2),AH65,IF($L66<>AH$4,0,1))) -> 2 | AI66: =IF(OR(ROW()=5,$U65<>$U66),0,IF(AND($P66=1,$L66=AI$4),2,IF(AND($L66<>AI$4,AI65=2),AI65,IF($L66<>AI$4,0,1)))) -> 0 | AJ66: =IF(OR(ROW()=5,$U65<>$U66),0,IF(AND($P66=1,$L66=AJ$4),2,IF(AND($L66<>AJ$4,AJ65=2),AJ65,IF($L66<>AJ$4,0,1)))) -> 0 | AK66: =IF(OR(ROW()=5,$U65<>$U66),0,IF(AND($P66=1,$L66=AK$4),2,IF(AND($L66<>AK$4,AK65=2),AK65,IF($L66<>AK$4,0,1)))) -> 0 | AL66: =IF(OR(ROW()=5,$U65<>$U66),0,IF(AND($P66=1,$L66=AL$4),2,IF(AND($L66<>AL$4,AL65=2),AL65,IF($L66<>AL$4,0,1)))) -> 0
A67: 2482 | B67: B.1.1 | C67: Are policies and standards based on industry accepted standards and practices? | D67: Yes | E67: Policies and Standards are based on industry accepted standards such as ISO 27002 | G67: Information Security Policy Management | H67: Information Security Policy Management | J67: 6.2 Information Security Objectives and Planning to Achieve Them | L67: 2 | M67: 3 | P67: =IF($L67="","",IF($D67="Yes",1,IF($D67="No",2,IF($D67="N/A",3,0)))) -> 1 | Q67: =IF(AND(Drops!$D$45>1,OR(U67<>U66,AND(ROW()=5,U66=U67))),VLOOKUP(U67,Drops!$D$26:$E$44,2,FALSE),"") | R67: =IF(Q67<>"",ROW(),"") | S67: =OFFSET(AC67,,L67-1) -> 1 | T67: =IF(OR(V67<>V66,U67<>U66,AND(V67<>V66,W67<>W66),AND(V67<>V66,W67<>W66,X67<>X66),AND(V67<>V66,W67<>W66,X67<>X66,Y67<>Y66),AND(V67<>V66,W67<>W66,X67<>X66,Y67<>Y66,Z67<>Z66),L67-L66>1),1,0) -> 0 | U67: B | V67: 1 | W67: 1 | X67: 0 | Y67: 0 | Z67: 0 | AA67: =IF(ROW()=5,1,IF(OR(AH67=1,P67>0,T67=1),1,IF(OR(AND(AH67=2,AI67=1),AND(AI67=2,AJ67=1),AND(AJ67=2,AK67=1),AND(AK67=2,AL67=1)),1,0))) -> 1 | AB67: =IF(L68>L67,1,0) -> 0 | AC67: =IF(ROW()=5,P67,IF(AND($P67>1,AC$4=$L67),$P67,IF(AND($U67=$U66,V67=V66),AC66,IF(AND($L67=AC$4,P67=1),P67,0)))) -> 1 | AD67: =IF(AC67>1,AC67,IF(AND($P67>1,AD$4=$L67),$P67,IF(AND($U67=$U66,W67=W66),AD66,IF(AND($L67=AD$4,P67=1),P67,0)))) -> 1 | AE67: =IF(AD67>1,AD67,IF(AND($P67>1,AE$4=$L67),$P67,IF(AND($U67=$U66,X67=X66),AE66,IF(AND($L67=AE$4,P67=1),P67,0)))) -> 0 | AF67: =IF(AE67>1,AE67,IF(AND($P67>1,AF$4=$L67),$P67,IF(AND($U67=$U66,Y67=Y66),AF66,IF(AND($L67=AF$4,P67=1),P67,0)))) -> 0 | AG67: =IF(AF67>1,AF67,IF(AND($P67>1,AG$4=$L67),$P67,IF(AND($U67=$U66,Z67=Z66),AG66,IF(AND($L67=AG$4,P67=1),P67,0)))) -> 0 | AH67: =IF(AND($P67=1,$L67=AH$4),2,IF(AND($L67<>AH$4,AH66=2),AH66,IF($L67<>AH$4,0,1))) -> 2 | AI67: =IF(OR(ROW()=5,$U66<>$U67),0,IF(AND($P67=1,$L67=AI$4),2,IF(AND($L67<>AI$4,AI66=2),AI66,IF($L67<>AI$4,0,1)))) -> 2 | AJ67: =IF(OR(ROW()=5,$U66<>$U67),0,IF(AND($P67=1,$L67=AJ$4),2,IF(AND($L67<>AJ$4,AJ66=2),AJ66,IF($L67<>AJ$4,0,1)))) -> 0 | AK67: =IF(OR(ROW()=5,$U66<>$U67),0,IF(AND($P67=1,$L67=AK$4),2,IF(AND($L67<>AK$4,AK66=2),AK66,IF($L67<>AK$4,0,1)))) -> 0 | AL67: =IF(OR(ROW()=5,$U66<>$U67),0,IF(AND($P67=1,$L67=AL$4),2,IF(AND($L67<>AL$4,AL66=2),AL66,IF($L67<>AL$4,0,1)))) -> 0
A68: 4414 | B68: B.1.2 | C68: Is there a management-approved process for handling deviations and exceptions? | D68: Yes | G68: Information Security Policy Management | H68: Information Security Policy Management | I68: B.1 Information Security Policy Maintenance | J68: 6.2 Information Security Objectives and Planning to Achieve Them | L68: 2 | M68: 3 | P68: =IF($L68="","",IF($D68="Yes",1,IF($D68="No",2,IF($D68="N/A",3,0)))) -> 1 | Q68: =IF(AND(Drops!$D$45>1,OR(U68<>U67,AND(ROW()=5,U67=U68))),VLOOKUP(U68,Drops!$D$26:$E$44,2,FALSE),"") | R68: =IF(Q68<>"",ROW(),"") | S68: =OFFSET(AC68,,L68-1) -> 1 | T68: =IF(OR(V68<>V67,U68<>U67,AND(V68<>V67,W68<>W67),AND(V68<>V67,W68<>W67,X68<>X67),AND(V68<>V67,W68<>W67,X68<>X67,Y68<>Y67),AND(V68<>V67,W68<>W67,X68<>X67,Y68<>Y67,Z68<>Z67),L68-L67>1),1,0) -> 0 | U68: B | V68: 1 | W68: 2 | X68: 0 | Y68: 0 | Z68: 0 | AA68: =IF(ROW()=5,1,IF(OR(AH68=1,P68>0,T68=1),1,IF(OR(AND(AH68=2,AI68=1),AND(AI68=2,AJ68=1),AND(AJ68=2,AK68=1),AND(AK68=2,AL68=1)),1,0))) -> 1 | AB68: =IF(L69>L68,1,0) -> 0 | AC68: =IF(ROW()=5,P68,IF(AND($P68>1,AC$4=$L68),$P68,IF(AND($U68=$U67,V68=V67),AC67,IF(AND($L68=AC$4,P68=1),P68,0)))) -> 1 | AD68: =IF(AC68>1,AC68,IF(AND($P68>1,AD$4=$L68),$P68,IF(AND($U68=$U67,W68=W67),AD67,IF(AND($L68=AD$4,P68=1),P68,0)))) -> 1 | AE68: =IF(AD68>1,AD68,IF(AND($P68>1,AE$4=$L68),$P68,IF(AND($U68=$U67,X68=X67),AE67,IF(AND($L68=AE$4,P68=1),P68,0)))) -> 0 | AF68: =IF(AE68>1,AE68,IF(AND($P68>1,AF$4=$L68),$P68,IF(AND($U68=$U67,Y68=Y67),AF67,IF(AND($L68=AF$4,P68=1),P68,0)))) -> 0 | AG68: =IF(AF68>1,AF68,IF(AND($P68>1,AG$4=$L68),$P68,IF(AND($U68=$U67,Z68=Z67),AG67,IF(AND($L68=AG$4,P68=1),P68,0)))) -> 0 | AH68: =IF(AND($P68=1,$L68=AH$4),2,IF(AND($L68<>AH$4,AH67=2),AH67,IF($L68<>AH$4,0,1))) -> 2 | AI68: =IF(OR(ROW()=5,$U67<>$U68),0,IF(AND($P68=1,$L68=AI$4),2,IF(AND($L68<>AI$4,AI67=2),AI67,IF($L68<>AI$4,0,1)))) -> 2 | AJ68: =IF(OR(ROW()=5,$U67<>$U68),0,IF(AND($P68=1,$L68=AJ$4),2,IF(AND($L68<>AJ$4,AJ67=2),AJ67,IF($L68<>AJ$4,0,1)))) -> 0 | AK68: =IF(OR(ROW()=5,$U67<>$U68),0,IF(AND($P68=1,$L68=AK$4),2,IF(AND($L68<>AK$4,AK67=2),AK67,IF($L68<>AK$4,0,1)))) -> 0 | AL68: =IF(OR(ROW()=5,$U67<>$U68),0,IF(AND($P68=1,$L68=AL$4),2,IF(AND($L68<>AL$4,AL67=2),AL67,IF($L68<>AL$4,0,1)))) -> 0
A69: 4415 | B69: B.1.3 | C69: Do the information security policies set requirements based on business strategy, regulations, legislation (Including privacy and civil liberties obligations) and cybersecurity threat environment? | D69: Yes | G69: Information Security Policy Management | H69: Information Security Policy Management | J69: 4.3 Scope of Information Security Management Systems|6.2 Information Security Objectives and Planning to Achieve Them|8.1 Operational Planning and Control | L69: 2 | M69: 3 | P69: =IF($L69="","",IF($D69="Yes",1,IF($D69="No",2,IF($D69="N/A",3,0)))) -> 1 | Q69: =IF(AND(Drops!$D$45>1,OR(U69<>U68,AND(ROW()=5,U68=U69))),VLOOKUP(U69,Drops!$D$26:$E$44,2,FALSE),"") | R69: =IF(Q69<>"",ROW(),"") | S69: =OFFSET(AC69,,L69-1) -> 1 | T69: =IF(OR(V69<>V68,U69<>U68,AND(V69<>V68,W69<>W68),AND(V69<>V68,W69<>W68,X69<>X68),AND(V69<>V68,W69<>W68,X69<>X68,Y69<>Y68),AND(V69<>V68,W69<>W68,X69<>X68,Y69<>Y68,Z69<>Z68),L69-L68>1),1,0) -> 0 | U69: B | V69: 1 | W69: 3 | X69: 0 | Y69: 0 | Z69: 0 | AA69: =IF(ROW()=5,1,IF(OR(AH69=1,P69>0,T69=1),1,IF(OR(AND(AH69=2,AI69=1),AND(AI69=2,AJ69=1),AND(AJ69=2,AK69=1),AND(AK69=2,AL69=1)),1,0))) -> 1 | AB69: =IF(L70>L69,1,0) -> 0 | AC69: =IF(ROW()=5,P69,IF(AND($P69>1,AC$4=$L69),$P69,IF(AND($U69=$U68,V69=V68),AC68,IF(AND($L69=AC$4,P69=1),P69,0)))) -> 1 | AD69: =IF(AC69>1,AC69,IF(AND($P69>1,AD$4=$L69),$P69,IF(AND($U69=$U68,W69=W68),AD68,IF(AND($L69=AD$4,P69=1),P69,0)))) -> 1 | AE69: =IF(AD69>1,AD69,IF(AND($P69>1,AE$4=$L69),$P69,IF(AND($U69=$U68,X69=X68),AE68,IF(AND($L69=AE$4,P69=1),P69,0)))) -> 0 | AF69: =IF(AE69>1,AE69,IF(AND($P69>1,AF$4=$L69),$P69,IF(AND($U69=$U68,Y69=Y68),AF68,IF(AND($L69=AF$4,P69=1),P69,0)))) -> 0 | AG69: =IF(AF69>1,AF69,IF(AND($P69>1,AG$4=$L69),$P69,IF(AND($U69=$U68,Z69=Z68),AG68,IF(AND($L69=AG$4,P69=1),P69,0)))) -> 0 | AH69: =IF(AND($P69=1,$L69=AH$4),2,IF(AND($L69<>AH$4,AH68=2),AH68,IF($L69<>AH$4,0,1))) -> 2 | AI69: =IF(OR(ROW()=5,$U68<>$U69),0,IF(AND($P69=1,$L69=AI$4),2,IF(AND($L69<>AI$4,AI68=2),AI68,IF($L69<>AI$4,0,1)))) -> 2 | AJ69: =IF(OR(ROW()=5,$U68<>$U69),0,IF(AND($P69=1,$L69=AJ$4),2,IF(AND($L69<>AJ$4,AJ68=2),AJ68,IF($L69<>AJ$4,0,1)))) -> 0 | AK69: =IF(OR(ROW()=5,$U68<>$U69),0,IF(AND($P69=1,$L69=AK$4),2,IF(AND($L69<>AK$4,AK68=2),AK68,IF($L69<>AK$4,0,1)))) -> 0 | AL69: =IF(OR(ROW()=5,$U68<>$U69),0,IF(AND($P69=1,$L69=AL$4),2,IF(AND($L69<>AL$4,AL68=2),AL68,IF($L69<>AL$4,0,1)))) -> 0
A70: 4173 | B70: B.1.5 | C70: Have all policies been assigned to an owner responsible for review and approve periodically? | D70: Yes | E70: All policies have been assigned for review and approved by the Director of Information Security. | G70: Information Security Policy Management | H70: Information Security Policy Management | J70: 10.1 Nonconformity and Corrective Action Plan|4.4 Information Security Management System|6.2 Information Security Objectives and Planning to Achieve Them|9.1 Monitoring, Measurement, Analysis, and Evaluation|9.3 Management Review | L70: 2 | M70: 2 | P70: =IF($L70="","",IF($D70="Yes",1,IF($D70="No",2,IF($D70="N/A",3,0)))) -> 1 | Q70: =IF(AND(Drops!$D$45>1,OR(U70<>U69,AND(ROW()=5,U69=U70))),VLOOKUP(U70,Drops!$D$26:$E$44,2,FALSE),"") | R70: =IF(Q70<>"",ROW(),"") | S70: =OFFSET(AC70,,L70-1) -> 1 | T70: =IF(OR(V70<>V69,U70<>U69,AND(V70<>V69,W70<>W69),AND(V70<>V69,W70<>W69,X70<>X69),AND(V70<>V69,W70<>W69,X70<>X69,Y70<>Y69),AND(V70<>V69,W70<>W69,X70<>X69,Y70<>Y69,Z70<>Z69),L70-L69>1),1,0) -> 0 | U70: B | V70: 1 | W70: 5 | X70: 0 | Y70: 0 | Z70: 0 | AA70: =IF(ROW()=5,1,IF(OR(AH70=1,P70>0,T70=1),1,IF(OR(AND(AH70=2,AI70=1),AND(AI70=2,AJ70=1),AND(AJ70=2,AK70=1),AND(AK70=2,AL70=1)),1,0))) -> 1 | AB70: =IF(L71>L70,1,0) -> 1 | AC70: =IF(ROW()=5,P70,IF(AND($P70>1,AC$4=$L70),$P70,IF(AND($U70=$U69,V70=V69),AC69,IF(AND($L70=AC$4,P70=1),P70,0)))) -> 1 | AD70: =IF(AC70>1,AC70,IF(AND($P70>1,AD$4=$L70),$P70,IF(AND($U70=$U69,W70=W69),AD69,IF(AND($L70=AD$4,P70=1),P70,0)))) -> 1 | AE70: =IF(AD70>1,AD70,IF(AND($P70>1,AE$4=$L70),$P70,IF(AND($U70=$U69,X70=X69),AE69,IF(AND($L70=AE$4,P70=1),P70,0)))) -> 0 | AF70: =IF(AE70>1,AE70,IF(AND($P70>1,AF$4=$L70),$P70,IF(AND($U70=$U69,Y70=Y69),AF69,IF(AND($L70=AF$4,P70=1),P70,0)))) -> 0 | AG70: =IF(AF70>1,AF70,IF(AND($P70>1,AG$4=$L70),$P70,IF(AND($U70=$U69,Z70=Z69),AG69,IF(AND($L70=AG$4,P70=1),P70,0)))) -> 0 | AH70: =IF(AND($P70=1,$L70=AH$4),2,IF(AND($L70<>AH$4,AH69=2),AH69,IF($L70<>AH$4,0,1))) -> 2 | AI70: =IF(OR(ROW()=5,$U69<>$U70),0,IF(AND($P70=1,$L70=AI$4),2,IF(AND($L70<>AI$4,AI69=2),AI69,IF($L70<>AI$4,0,1)))) -> 2 | AJ70: =IF(OR(ROW()=5,$U69<>$U70),0,IF(AND($P70=1,$L70=AJ$4),2,IF(AND($L70<>AJ$4,AJ69=2),AJ69,IF($L70<>AJ$4,0,1)))) -> 0 | AK70: =IF(OR(ROW()=5,$U69<>$U70),0,IF(AND($P70=1,$L70=AK$4),2,IF(AND($L70<>AK$4,AK69=2),AK69,IF($L70<>AK$4,0,1)))) -> 0 | AL70: =IF(OR(ROW()=5,$U69<>$U70),0,IF(AND($P70=1,$L70=AL$4),2,IF(AND($L70<>AL$4,AL69=2),AL69,IF($L70<>AL$4,0,1)))) -> 0
A71: 4174 | B71: B.1.5.1 | C71: Do owners review and update policies if significant changes occur in legal, business, organizational, or technical conditions? | D71: Yes | G71: Information Security Policy Management | H71: Information Security Policy Management | J71: 10.1 Nonconformity and Corrective Action Plan|10.2 Continual Improvement|4.4 Information Security Management System|5.1.2 Review of the Policies for Information Security|9.1 Monitoring, Measurement, Analysis, and Evaluation|9.3 Management Review | L71: 3 | M71: 3 | P71: =IF($L71="","",IF($D71="Yes",1,IF($D71="No",2,IF($D71="N/A",3,0)))) -> 1 | Q71: =IF(AND(Drops!$D$45>1,OR(U71<>U70,AND(ROW()=5,U70=U71))),VLOOKUP(U71,Drops!$D$26:$E$44,2,FALSE),"") | R71: =IF(Q71<>"",ROW(),"") | S71: =OFFSET(AC71,,L71-1) -> 1 | T71: =IF(OR(V71<>V70,U71<>U70,AND(V71<>V70,W71<>W70),AND(V71<>V70,W71<>W70,X71<>X70),AND(V71<>V70,W71<>W70,X71<>X70,Y71<>Y70),AND(V71<>V70,W71<>W70,X71<>X70,Y71<>Y70,Z71<>Z70),L71-L70>1),1,0) -> 0 | U71: B | V71: 1 | W71: 5 | X71: 1 | Y71: 0 | Z71: 0 | AA71: =IF(ROW()=5,1,IF(OR(AH71=1,P71>0,T71=1),1,IF(OR(AND(AH71=2,AI71=1),AND(AI71=2,AJ71=1),AND(AJ71=2,AK71=1),AND(AK71=2,AL71=1)),1,0))) -> 1 | AB71: =IF(L72>L71,1,0) -> 0 | AC71: =IF(ROW()=5,P71,IF(AND($P71>1,AC$4=$L71),$P71,IF(AND($U71=$U70,V71=V70),AC70,IF(AND($L71=AC$4,P71=1),P71,0)))) -> 1 | AD71: =IF(AC71>1,AC71,IF(AND($P71>1,AD$4=$L71),$P71,IF(AND($U71=$U70,W71=W70),AD70,IF(AND($L71=AD$4,P71=1),P71,0)))) -> 1 | AE71: =IF(AD71>1,AD71,IF(AND($P71>1,AE$4=$L71),$P71,IF(AND($U71=$U70,X71=X70),AE70,IF(AND($L71=AE$4,P71=1),P71,0)))) -> 1 | AF71: =IF(AE71>1,AE71,IF(AND($P71>1,AF$4=$L71),$P71,IF(AND($U71=$U70,Y71=Y70),AF70,IF(AND($L71=AF$4,P71=1),P71,0)))) -> 0 | AG71: =IF(AF71>1,AF71,IF(AND($P71>1,AG$4=$L71),$P71,IF(AND($U71=$U70,Z71=Z70),AG70,IF(AND($L71=AG$4,P71=1),P71,0)))) -> 0 | AH71: =IF(AND($P71=1,$L71=AH$4),2,IF(AND($L71<>AH$4,AH70=2),AH70,IF($L71<>AH$4,0,1))) -> 2 | AI71: =IF(OR(ROW()=5,$U70<>$U71),0,IF(AND($P71=1,$L71=AI$4),2,IF(AND($L71<>AI$4,AI70=2),AI70,IF($L71<>AI$4,0,1)))) -> 2 | AJ71: =IF(OR(ROW()=5,$U70<>$U71),0,IF(AND($P71=1,$L71=AJ$4),2,IF(AND($L71<>AJ$4,AJ70=2),AJ70,IF($L71<>AJ$4,0,1)))) -> 2 | AK71: =IF(OR(ROW()=5,$U70<>$U71),0,IF(AND($P71=1,$L71=AK$4),2,IF(AND($L71<>AK$4,AK70=2),AK70,IF($L71<>AK$4,0,1)))) -> 0 | AL71: =IF(OR(ROW()=5,$U70<>$U71),0,IF(AND($P71=1,$L71=AL$4),2,IF(AND($L71<>AL$4,AL70=2),AL70,IF($L71<>AL$4,0,1)))) -> 0
A72: 2471 | B72: B.1.6 | C72: Have all information security policies and standards been reviewed in the last 12 months? | D72: Yes | G72: Information Security Policy Management | H72: Information Security Policy Management | I72: B.2 Information Security Standards | J72: 10.2 Continual Improvement|18.2.1 Independent Review of Information Security|4.4 Information Security Management System|5.1.2 Review of the Policies for Information Security|9.1 Monitoring, Measurement, Analysis, and Evaluation|9.3 Management Review | L72: 2 | M72: 2 | P72: =IF($L72="","",IF($D72="Yes",1,IF($D72="No",2,IF($D72="N/A",3,0)))) -> 1 | Q72: =IF(AND(Drops!$D$45>1,OR(U72<>U71,AND(ROW()=5,U71=U72))),VLOOKUP(U72,Drops!$D$26:$E$44,2,FALSE),"") | R72: =IF(Q72<>"",ROW(),"") | S72: =OFFSET(AC72,,L72-1) -> 1 | T72: =IF(OR(V72<>V71,U72<>U71,AND(V72<>V71,W72<>W71),AND(V72<>V71,W72<>W71,X72<>X71),AND(V72<>V71,W72<>W71,X72<>X71,Y72<>Y71),AND(V72<>V71,W72<>W71,X72<>X71,Y72<>Y71,Z72<>Z71),L72-L71>1),1,0) -> 0 | U72: B | V72: 1 | W72: 6 | X72: 0 | Y72: 0 | Z72: 0 | AA72: =IF(ROW()=5,1,IF(OR(AH72=1,P72>0,T72=1),1,IF(OR(AND(AH72=2,AI72=1),AND(AI72=2,AJ72=1),AND(AJ72=2,AK72=1),AND(AK72=2,AL72=1)),1,0))) -> 1 | AB72: =IF(L73>L72,1,0) -> 0 | AC72: =IF(ROW()=5,P72,IF(AND($P72>1,AC$4=$L72),$P72,IF(AND($U72=$U71,V72=V71),AC71,IF(AND($L72=AC$4,P72=1),P72,0)))) -> 1 | AD72: =IF(AC72>1,AC72,IF(AND($P72>1,AD$4=$L72),$P72,IF(AND($U72=$U71,W72=W71),AD71,IF(AND($L72=AD$4,P72=1),P72,0)))) -> 1 | AE72: =IF(AD72>1,AD72,IF(AND($P72>1,AE$4=$L72),$P72,IF(AND($U72=$U71,X72=X71),AE71,IF(AND($L72=AE$4,P72=1),P72,0)))) -> 0 | AF72: =IF(AE72>1,AE72,IF(AND($P72>1,AF$4=$L72),$P72,IF(AND($U72=$U71,Y72=Y71),AF71,IF(AND($L72=AF$4,P72=1),P72,0)))) -> 0 | AG72: =IF(AF72>1,AF72,IF(AND($P72>1,AG$4=$L72),$P72,IF(AND($U72=$U71,Z72=Z71),AG71,IF(AND($L72=AG$4,P72=1),P72,0)))) -> 0 | AH72: =IF(AND($P72=1,$L72=AH$4),2,IF(AND($L72<>AH$4,AH71=2),AH71,IF($L72<>AH$4,0,1))) -> 2 | AI72: =IF(OR(ROW()=5,$U71<>$U72),0,IF(AND($P72=1,$L72=AI$4),2,IF(AND($L72<>AI$4,AI71=2),AI71,IF($L72<>AI$4,0,1)))) -> 2 | AJ72: =IF(OR(ROW()=5,$U71<>$U72),0,IF(AND($P72=1,$L72=AJ$4),2,IF(AND($L72<>AJ$4,AJ71=2),AJ71,IF($L72<>AJ$4,0,1)))) -> 2 | AK72: =IF(OR(ROW()=5,$U71<>$U72),0,IF(AND($P72=1,$L72=AK$4),2,IF(AND($L72<>AK$4,AK71=2),AK71,IF($L72<>AK$4,0,1)))) -> 0 | AL72: =IF(OR(ROW()=5,$U71<>$U72),0,IF(AND($P72=1,$L72=AL$4),2,IF(AND($L72<>AL$4,AL71=2),AL71,IF($L72<>AL$4,0,1)))) -> 0
A73: 4417 | B73: C.1 | C73: Are responsibilities for asset protection and for carrying out specific information security processes clearly identified and communicated to the relevant parties? | D73: Yes | E73: Seismic has a written Information Security Policy all employees must acknowledge on an annual basis. | G73: Security Organization | H73: Organizational Information Security Responsibilities | I73: C.1 Security Organization Roles and Responsibilities | J73: 5.1 Leadership and Commitment|5.3 Organizational Roles, Responsibilities, and Authorities|6.1.1 Information Security Roles and Responsibilities | L73: 1 | M73: 2 | P73: =IF($L73="","",IF($D73="Yes",1,IF($D73="No",2,IF($D73="N/A",3,0)))) -> 1 | Q73: =IF(AND(Drops!$D$45>1,OR(U73<>U72,AND(ROW()=5,U72=U73))),VLOOKUP(U73,Drops!$D$26:$E$44,2,FALSE),"") -> C. Organizational Security | R73: =IF(Q73<>"",ROW(),"") -> 73 | S73: =OFFSET(AC73,,L73-1) -> 1 | T73: =IF(OR(V73<>V72,U73<>U72,AND(V73<>V72,W73<>W72),AND(V73<>V72,W73<>W72,X73<>X72),AND(V73<>V72,W73<>W72,X73<>X72,Y73<>Y72),AND(V73<>V72,W73<>W72,X73<>X72,Y73<>Y72,Z73<>Z72),L73-L72>1),1,0) -> 1 | U73: C | V73: 1 | W73: 6 | X73: 0 | Y73: 0 | Z73: 0 | AA73: =IF(ROW()=5,1,IF(OR(AH73=1,P73>0,T73=1),1,IF(OR(AND(AH73=2,AI73=1),AND(AI73=2,AJ73=1),AND(AJ73=2,AK73=1),AND(AK73=2,AL73=1)),1,0))) -> 1 | AB73: =IF(L74>L73,1,0) -> 1 | AC73: =IF(ROW()=5,P73,IF(AND($P73>1,AC$4=$L73),$P73,IF(AND($U73=$U72,V73=V72),AC72,IF(AND($L73=AC$4,P73=1),P73,0)))) -> 1 | AD73: =IF(AC73>1,AC73,IF(AND($P73>1,AD$4=$L73),$P73,IF(AND($U73=$U72,W73=W72),AD72,IF(AND($L73=AD$4,P73=1),P73,0)))) -> 0 | AE73: =IF(AD73>1,AD73,IF(AND($P73>1,AE$4=$L73),$P73,IF(AND($U73=$U72,X73=X72),AE72,IF(AND($L73=AE$4,P73=1),P73,0)))) -> 0 | AF73: =IF(AE73>1,AE73,IF(AND($P73>1,AF$4=$L73),$P73,IF(AND($U73=$U72,Y73=Y72),AF72,IF(AND($L73=AF$4,P73=1),P73,0)))) -> 0 | AG73: =IF(AF73>1,AF73,IF(AND($P73>1,AG$4=$L73),$P73,IF(AND($U73=$U72,Z73=Z72),AG72,IF(AND($L73=AG$4,P73=1),P73,0)))) -> 0 | AH73: =IF(AND($P73=1,$L73=AH$4),2,IF(AND($L73<>AH$4,AH72=2),AH72,IF($L73<>AH$4,0,1))) -> 2 | AI73: =IF(OR(ROW()=5,$U72<>$U73),0,IF(AND($P73=1,$L73=AI$4),2,IF(AND($L73<>AI$4,AI72=2),AI72,IF($L73<>AI$4,0,1)))) -> 0 | AJ73: =IF(OR(ROW()=5,$U72<>$U73),0,IF(AND($P73=1,$L73=AJ$4),2,IF(AND($L73<>AJ$4,AJ72=2),AJ72,IF($L73<>AJ$4,0,1)))) -> 0 | AK73: =IF(OR(ROW()=5,$U72<>$U73),0,IF(AND($P73=1,$L73=AK$4),2,IF(AND($L73<>AK$4,AK72=2),AK72,IF($L73<>AK$4,0,1)))) -> 0 | AL73: =IF(OR(ROW()=5,$U72<>$U73),0,IF(AND($P73=1,$L73=AL$4),2,IF(AND($L73<>AL$4,AL72=2),AL72,IF($L73<>AL$4,0,1)))) -> 0
A74: 4418 | B74: C.1.7 | C74: Do the processes include residual risk acceptance responsibilities? | D74: Yes | G74: Security Organization | H74: Organizational Information Security Responsibilities | J74: 6.1.1 Information Security Roles and Responsibilities | L74: 2 | M74: 3 | P74: =IF($L74="","",IF($D74="Yes",1,IF($D74="No",2,IF($D74="N/A",3,0)))) -> 1 | Q74: =IF(AND(Drops!$D$45>1,OR(U74<>U73,AND(ROW()=5,U73=U74))),VLOOKUP(U74,Drops!$D$26:$E$44,2,FALSE),"") | R74: =IF(Q74<>"",ROW(),"") | S74: =OFFSET(AC74,,L74-1) -> 1 | T74: =IF(OR(V74<>V73,U74<>U73,AND(V74<>V73,W74<>W73),AND(V74<>V73,W74<>W73,X74<>X73),AND(V74<>V73,W74<>W73,X74<>X73,Y74<>Y73),AND(V74<>V73,W74<>W73,X74<>X73,Y74<>Y73,Z74<>Z73),L74-L73>1),1,0) -> 0 | U74: C | V74: 1 | W74: 7 | X74: 0 | Y74: 0 | Z74: 0 | AA74: =IF(ROW()=5,1,IF(OR(AH74=1,P74>0,T74=1),1,IF(OR(AND(AH74=2,AI74=1),AND(AI74=2,AJ74=1),AND(AJ74=2,AK74=1),AND(AK74=2,AL74=1)),1,0))) -> 1 | AB74: =IF(L75>L74,1,0) -> 0 | AC74: =IF(ROW()=5,P74,IF(AND($P74>1,AC$4=$L74),$P74,IF(AND($U74=$U73,V74=V73),AC73,IF(AND($L74=AC$4,P74=1),P74,0)))) -> 1 | AD74: =IF(AC74>1,AC74,IF(AND($P74>1,AD$4=$L74),$P74,IF(AND($U74=$U73,W74=W73),AD73,IF(AND($L74=AD$4,P74=1),P74,0)))) -> 1 | AE74: =IF(AD74>1,AD74,IF(AND($P74>1,AE$4=$L74),$P74,IF(AND($U74=$U73,X74=X73),AE73,IF(AND($L74=AE$4,P74=1),P74,0)))) -> 0 | AF74: =IF(AE74>1,AE74,IF(AND($P74>1,AF$4=$L74),$P74,IF(AND($U74=$U73,Y74=Y73),AF73,IF(AND($L74=AF$4,P74=1),P74,0)))) -> 0 | AG74: =IF(AF74>1,AF74,IF(AND($P74>1,AG$4=$L74),$P74,IF(AND($U74=$U73,Z74=Z73),AG73,IF(AND($L74=AG$4,P74=1),P74,0)))) -> 0 | AH74: =IF(AND($P74=1,$L74=AH$4),2,IF(AND($L74<>AH$4,AH73=2),AH73,IF($L74<>AH$4,0,1))) -> 2 | AI74: =IF(OR(ROW()=5,$U73<>$U74),0,IF(AND($P74=1,$L74=AI$4),2,IF(AND($L74<>AI$4,AI73=2),AI73,IF($L74<>AI$4,0,1)))) -> 2 | AJ74: =IF(OR(ROW()=5,$U73<>$U74),0,IF(AND($P74=1,$L74=AJ$4),2,IF(AND($L74<>AJ$4,AJ73=2),AJ73,IF($L74<>AJ$4,0,1)))) -> 0 | AK74: =IF(OR(ROW()=5,$U73<>$U74),0,IF(AND($P74=1,$L74=AK$4),2,IF(AND($L74<>AK$4,AK73=2),AK73,IF($L74<>AK$4,0,1)))) -> 0 | AL74: =IF(OR(ROW()=5,$U73<>$U74),0,IF(AND($P74=1,$L74=AL$4),2,IF(AND($L74<>AL$4,AL73=2),AL73,IF($L74<>AL$4,0,1)))) -> 0
A75: 4656 | B75: C.2 | C75: Does the organization's executive leadership ensure information security policy is established and aligned with organizational strategy, and communicated to the entire organization? | D75: Yes | E75: Seismic's Information Security Policy is reviewed and approved by the CEO on an annual basis. | G75: Security Organization | H75: Executive Sponsorship | J75: 4.3 Scope of Information Security Management Systems|4.4 Information Security Management System|5.1 Leadership and Commitment|5.1.1 Policies for Information Security|5.2 Policy|6.2 Information Security Objectives and Planning to Achieve Them|8.1 Operational Planning and Control | L75: 1 | M75: 3 | P75: =IF($L75="","",IF($D75="Yes",1,IF($D75="No",2,IF($D75="N/A",3,0)))) -> 1 | Q75: =IF(AND(Drops!$D$45>1,OR(U75<>U74,AND(ROW()=5,U74=U75))),VLOOKUP(U75,Drops!$D$26:$E$44,2,FALSE),"") | R75: =IF(Q75<>"",ROW(),"") | S75: =OFFSET(AC75,,L75-1) -> 1 | T75: =IF(OR(V75<>V74,U75<>U74,AND(V75<>V74,W75<>W74),AND(V75<>V74,W75<>W74,X75<>X74),AND(V75<>V74,W75<>W74,X75<>X74,Y75<>Y74),AND(V75<>V74,W75<>W74,X75<>X74,Y75<>Y74,Z75<>Z74),L75-L74>1),1,0) -> 1 | U75: C | V75: 2 | W75: 0 | X75: 0 | Y75: 0 | Z75: 0 | AA75: =IF(ROW()=5,1,IF(OR(AH75=1,P75>0,T75=1),1,IF(OR(AND(AH75=2,AI75=1),AND(AI75=2,AJ75=1),AND(AJ75=2,AK75=1),AND(AK75=2,AL75=1)),1,0))) -> 1 | AB75: =IF(L76>L75,1,0) -> 1 | AC75: =IF(ROW()=5,P75,IF(AND($P75>1,AC$4=$L75),$P75,IF(AND($U75=$U74,V75=V74),AC74,IF(AND($L75=AC$4,P75=1),P75,0)))) -> 1 | AD75: =IF(AC75>1,AC75,IF(AND($P75>1,AD$4=$L75),$P75,IF(AND($U75=$U74,W75=W74),AD74,IF(AND($L75=AD$4,P75=1),P75,0)))) -> 0 | AE75: =IF(AD75>1,AD75,IF(AND($P75>1,AE$4=$L75),$P75,IF(AND($U75=$U74,X75=X74),AE74,IF(AND($L75=AE$4,P75=1),P75,0)))) -> 0 | AF75: =IF(AE75>1,AE75,IF(AND($P75>1,AF$4=$L75),$P75,IF(AND($U75=$U74,Y75=Y74),AF74,IF(AND($L75=AF$4,P75=1),P75,0)))) -> 0 | AG75: =IF(AF75>1,AF75,IF(AND($P75>1,AG$4=$L75),$P75,IF(AND($U75=$U74,Z75=Z74),AG74,IF(AND($L75=AG$4,P75=1),P75,0)))) -> 0 | AH75: =IF(AND($P75=1,$L75=AH$4),2,IF(AND($L75<>AH$4,AH74=2),AH74,IF($L75<>AH$4,0,1))) -> 2 | AI75: =IF(OR(ROW()=5,$U74<>$U75),0,IF(AND($P75=1,$L75=AI$4),2,IF(AND($L75<>AI$4,AI74=2),AI74,IF($L75<>AI$4,0,1)))) -> 2 | AJ75: =IF(OR(ROW()=5,$U74<>$U75),0,IF(AND($P75=1,$L75=AJ$4),2,IF(AND($L75<>AJ$4,AJ74=2),AJ74,IF($L75<>AJ$4,0,1)))) -> 0 | AK75: =IF(OR(ROW()=5,$U74<>$U75),0,IF(AND($P75=1,$L75=AK$4),2,IF(AND($L75<>AK$4,AK74=2),AK74,IF($L75<>AK$4,0,1)))) -> 0 | AL75: =IF(OR(ROW()=5,$U74<>$U75),0,IF(AND($P75=1,$L75=AL$4),2,IF(AND($L75<>AL$4,AL74=2),AL74,IF($L75<>AL$4,0,1)))) -> 0
A76: 4657 | B76: C.2.1 | C76: Does the organization's executive leadership communicate the mandate of information security awareness, compliance and effectiveness to the entire organization? | D76: Yes | G76: Security Organization | H76: Executive Sponsorship | J76: 4.3 Scope of Information Security Management Systems|5.1 Leadership and Commitment|6.2 Information Security Objectives and Planning to Achieve Them | L76: 2 | M76: 3 | P76: =IF($L76="","",IF($D76="Yes",1,IF($D76="No",2,IF($D76="N/A",3,0)))) -> 1 | Q76: =IF(AND(Drops!$D$45>1,OR(U76<>U75,AND(ROW()=5,U75=U76))),VLOOKUP(U76,Drops!$D$26:$E$44,2,FALSE),"") | R76: =IF(Q76<>"",ROW(),"") | S76: =OFFSET(AC76,,L76-1) -> 1 | T76: =IF(OR(V76<>V75,U76<>U75,AND(V76<>V75,W76<>W75),AND(V76<>V75,W76<>W75,X76<>X75),AND(V76<>V75,W76<>W75,X76<>X75,Y76<>Y75),AND(V76<>V75,W76<>W75,X76<>X75,Y76<>Y75,Z76<>Z75),L76-L75>1),1,0) -> 0 | U76: C | V76: 2 | W76: 1 | X76: 0 | Y76: 0 | Z76: 0 | AA76: =IF(ROW()=5,1,IF(OR(AH76=1,P76>0,T76=1),1,IF(OR(AND(AH76=2,AI76=1),AND(AI76=2,AJ76=1),AND(AJ76=2,AK76=1),AND(AK76=2,AL76=1)),1,0))) -> 1 | AB76: =IF(L77>L76,1,0) -> 0 | AC76: =IF(ROW()=5,P76,IF(AND($P76>1,AC$4=$L76),$P76,IF(AND($U76=$U75,V76=V75),AC75,IF(AND($L76=AC$4,P76=1),P76,0)))) -> 1 | AD76: =IF(AC76>1,AC76,IF(AND($P76>1,AD$4=$L76),$P76,IF(AND($U76=$U75,W76=W75),AD75,IF(AND($L76=AD$4,P76=1),P76,0)))) -> 1 | AE76: =IF(AD76>1,AD76,IF(AND($P76>1,AE$4=$L76),$P76,IF(AND($U76=$U75,X76=X75),AE75,IF(AND($L76=AE$4,P76=1),P76,0)))) -> 0 | AF76: =IF(AE76>1,AE76,IF(AND($P76>1,AF$4=$L76),$P76,IF(AND($U76=$U75,Y76=Y75),AF75,IF(AND($L76=AF$4,P76=1),P76,0)))) -> 0 | AG76: =IF(AF76>1,AF76,IF(AND($P76>1,AG$4=$L76),$P76,IF(AND($U76=$U75,Z76=Z75),AG75,IF(AND($L76=AG$4,P76=1),P76,0)))) -> 0 | AH76: =IF(AND($P76=1,$L76=AH$4),2,IF(AND($L76<>AH$4,AH75=2),AH75,IF($L76<>AH$4,0,1))) -> 2 | AI76: =IF(OR(ROW()=5,$U75<>$U76),0,IF(AND($P76=1,$L76=AI$4),2,IF(AND($L76<>AI$4,AI75=2),AI75,IF($L76<>AI$4,0,1)))) -> 2 | AJ76: =IF(OR(ROW()=5,$U75<>$U76),0,IF(AND($P76=1,$L76=AJ$4),2,IF(AND($L76<>AJ$4,AJ75=2),AJ75,IF($L76<>AJ$4,0,1)))) -> 0 | AK76: =IF(OR(ROW()=5,$U75<>$U76),0,IF(AND($P76=1,$L76=AK$4),2,IF(AND($L76<>AK$4,AK75=2),AK75,IF($L76<>AK$4,0,1)))) -> 0 | AL76: =IF(OR(ROW()=5,$U75<>$U76),0,IF(AND($P76=1,$L76=AL$4),2,IF(AND($L76<>AL$4,AL75=2),AL75,IF($L76<>AL$4,0,1)))) -> 0
A77: 4658 | B77: C.2.2 | C77: Does the organization's board of directors or ownership ensure information security programs are funded sufficiently to meet the organization's objectives? | D77: Yes | G77: Security Organization | H77: Executive Sponsorship | J77: 4.1 Understanding Organization and its Context|4.4 Information Security Management System|5.1 Leadership and Commitment|6.2 Information Security Objectives and Planning to Achieve Them|7.1 Resources | L77: 2 | M77: 3 | P77: =IF($L77="","",IF($D77="Yes",1,IF($D77="No",2,IF($D77="N/A",3,0)))) -> 1 | Q77: =IF(AND(Drops!$D$45>1,OR(U77<>U76,AND(ROW()=5,U76=U77))),VLOOKUP(U77,Drops!$D$26:$E$44,2,FALSE),"") | R77: =IF(Q77<>"",ROW(),"") | S77: =OFFSET(AC77,,L77-1) -> 1 | T77: =IF(OR(V77<>V76,U77<>U76,AND(V77<>V76,W77<>W76),AND(V77<>V76,W77<>W76,X77<>X76),AND(V77<>V76,W77<>W76,X77<>X76,Y77<>Y76),AND(V77<>V76,W77<>W76,X77<>X76,Y77<>Y76,Z77<>Z76),L77-L76>1),1,0) -> 0 | U77: C | V77: 2 | W77: 2 | X77: 0 | Y77: 0 | Z77: 0 | AA77: =IF(ROW()=5,1,IF(OR(AH77=1,P77>0,T77=1),1,IF(OR(AND(AH77=2,AI77=1),AND(AI77=2,AJ77=1),AND(AJ77=2,AK77=1),AND(AK77=2,AL77=1)),1,0))) -> 1 | AB77: =IF(L78>L77,1,0) -> 0 | AC77: =IF(ROW()=5,P77,IF(AND($P77>1,AC$4=$L77),$P77,IF(AND($U77=$U76,V77=V76),AC76,IF(AND($L77=AC$4,P77=1),P77,0)))) -> 1 | AD77: =IF(AC77>1,AC77,IF(AND($P77>1,AD$4=$L77),$P77,IF(AND($U77=$U76,W77=W76),AD76,IF(AND($L77=AD$4,P77=1),P77,0)))) -> 1 | AE77: =IF(AD77>1,AD77,IF(AND($P77>1,AE$4=$L77),$P77,IF(AND($U77=$U76,X77=X76),AE76,IF(AND($L77=AE$4,P77=1),P77,0)))) -> 0 | AF77: =IF(AE77>1,AE77,IF(AND($P77>1,AF$4=$L77),$P77,IF(AND($U77=$U76,Y77=Y76),AF76,IF(AND($L77=AF$4,P77=1),P77,0)))) -> 0 | AG77: =IF(AF77>1,AF77,IF(AND($P77>1,AG$4=$L77),$P77,IF(AND($U77=$U76,Z77=Z76),AG76,IF(AND($L77=AG$4,P77=1),P77,0)))) -> 0 | AH77: =IF(AND($P77=1,$L77=AH$4),2,IF(AND($L77<>AH$4,AH76=2),AH76,IF($L77<>AH$4,0,1))) -> 2 | AI77: =IF(OR(ROW()=5,$U76<>$U77),0,IF(AND($P77=1,$L77=AI$4),2,IF(AND($L77<>AI$4,AI76=2),AI76,IF($L77<>AI$4,0,1)))) -> 2 | AJ77: =IF(OR(ROW()=5,$U76<>$U77),0,IF(AND($P77=1,$L77=AJ$4),2,IF(AND($L77<>AJ$4,AJ76=2),AJ76,IF($L77<>AJ$4,0,1)))) -> 0 | AK77: =IF(OR(ROW()=5,$U76<>$U77),0,IF(AND($P77=1,$L77=AK$4),2,IF(AND($L77<>AK$4,AK76=2),AK76,IF($L77<>AK$4,0,1)))) -> 0 | AL77: =IF(OR(ROW()=5,$U76<>$U77),0,IF(AND($P77=1,$L77=AL$4),2,IF(AND($L77<>AL$4,AL76=2),AL76,IF($L77<>AL$4,0,1)))) -> 0
A78: 4659 | B78: C.2.3 | C78: Does the organization's board of directors or ownership require management to regularly demonstrate that the information security program meets its intended objectives? | D78: Yes | G78: Security Organization | H78: Executive Sponsorship | J78: 10.1 Nonconformity and Corrective Action Plan|18.2.3 Technical Compliance Review|4.1 Understanding Organization and its Context|4.3 Scope of Information Security Management Systems|4.4 Information Security Management System|6.2 Information Security Objectives and Planning to Achieve Them|8.1 Operational Planning and Control|9.1 Monitoring, Measurement, Analysis, and Evaluation|9.3 Management Review | L78: 2 | M78: 3 | P78: =IF($L78="","",IF($D78="Yes",1,IF($D78="No",2,IF($D78="N/A",3,0)))) -> 1 | Q78: =IF(AND(Drops!$D$45>1,OR(U78<>U77,AND(ROW()=5,U77=U78))),VLOOKUP(U78,Drops!$D$26:$E$44,2,FALSE),"") | R78: =IF(Q78<>"",ROW(),"") | S78: =OFFSET(AC78,,L78-1) -> 1 | T78: =IF(OR(V78<>V77,U78<>U77,AND(V78<>V77,W78<>W77),AND(V78<>V77,W78<>W77,X78<>X77),AND(V78<>V77,W78<>W77,X78<>X77,Y78<>Y77),AND(V78<>V77,W78<>W77,X78<>X77,Y78<>Y77,Z78<>Z77),L78-L77>1),1,0) -> 0 | U78: C | V78: 2 | W78: 3 | X78: 0 | Y78: 0 | Z78: 0 | AA78: =IF(ROW()=5,1,IF(OR(AH78=1,P78>0,T78=1),1,IF(OR(AND(AH78=2,AI78=1),AND(AI78=2,AJ78=1),AND(AJ78=2,AK78=1),AND(AK78=2,AL78=1)),1,0))) -> 1 | AB78: =IF(L79>L78,1,0) -> 0 | AC78: =IF(ROW()=5,P78,IF(AND($P78>1,AC$4=$L78),$P78,IF(AND($U78=$U77,V78=V77),AC77,IF(AND($L78=AC$4,P78=1),P78,0)))) -> 1 | AD78: =IF(AC78>1,AC78,IF(AND($P78>1,AD$4=$L78),$P78,IF(AND($U78=$U77,W78=W77),AD77,IF(AND($L78=AD$4,P78=1),P78,0)))) -> 1 | AE78: =IF(AD78>1,AD78,IF(AND($P78>1,AE$4=$L78),$P78,IF(AND($U78=$U77,X78=X77),AE77,IF(AND($L78=AE$4,P78=1),P78,0)))) -> 0 | AF78: =IF(AE78>1,AE78,IF(AND($P78>1,AF$4=$L78),$P78,IF(AND($U78=$U77,Y78=Y77),AF77,IF(AND($L78=AF$4,P78=1),P78,0)))) -> 0 | AG78: =IF(AF78>1,AF78,IF(AND($P78>1,AG$4=$L78),$P78,IF(AND($U78=$U77,Z78=Z77),AG77,IF(AND($L78=AG$4,P78=1),P78,0)))) -> 0 | AH78: =IF(AND($P78=1,$L78=AH$4),2,IF(AND($L78<>AH$4,AH77=2),AH77,IF($L78<>AH$4,0,1))) -> 2 | AI78: =IF(OR(ROW()=5,$U77<>$U78),0,IF(AND($P78=1,$L78=AI$4),2,IF(AND($L78<>AI$4,AI77=2),AI77,IF($L78<>AI$4,0,1)))) -> 2 | AJ78: =IF(OR(ROW()=5,$U77<>$U78),0,IF(AND($P78=1,$L78=AJ$4),2,IF(AND($L78<>AJ$4,AJ77=2),AJ77,IF($L78<>AJ$4,0,1)))) -> 0 | AK78: =IF(OR(ROW()=5,$U77<>$U78),0,IF(AND($P78=1,$L78=AK$4),2,IF(AND($L78<>AK$4,AK77=2),AK77,IF($L78<>AK$4,0,1)))) -> 0 | AL78: =IF(OR(ROW()=5,$U77<>$U78),0,IF(AND($P78=1,$L78=AL$4),2,IF(AND($L78<>AL$4,AL77=2),AL77,IF($L78<>AL$4,0,1)))) -> 0
A79: 4551 | B79: C.3 | C79: Has a qualified individual responsible been designated as a Chief Information Security Officer (CISO) to oversee and implement the organization's cybersecurity program and enforce its cybersecurity policy? | D79: No | E79: Seismic does not have a CISO by title, but the Director of Information Security is assigned the responsibility for Seismic's Information Security Program. | G79: Security Organization | H79: Chief Information Security Officer | J79: 5.3 Organizational Roles, Responsibilities, and Authorities | L79: 1 | M79: 3 | P79: =IF($L79="","",IF($D79="Yes",1,IF($D79="No",2,IF($D79="N/A",3,0)))) -> 2 | Q79: =IF(AND(Drops!$D$45>1,OR(U79<>U78,AND(ROW()=5,U78=U79))),VLOOKUP(U79,Drops!$D$26:$E$44,2,FALSE),"") | R79: =IF(Q79<>"",ROW(),"") | S79: =OFFSET(AC79,,L79-1) -> 2 | T79: =IF(OR(V79<>V78,U79<>U78,AND(V79<>V78,W79<>W78),AND(V79<>V78,W79<>W78,X79<>X78),AND(V79<>V78,W79<>W78,X79<>X78,Y79<>Y78),AND(V79<>V78,W79<>W78,X79<>X78,Y79<>Y78,Z79<>Z78),L79-L78>1),1,0) -> 1 | U79: C | V79: 3 | W79: 0 | X79: 0 | Y79: 0 | Z79: 0 | AA79: =IF(ROW()=5,1,IF(OR(AH79=1,P79>0,T79=1),1,IF(OR(AND(AH79=2,AI79=1),AND(AI79=2,AJ79=1),AND(AJ79=2,AK79=1),AND(AK79=2,AL79=1)),1,0))) -> 1 | AB79: =IF(L80>L79,1,0) -> 1 | AC79: =IF(ROW()=5,P79,IF(AND($P79>1,AC$4=$L79),$P79,IF(AND($U79=$U78,V79=V78),AC78,IF(AND($L79=AC$4,P79=1),P79,0)))) -> 2 | AD79: =IF(AC79>1,AC79,IF(AND($P79>1,AD$4=$L79),$P79,IF(AND($U79=$U78,W79=W78),AD78,IF(AND($L79=AD$4,P79=1),P79,0)))) -> 2 | AE79: =IF(AD79>1,AD79,IF(AND($P79>1,AE$4=$L79),$P79,IF(AND($U79=$U78,X79=X78),AE78,IF(AND($L79=AE$4,P79=1),P79,0)))) -> 2 | AF79: =IF(AE79>1,AE79,IF(AND($P79>1,AF$4=$L79),$P79,IF(AND($U79=$U78,Y79=Y78),AF78,IF(AND($L79=AF$4,P79=1),P79,0)))) -> 2 | AG79: =IF(AF79>1,AF79,IF(AND($P79>1,AG$4=$L79),$P79,IF(AND($U79=$U78,Z79=Z78),AG78,IF(AND($L79=AG$4,P79=1),P79,0)))) -> 2 | AH79: =IF(AND($P79=1,$L79=AH$4),2,IF(AND($L79<>AH$4,AH78=2),AH78,IF($L79<>AH$4,0,1))) -> 1 | AI79: =IF(OR(ROW()=5,$U78<>$U79),0,IF(AND($P79=1,$L79=AI$4),2,IF(AND($L79<>AI$4,AI78=2),AI78,IF($L79<>AI$4,0,1)))) -> 2 | AJ79: =IF(OR(ROW()=5,$U78<>$U79),0,IF(AND($P79=1,$L79=AJ$4),2,IF(AND($L79<>AJ$4,AJ78=2),AJ78,IF($L79<>AJ$4,0,1)))) -> 0 | AK79: =IF(OR(ROW()=5,$U78<>$U79),0,IF(AND($P79=1,$L79=AK$4),2,IF(AND($L79<>AK$4,AK78=2),AK78,IF($L79<>AK$4,0,1)))) -> 0 | AL79: =IF(OR(ROW()=5,$U78<>$U79),0,IF(AND($P79=1,$L79=AL$4),2,IF(AND($L79<>AL$4,AL78=2),AL78,IF($L79<>AL$4,0,1)))) -> 0
A80: 4552 | B80: C.3.1 | C80: Does the CISO issue a report at least annually on the organization's cybersecurity program and material cybersecurity risks to the organization's board of directors, equivalent body, or senior officer in charge of cybersecurity risk? | D80: Yes | E80: The Director of Information Security meets with executives at least annually. | G80: Security Organization | H80: Chief Information Security Officer | L80: 2 | M80: 3 | P80: =IF($L80="","",IF($D80="Yes",1,IF($D80="No",2,IF($D80="N/A",3,0)))) -> 1 | Q80: =IF(AND(Drops!$D$45>1,OR(U80<>U79,AND(ROW()=5,U79=U80))),VLOOKUP(U80,Drops!$D$26:$E$44,2,FALSE),"") | R80: =IF(Q80<>"",ROW(),"") | S80: =OFFSET(AC80,,L80-1) -> 2 | T80: =IF(OR(V80<>V79,U80<>U79,AND(V80<>V79,W80<>W79),AND(V80<>V79,W80<>W79,X80<>X79),AND(V80<>V79,W80<>W79,X80<>X79,Y80<>Y79),AND(V80<>V79,W80<>W79,X80<>X79,Y80<>Y79,Z80<>Z79),L80-L79>1),1,0) -> 0 | U80: C | V80: 3 | W80: 1 | X80: 0 | Y80: 0 | Z80: 0 | AA80: =IF(ROW()=5,1,IF(OR(AH80=1,P80>0,T80=1),1,IF(OR(AND(AH80=2,AI80=1),AND(AI80=2,AJ80=1),AND(AJ80=2,AK80=1),AND(AK80=2,AL80=1)),1,0))) -> 1 | AB80: =IF(L81>L80,1,0) -> 0 | AC80: =IF(ROW()=5,P80,IF(AND($P80>1,AC$4=$L80),$P80,IF(AND($U80=$U79,V80=V79),AC79,IF(AND($L80=AC$4,P80=1),P80,0)))) -> 2 | AD80: =IF(AC80>1,AC80,IF(AND($P80>1,AD$4=$L80),$P80,IF(AND($U80=$U79,W80=W79),AD79,IF(AND($L80=AD$4,P80=1),P80,0)))) -> 2 | AE80: =IF(AD80>1,AD80,IF(AND($P80>1,AE$4=$L80),$P80,IF(AND($U80=$U79,X80=X79),AE79,IF(AND($L80=AE$4,P80=1),P80,0)))) -> 2 | AF80: =IF(AE80>1,AE80,IF(AND($P80>1,AF$4=$L80),$P80,IF(AND($U80=$U79,Y80=Y79),AF79,IF(AND($L80=AF$4,P80=1),P80,0)))) -> 2 | AG80: =IF(AF80>1,AF80,IF(AND($P80>1,AG$4=$L80),$P80,IF(AND($U80=$U79,Z80=Z79),AG79,IF(AND($L80=AG$4,P80=1),P80,0)))) -> 2 | AH80: =IF(AND($P80=1,$L80=AH$4),2,IF(AND($L80<>AH$4,AH79=2),AH79,IF($L80<>AH$4,0,1))) -> 0 | AI80: =IF(OR(ROW()=5,$U79<>$U80),0,IF(AND($P80=1,$L80=AI$4),2,IF(AND($L80<>AI$4,AI79=2),AI79,IF($L80<>AI$4,0,1)))) -> 2 | AJ80: =IF(OR(ROW()=5,$U79<>$U80),0,IF(AND($P80=1,$L80=AJ$4),2,IF(AND($L80<>AJ$4,AJ79=2),AJ79,IF($L80<>AJ$4,0,1)))) -> 0 | AK80: =IF(OR(ROW()=5,$U79<>$U80),0,IF(AND($P80=1,$L80=AK$4),2,IF(AND($L80<>AK$4,AK79=2),AK79,IF($L80<>AK$4,0,1)))) -> 0 | AL80: =IF(OR(ROW()=5,$U79<>$U80),0,IF(AND($P80=1,$L80=AL$4),2,IF(AND($L80<>AL$4,AL79=2),AL79,IF($L80<>AL$4,0,1)))) -> 0
A81: 58 | B81: C.4 | C81: Are information security personnel (internal or outsourced) responsible for information security processes? | D81: Yes | E81: Seismic has an internal Information Security Team. | G81: Security Organization | H81: Information Security Personnel Responsibilities | J81: 10.1 Nonconformity and Corrective Action Plan|10.2 Continual Improvement|4.1 Understanding Organization and its Context|4.3 Scope of Information Security Management Systems|4.4 Information Security Management System|7.1 Resources|8.1 Operational Planning and Control|9.1 Monitoring, Measurement, Analysis, and Evaluation | L81: 1 | M81: 2 | P81: =IF($L81="","",IF($D81="Yes",1,IF($D81="No",2,IF($D81="N/A",3,0)))) -> 1 | Q81: =IF(AND(Drops!$D$45>1,OR(U81<>U80,AND(ROW()=5,U80=U81))),VLOOKUP(U81,Drops!$D$26:$E$44,2,FALSE),"") | R81: =IF(Q81<>"",ROW(),"") | S81: =OFFSET(AC81,,L81-1) -> 1 | T81: =IF(OR(V81<>V80,U81<>U80,AND(V81<>V80,W81<>W80),AND(V81<>V80,W81<>W80,X81<>X80),AND(V81<>V80,W81<>W80,X81<>X80,Y81<>Y80),AND(V81<>V80,W81<>W80,X81<>X80,Y81<>Y80,Z81<>Z80),L81-L80>1),1,0) -> 1 | U81: C | V81: 4 | W81: 0 | X81: 0 | Y81: 0 | Z81: 0 | AA81: =IF(ROW()=5,1,IF(OR(AH81=1,P81>0,T81=1),1,IF(OR(AND(AH81=2,AI81=1),AND(AI81=2,AJ81=1),AND(AJ81=2,AK81=1),AND(AK81=2,AL81=1)),1,0))) -> 1 | AB81: =IF(L82>L81,1,0) -> 1 | AC81: =IF(ROW()=5,P81,IF(AND($P81>1,AC$4=$L81),$P81,IF(AND($U81=$U80,V81=V80),AC80,IF(AND($L81=AC$4,P81=1),P81,0)))) -> 1 | AD81: =IF(AC81>1,AC81,IF(AND($P81>1,AD$4=$L81),$P81,IF(AND($U81=$U80,W81=W80),AD80,IF(AND($L81=AD$4,P81=1),P81,0)))) -> 0 | AE81: =IF(AD81>1,AD81,IF(AND($P81>1,AE$4=$L81),$P81,IF(AND($U81=$U80,X81=X80),AE80,IF(AND($L81=AE$4,P81=1),P81,0)))) -> 2 | AF81: =IF(AE81>1,AE81,IF(AND($P81>1,AF$4=$L81),$P81,IF(AND($U81=$U80,Y81=Y80),AF80,IF(AND($L81=AF$4,P81=1),P81,0)))) -> 2 | AG81: =IF(AF81>1,AF81,IF(AND($P81>1,AG$4=$L81),$P81,IF(AND($U81=$U80,Z81=Z80),AG80,IF(AND($L81=AG$4,P81=1),P81,0)))) -> 2 | AH81: =IF(AND($P81=1,$L81=AH$4),2,IF(AND($L81<>AH$4,AH80=2),AH80,IF($L81<>AH$4,0,1))) -> 2 | AI81: =IF(OR(ROW()=5,$U80<>$U81),0,IF(AND($P81=1,$L81=AI$4),2,IF(AND($L81<>AI$4,AI80=2),AI80,IF($L81<>AI$4,0,1)))) -> 2 | AJ81: =IF(OR(ROW()=5,$U80<>$U81),0,IF(AND($P81=1,$L81=AJ$4),2,IF(AND($L81<>AJ$4,AJ80=2),AJ80,IF($L81<>AJ$4,0,1)))) -> 0 | AK81: =IF(OR(ROW()=5,$U80<>$U81),0,IF(AND($P81=1,$L81=AK$4),2,IF(AND($L81<>AK$4,AK80=2),AK80,IF($L81<>AK$4,0,1)))) -> 0 | AL81: =IF(OR(ROW()=5,$U80<>$U81),0,IF(AND($P81=1,$L81=AL$4),2,IF(AND($L81<>AL$4,AL80=2),AL80,IF($L81<>AL$4,0,1)))) -> 0
